Workbook

Sheet Cover
B2: Integrated FP&A Planning & Forecast Model
B3: Rukmini KS — Illustrative IT Services Company (For demonstration)
B5: Prepared by: | C5: Rukmini KS
B6: Model date: | C6: 46285
B7: Portfolio Project | C7: 3-Year Driver-Based Financial Model
B8: Currency | C8: ₹ million unless otherwise stated
B9: Historical Period | C9: Jan-2025 to Dec-2026
B10: Forecast Period | C10: Jan-2027 to Dec-2027
B11: Model Purpose | C11: Revenue, headcount, opex, P&L, variance and scenario planning
B12: Model Logic | C12: Billable HC × utilization × working hours × billing rate
B13: Budget Logic | C13: Independent headcount, utilization, rate and cost assumptions
B14: Model Checks | C14: Reconciliations included on the Checks sheet
B15: Portfolio Note | C15: All data is fictional and created for demonstration purposes.
B17: How to use | C17: Select Base, Upside or Downside in Assumptions!B3. All forecast schedules, P&L and Executive Summary update automatically.

Sheet Assumptions
A1: Model Assumptions & Controls
A3: Active Scenario | B3: Base | C3: Select Base / Upside / Downside
A5: Active Scenario Drivers | B5: Value | C5: Unit | D5: Source / Note
A6: Utilization Change | B6: =INDEX(Scenarios!$B$4:$B$6,MATCH($B$3,Scenarios!$A$4:$A$6,0)) -> 0 | C6: percentage points | D6: Selected from Scenarios
A7: Billing Rate Growth | B7: =INDEX(Scenarios!$C$4:$C$6,MATCH($B$3,Scenarios!$A$4:$A$6,0)) -> 0.05 | C7: % | D7: Selected from Scenarios
A8: Salary Inflation | B8: =INDEX(Scenarios!$D$4:$D$6,MATCH($B$3,Scenarios!$A$4:$A$6,0)) -> 0.06 | C8: % | D8: Selected from Scenarios
A9: Other Opex Growth | B9: =INDEX(Scenarios!$E$4:$E$6,MATCH($B$3,Scenarios!$A$4:$A$6,0)) -> 0.05 | C9: % | D9: Selected from Scenarios
A10: Annual HC Growth | B10: =INDEX(Scenarios!$F$4:$F$6,MATCH($B$3,Scenarios!$A$4:$A$6,0)) -> 0.04 | C10: % | D10: Selected from Scenarios
A12: Business Unit | B12: Opening HC | C12: Billable % | D12: Base Utilization | E12: Billing Rate (₹/hr) | F12: Avg Monthly Salary (₹m) | G12: Software / HC (₹m)
A13: Cloud Services | B13: 145 | C13: 0.82 | D13: 0.78 | E13: 2250 | F13: 0.115 | G13: 0.01
A14: Data & Analytics | B14: 125 | C14: 0.84 | D14: 0.8 | E14: 2400 | F14: 0.12 | G14: 0.011
A15: Cybersecurity | B15: 95 | C15: 0.86 | D15: 0.82 | E15: 2600 | F15: 0.13 | G15: 0.012
A16: Application Development | B16: 180 | C16: 0.8 | D16: 0.76 | E16: 2100 | F16: 0.105 | G16: 0.009
A17: Managed Services | B17: 155 | C17: 0.78 | D17: 0.74 | E17: 1950 | F17: 0.1 | G17: 0.008
A18: TOTAL / AVG | B18: =SUM(B13:B17) -> 700
A20: Forecast Model Inputs | B20: Value
A21: Working Hours / Month | B21: 160
A22: Annual Attrition Rate | B22: 0.1
A23: Subcontractor Cost % Revenue | B23: 0.075
A24: Facilities Cost / HC (₹m) | B24: 0.006
A25: Travel + Marketing + Other Opex % Revenue | B25: 0.045
A27: Independent 2027 Budget Inputs | B27: Value
A28: Annual HC Growth | B28: 0.02
A29: Annual Attrition Rate | B29: 0.1
A30: Utilization Change | B30: -0.01
A31: Billing Rate Growth | B31: 0.03
A32: Salary Inflation | B32: 0.05
A33: Other Opex Growth | B33: 0.04
A34: Subcontractor Cost % Revenue | B34: 0.075
A35: Facilities Cost / HC (₹m) | B35: 0.006
A36: Other Opex % Revenue | B36: 0.045

Sheet Actuals
A1: Historical Actuals by Business Unit (₹m unless stated)
A3: Month | B3: Fiscal Year | C3: Quarter | D3: Business Unit | E3: Total HC | F3: Billable HC | G3: Utilization % | H3: Billing Rate (₹/hr) | I3: Revenue (₹m) | J3: Personnel Cost (₹m) | K3: Subcontractor Cost (₹m) | L3: Software Cost (₹m) | M3: Facilities Cost (₹m) | N3: Travel Cost (₹m) | O3: Marketing Cost (₹m) | P3: Other Opex (₹m) | Q3: Total Cost (₹m) | R3: Gross Profit (₹m) | S3: Gross Margin % | T3: EBITDA (₹m) | U3: EBITDA Margin %
A4: 45658 | B4: 2025 | C4: Q1 | D4: Cloud Services | E4: 120 | F4: 98 | G4: 0.75718132 | H4: 2050 | I4: 24.338836 | J4: 12.6 | K4: 1.5820244 | L4: 1.08 | M4: 0.66 | N4: 0.29206604 | O4: 0.19471069 | P4: 0.38942138 | Q4: 16.798222 | R4: 10.156812 | S4: 0.41730886 | T4: 7.540614 | U4: 0.30981818
A5: 45658 | B5: 2025 | C5: Q1 | D5: Data & Analytics | E5: 102 | F5: 85 | G5: 0.77441359 | H5: 2200 | I5: 23.170455 | J5: 11.22 | K5: 1.5987614 | L5: 1.02 | M5: 0.561 | N5: 0.27804545 | O5: 0.18536364 | P5: 0.37072727 | Q5: 15.233898 | R5: 10.351693 | S5: 0.44676263 | T5: 7.9365568 | U5: 0.34252918
A6: 45658 | B6: 2025 | C6: Q1 | D6: Cybersecurity | E6: 76 | F6: 65 | G6: 0.80241495 | H6: 2400 | I6: 20.028277 | J6: 9.12 | K6: 1.4620642 | L6: 0.836 | M6: 0.418 | N6: 0.24033933 | O6: 0.16022622 | P6: 0.32045244 | Q6: 12.557082 | R6: 9.446213 | S6: 0.47164381 | T6: 7.471195 | U6: 0.37303233
A7: 45658 | B7: 2025 | C7: Q1 | D7: Application Development | E7: 155 | F7: 122 | G7: 0.73315898 | H7: 1950 | I7: 27.906963 | J7: 14.88 | K7: 2.1488362 | L7: 1.24 | M7: 0.8525 | N7: 0.33488356 | O7: 0.22325571 | P7: 0.44651141 | Q7: 20.125987 | R7: 10.878127 | S7: 0.38979975 | T7: 7.7809766 | U7: 0.27881846
A8: 45658 | B8: 2025 | C8: Q1 | D8: Managed Services | E8: 132 | F8: 102 | G8: 0.72057411 | H8: 1800 | I8: 21.167585 | J8: 12.144 | K8: 1.7145744 | L8: 0.924 | M8: 0.726 | N8: 0.25401102 | O8: 0.16934068 | P8: 0.33868136 | Q8: 16.270607 | R8: 7.3090107 | S8: 0.34529261 | T8: 4.8969777 | U8: 0.23134324
A9: 45689 | B9: 2025 | C9: Q1 | D9: Cloud Services | E9: 121 | F9: 99 | G9: 0.75935102 | H9: 2054.1 | I9: 24.706962 | J9: 12.705 | K9: 1.6059525 | L9: 1.089 | M9: 0.6655 | N9: 0.37060443 | O9: 0.19765569 | P9: 0.39531139 | Q9: 17.029024 | R9: 10.396009 | S9: 0.42077247 | T9: 7.6779377 | U9: 0.31076009
A10: 45689 | B10: 2025 | C10: Q1 | D10: Data & Analytics | E10: 103 | F10: 85 | G10: 0.77442798 | H10: 2204.4 | I10: 23.217227 | J10: 11.33 | K10: 1.6019887 | L10: 1.03 | M10: 0.5665 | N10: 0.34825841 | O10: 0.18573782 | P10: 0.37147563 | Q10: 15.433961 | R10: 10.285238 | S10: 0.44300029 | T10: 7.7832665 | U10: 0.3352367
A11: 45689 | B11: 2025 | C11: Q1 | D11: Cybersecurity | E11: 77 | F11: 65 | G11: 0.80161897 | H11: 2404.8 | I11: 20.048426 | J11: 9.24 | K11: 1.4635351 | L11: 0.847 | M11: 0.4235 | N11: 0.3007264 | O11: 0.16038741 | P11: 0.32077482 | Q11: 12.755924 | R11: 9.3448912 | S11: 0.46611595 | T11: 7.2925026 | U11: 0.36374439
A12: 45689 | B12: 2025 | C12: Q1 | D12: Application Development | E12: 157 | F12: 124 | G12: 0.73409993 | H12: 1953.9 | I12: 28.45766 | J12: 15.072 | K12: 2.1912398 | L12: 1.256 | M12: 0.8635 | N12: 0.4268649 | O12: 0.22766128 | P12: 0.45532256 | Q12: 20.492589 | R12: 11.19442 | S12: 0.39337107 | T12: 7.9650713 | U12: 0.279892
A13: 45689 | B13: 2025 | C13: Q1 | D13: Managed Services | E13: 134 | F13: 103 | G13: 0.72043833 | H13: 1803.6 | I13: 21.413825 | J13: 12.328 | K13: 1.7345198 | L13: 0.938 | M13: 0.737 | N13: 0.32120737 | O13: 0.1713106 | P13: 0.3426212 | Q13: 16.572659 | R13: 7.351305 | S13: 0.34329715 | T13: 4.8411658 | U13: 0.22607665
A14: 45717 | B14: 2025 | C14: Q1 | D14: Cloud Services | E14: 122 | F14: 100 | G14: 0.75611769 | H14: 2058.2 | I14: 24.899863 | J14: 12.81 | K14: 1.6184911 | L14: 1.098 | M14: 0.671 | N14: 0.37349794 | O14: 0.1991989 | P14: 0.3983978 | Q14: 17.168586 | R14: 10.471372 | S14: 0.42053933 | T14: 7.731277 | U14: 0.31049477
A15: 45717 | B15: 2025 | C15: Q1 | D15: Data & Analytics | E15: 104 | F15: 86 | G15: 0.77645141 | H15: 2208.8 | I15: 23.598756 | J15: 11.44 | K15: 1.6283142 | L15: 1.04 | M15: 0.572 | N15: 0.35398134 | O15: 0.18879005 | P15: 0.3775801 | Q15: 15.600666 | R15: 10.530442 | S15: 0.44622868 | T15: 7.9980903 | U15: 0.33892
... A123: 46357 | B123: 2026 | C123: Q4 | D123: Managed Services | E123: 167 | F123: 129 | G123: 0.73426597 | H123: 1922.382 | I123: 29.134179 | J123: 16.28584 | K123: 2.3598685 | L123: 1.22745 | M123: 0.9185 | N123: 0.34961015 | O123: 0.23307343 | P123: 0.46614687 | Q123: 21.840489 | R123: 10.488471 | S123: 0.3600057 | T123: 7.2936901 | U123: 0.25034823

Sheet Revenue Forecast
A1: 2027 Driver-Based Revenue Forecast
A2: Case Selected: | B2: =Assumptions!B3 -> Base
A3: Month | B3: Business Unit | C3: Billable HC | D3: Base Utilization | E3: Scenario Utilization | F3: Working Hours | G3: Base Billing Rate (₹/hr) | H3: Scenario Billing Rate (₹/hr) | I3: Revenue Forecast (₹m) | J3: Revenue Driver
A4: 46388 | B4: Cloud Services | C4: ='Headcount Plan'!I4 -> 119.09817 | D4: =Assumptions!D13 -> 0.78 | E4: =MAX(0,MIN(0.95,D4+Assumptions!$B$6)) -> 0.78 | F4: =Assumptions!$B$21 -> 160 | G4: =Assumptions!E13 -> 2250 | H4: =G4*(1+Assumptions!$B$7) -> 2362.5 | I4: =C4*E4*F4*H4/1000000 -> 35.114903 | J4: Billable HC × utilization × hours × rate
A5: 46388 | B5: Data & Analytics | C5: ='Headcount Plan'!I5 -> 105.175 | D5: =Assumptions!D14 -> 0.8 | E5: =MAX(0,MIN(0.95,D5+Assumptions!$B$6)) -> 0.8 | F5: =Assumptions!$B$21 -> 160 | G5: =Assumptions!E14 -> 2400 | H5: =G5*(1+Assumptions!$B$7) -> 2520 | I5: =C5*E5*F5*H5/1000000 -> 33.925248 | J5: Billable HC × utilization × hours × rate
A6: 46388 | B6: Cybersecurity | C6: ='Headcount Plan'!I6 -> 81.836167 | D6: =Assumptions!D15 -> 0.82 | E6: =MAX(0,MIN(0.95,D6+Assumptions!$B$6)) -> 0.82 | F6: =Assumptions!$B$21 -> 160 | G6: =Assumptions!E15 -> 2600 | H6: =G6*(1+Assumptions!$B$7) -> 2730 | I6: =C6*E6*F6*H6/1000000 -> 29.311751 | J6: Billable HC × utilization × hours × rate
A7: 46388 | B7: Application Development | C7: ='Headcount Plan'!I7 -> 144.24 | D7: =Assumptions!D16 -> 0.76 | E7: =MAX(0,MIN(0.95,D7+Assumptions!$B$6)) -> 0.76 | F7: =Assumptions!$B$21 -> 160 | G7: =Assumptions!E16 -> 2100 | H7: =G7*(1+Assumptions!$B$7) -> 2205 | I7: =C7*E7*F7*H7/1000000 -> 38.674783 | J7: Billable HC × utilization × hours × rate
A8: 46388 | B8: Managed Services | C8: ='Headcount Plan'!I8 -> 121.1015 | D8: =Assumptions!D17 -> 0.74 | E8: =MAX(0,MIN(0.95,D8+Assumptions!$B$6)) -> 0.74 | F8: =Assumptions!$B$21 -> 160 | G8: =Assumptions!E17 -> 1950 | H8: =G8*(1+Assumptions!$B$7) -> 2047.5 | I8: =C8*E8*F8*H8/1000000 -> 29.35791 | J8: Billable HC × utilization × hours × rate
A9: 46419 | B9: Cloud Services | C9: ='Headcount Plan'!I9 -> 119.49516 | D9: =Assumptions!D13 -> 0.78 | E9: =MAX(0,MIN(0.95,D9+Assumptions!$B$6)) -> 0.78 | F9: =Assumptions!$B$21 -> 160 | G9: =Assumptions!E13 -> 2250 | H9: =G9*(1+Assumptions!$B$7) -> 2362.5 | I9: =C9*E9*F9*H9/1000000 -> 35.231953 | J9: Billable HC × utilization × hours × rate
A10: 46419 | B10: Data & Analytics | C10: ='Headcount Plan'!I10 -> 105.52558 | D10: =Assumptions!D14 -> 0.8 | E10: =MAX(0,MIN(0.95,D10+Assumptions!$B$6)) -> 0.8 | F10: =Assumptions!$B$21 -> 160 | G10: =Assumptions!E14 -> 2400 | H10: =G10*(1+Assumptions!$B$7) -> 2520 | I10: =C10*E10*F10*H10/1000000 -> 34.038332 | J10: Billable HC × utilization × hours × rate
A11: 46419 | B11: Cybersecurity | C11: ='Headcount Plan'!I11 -> 82.108954 | D11: =Assumptions!D15 -> 0.82 | E11: =MAX(0,MIN(0.95,D11+Assumptions!$B$6)) -> 0.82 | F11: =Assumptions!$B$21 -> 160 | G11: =Assumptions!E15 -> 2600 | H11: =G11*(1+Assumptions!$B$7) -> 2730 | I11: =C11*E11*F11*H11/1000000 -> 29.409457 | J11: Billable HC × utilization × hours × rate
A12: 46419 | B12: Application Development | C12: ='Headcount Plan'!I12 -> 144.7208 | D12: =Assumptions!D16 -> 0.76 | E12: =MAX(0,MIN(0.95,D12+Assumptions!$B$6)) -> 0.76 | F12: =Assumptions!$B$21 -> 160 | G12: =Assumptions!E16 -> 2100 | H12: =G12*(1+Assumptions!$B$7) -> 2205 | I12: =C12*E12*F12*H12/1000000 -> 38.803699 | J12: Billable HC × utilization × hours × rate
A13: 46419 | B13: Managed Services | C13: ='Headcount Plan'!I13 -> 121.50517 | D13: =Assumptions!D17 -> 0.74 | E13: =MAX(0,MIN(0.95,D13+Assumptions!$B$6)) -> 0.74 | F13: =Assumptions!$B$21 -> 160 | G13: =Assumptions!E17 -> 1950 | H13: =G13*(1+Assumptions!$B$7) -> 2047.5 | I13: =C13*E13*F13*H13/1000000 -> 29.45577 | J13: Billable HC × utilization × hours × rate
A14: 46447 | B14: Cloud Services | C14: ='Headcount Plan'!I14 -> 119.89348 | D14: =Assumptions!D13 -> 0.78 | E14: =MAX(0,MIN(0.95,D14+Assumptions!$B$6)) -> 0.78 | F14: =Assumptions!$B$21 -> 160 | G14: =Assumptions!E13 -> 2250 | H14: =G14*(1+Assumptions!$B$7) -> 2362.5 | I14: =C14*E14*F14*H14/1000000 -> 35.349393 | J14: Billable HC × utilization × hours × rate
A15: 46447 | B15: Data & Analytics | C15: ='Headcount Plan'!I15 -> 105.87734 | D15: =Assumptions!D14 -> 0.8 | E15: =MAX(0,MIN(0.95,D15+Assumptions!$B$6)) -> 0.8 | F15: =Assumptions!$B$21 -> 160 | G15: =Assumptions!E14 -> 2400 | H15: =G15*(1+Assumptions!$B$7) -> 2520 | I15: =C15*E15*F15*H15/1000000 -> 34.151793 | J15: Billable HC × utilization × hours × rate
A16: 46447 | B16: Cybersecurity | C16: ='Headcount Plan'!I16 -> 82.38265 | D16: =Assumptions!D15 -> 0.82 | E16: =MAX(0,MIN(0.95,D16+Assumptions!$B$6)) -> 0.82 | F16: =Assumptions!$B$21 -> 160 | G16: =Assumptions!E15 -> 2600 | H16: =G16*(1+Assumptions!$B$7) -> 2730 | I16: =C16*E16*F16*H16/1000000 -> 29.507488 | J16: Billable HC × utilization × hours × rate
A17: 46447 | B17: Application Development | C17: ='Headcount Plan'!I17 -> 145.2032 | D17: =Assumptions!D16 -> 0.76 | E17: =MAX(0,MIN(0.95,D17+Assumptions!$B$6)) -> 0.76 | F17: =Assumptions!$B$21 -> 160 | G17: =Assumptions!E16 -> 2100 | H17: =G17*(1+Assumptions!$B$7) -> 2205 | I17: =C17*E17*F17*H17/1000000 -> 38.933044 | J17: Billable HC × utilization × hours × rate
A18: 46447 | B18: Managed Services | C18: ='Headcount Plan'!I18 -> 121.91019 | D18: =Assumptions!D17 -> 0.74 | E18: =MAX(0,MIN(0.95,D18+Assumptions!$B$6)) -> 0.74 | F18: =Assumptions!$B$21 -> 160 | G18: =Assumptions!E17 -> 1950 | H18: =G18*(1+Assumptions!$B$7) -> 2047.5 | I18: =C18*E18*F18*H18/1000000 -> 29.553956 | J18: Billable HC × utilization × hours × rate
A19: 46478 | B19: Cloud Services | C19: ='Headcount Plan'!I19 -> 120.29312 | D19: =Assumptions!D13 -> 0.78 | E19: =MAX(0,MIN(0.95,D19+Assumptions!$B$6)) -> 0.78 | F19: =Assumptions!$B$21 -> 160 | G19: =Assumptions!E13 -> 2250 | H19: =G19*(1+Assumptions!$B$7) -> 2362.5 | I19: =C19*E19*F19*H19/1000000 -> 35.467224 | J19: Billable HC × utilization × hours × rate
A20: 46478 | B20: Data & Analytics | C20: ='Headcount Plan'!I20 -> 106.23026 | D20: =Assumptions!D14 -> 0.8 | E20: =MAX(0,MIN(0.95,D20+Assumptions!$B$6)) -> 0.8 | F20: =Assumptions!$B$21 -> 160 | G20: =Assumptions!E14 -> 2400 | H20: =G20*(1+Assumptions!$B$7) -> 2520 | I20: =C20*E20*F20*H20/1000000 -> 34.265633 | J20: Billable HC × utilization × hours × rate
A21: 46478 | B21: Cybersecurity | C21: ='Headcount Plan'!I21 -> 82.657259 | D21: =Assumptions!D15 -> 0.82 | E21: =MAX(0,MIN(0.95,D21+Assumptions!$B$6)) -> 0.82 | F21: =Assumptions!$B$21 -> 160 | G21: =Assumptions!E15 -> 2600 | H21: =G21*(1+Assumptions!$B$7) -> 2730 | I21: =C21*E21*F21*H21/1000000 -> 29.605846 | J21: Billable HC × utilization × hours × rate
A22: 46478 | B22: Application Development | C22: ='Headcount Plan'!I22 -> 145.68721 | D22: =Assumptions!D16 -> 0.76 | E22: =MAX(0,MIN(0.95,D22+Assumptions!$B$6)) -> 0.76 | F22: =Assumptions!$B$21 -> 160 | G22: =Assumptions!E16 -> 2100 | H22: =G22*(1+Assumptions!$B$7) -> 2205 | I22: =C22*E22*F22*H22/1000000 -> 39.062821 | J22: Billable HC × utilization × hours × rate
A23: 46478 | B23: Managed Services | C23: ='Headcount Plan'!I23 -> 122.31656 | D23: =Assumptions!D17 -> 0.74 | E23: =MAX(0,MIN(0.95,D23+Assumptions!$B$6)) -> 0.74 | F23: =Assumptions!$B$21 -> 160 | G23: =Assumptions!E17 -> 1950 | H23: =G23*(1+Assumptions!$B$7) -> 2047.5 | I23: =C23*E23*F23*H23/1000000 -> 29.652469 | J23: Billable HC × utilization × hours × rate
A24: 46508 | B24: Cloud Services | C24: ='Headcount Plan'!I24 -> 120.6941 | D24: =Assumptions!D13 -> 0.78 | E24: =MAX(0,MIN(0.95,D24+Assumptions!$B$6)) -> 0.78 | F24: =Assumptions!$B$21 -> 160 | G24: =Assumptions!E13 -> 2250 | H24: =G24*(1+Assumptions!$B$7) -> 2362.5 | I24: =C24*E24*F24*H24/1000000 -> 35.585448 | J24: Billable HC × utilization × hours × rate
A25: 46508 | B25: Data & Analytics | C25: ='Headcount Plan'!I25 -> 106.58436 | D25: =Assumptions!D14 -> 0.8 | E25: =MAX(0,MIN(0.95,D25+Assumptions!$B$6)) -> 0.8 | F25: =Assumptions!$B$21 -> 160 | G25: =Assumptions!E14 -> 2400 | H25: =G25*(1+Assumptions!$B$7) -> 2520 | I25: =C25*E25*F25*H25/1000000 -> 34.379851 | J25: Billable HC × utilization × hours × rate
A26: 46508 | B26: Cybersecurity | C26: ='Headcount Plan'!I26 -> 82.932783 | D26: =Assumptions!D15 -> 0.82 | E26: =MAX(0,MIN(0.95,D26+Assumptions!$B$6)) -> 0.82 | F26: =Assumptions!$B$21 -> 160 | G26: =Assumptions!E15 -> 2600 | H26: =G26*(1+Assumptions!$B$7) -> 2730 | I26: =C26*E26*F26*H26/1000000 -> 29.704533 | J26: Billable HC × utilization × hours × rate
A27: 46508 | B27: Application Development | C27: ='Headcount Plan'!I27 -> 146.17284 | D27: =Assumptions!D16 -> 0.76 | E27: =MAX(0,MIN(0.95,D27+Assumptions!$B$6)) -> 0.76 | F27: =Assumptions!$B$21 -> 160 | G27: =Assumptions!E16 -> 2100 | H27: =G27*(1+Assumptions!$B$7) -> 2205 | I27: =C27*E27*F27*H27/1000000 -> 39.193031 | J27: Billable HC × utilization × hours × rate
A28: 46508 | B28: Managed Services | C28: ='Headcount Plan'!I28 -> 122.72428 | D28: =Assumptions!D17 -> 0.74 | E28: =MAX(0,MIN(0.95,D28+Assumptions!$B$6)) -> 0.74 | F28: =Assumptions!$B$21 -> 160 | G28: =Assumptions!E17 -> 1950 | H28: =G28*(1+Assumptions!$B$7) -> 2047.5 | I28: =C28*E28*F28*H28/1000000 -> 29.75131 | J28: Billable HC × utilization × hours × rate
A29: 46539 | B29: Cloud Services | C29: ='Headcount Plan'!I29 -> 121.09641 | D29: =Assumptions!D13 -> 0.78 | E29: =MAX(0,MIN(0.95,D29+Assumptions!$B$6)) -> 0.78 | F29: =Assumptions!$B$21 -> 160 | G29: =Assumptions!E13 -> 2250 | H29: =G29*(1+Assumptions!$B$7) -> 2362.5 | I29: =C29*E29*F29*H29/1000000 -> 35.704067 | J29: Billable HC × utilization × hours × rate
A30: 46539 | B30: Data & Analytics | C30: ='Headcount Plan'!I30 -> 106.93964 | D30: =Assumptions!D14 -> 0.8 | E30: =MAX(0,MIN(0.95,D30+Assumptions!$B$6)) -> 0.8 | F30: =Assumptions!$B$21 -> 160 | G30: =Assumptions!E14 -> 2400 | H30: =G30*(1+Assumptions!$B$7) -> 2520 | I30: =C30*E30*F30*H30/1000000 -> 34.494451 | J30: Billable HC × utilization × hours × rate
A31: 46539 | B31: Cybersecurity | C31: ='Headcount Plan'!I31 -> 83.209226 | D31: =Assumptions!D15 -> 0.82 | E31: =MAX(0,MIN(0.95,D31+Assumptions!$B$6)) -> 0.82 | F31: =Assumptions!$B$21 -> 160 | G31: =Assumptions!E15 -> 2600 | H31: =G31*(1+Assumptions!$B$7) -> 2730 | I31: =C31*E31*F31*H31/1000000 -> 29.803548 | J31: Billable HC × utilization × hours × rate
A32: 46539 | B32: Application Development | C32: ='Headcount Plan'!I32 -> 146.66008 | D32: =Assumptions!D16 -> 0.76 | E32: =MAX(0,MIN(0.95,D32+Assumptions!$B$6)) -> 0.76 | F32: =Assumptions!$B$21 -> 160 | G32: =Assumptions!E16 -> 2100 | H32: =G32*(1+Assumptions!$B$7) -> 2205 | I32: =C32*E32*F32*H32/1000000 -> 39.323674 | J32: Billable HC × utilization × hours × rate
A33: 46539 | B33: Managed Services | C33: ='Headcount Plan'!I33 -> 123.13336 | D33: =Assumptions!D17 -> 0.74 | E33: =MAX(0,MIN(0.95,D33+Assumptions!$B$6)) -> 0.74 | F33: =Assumptions!$B$21 -> 160 | G33: =Assumptions!E17 -> 1950 | H33: =G33*(1+Assumptions!$B$7) -> 2047.5 | I33: =C33*E33*F33*H33/1000000 -> 29.850481 | J33: Billable HC × utilization × hours × rate
A34: 46569 | B34: Cloud Services | C34: ='Headcount Plan'!I34 -> 121.50007 | D34: =Assumptions!D13 -> 0.78 | E34: =MAX(0,MIN(0.95,D34+Assumptions!$B$6)) -> 0.78 | F34: =Assumptions!$B$21 -> 160 | G34: =Assumptions!E13 -> 2250 | H34: =G34*(1+Assumptions!$B$7) -> 2362.5 | I34: =C34*E34*F34*H34/1000000 -> 35.82308 | J34: Billable HC × utilization × hours × rate
A35: 46569 | B35: Data & Analytics | C35: ='Headcount Plan'!I35 -> 107.29611 | D35: =Assumptions!D14 -> 0.8 | E35: =MAX(0,MIN(0.95,D35+Assumptions!$B$6)) -> 0.8 | F35: =Assumptions!$B$21 -> 160 | G35: =Assumptions!E14 -> 2400 | H35: =G35*(1+Assumptions!$B$7) -> 2520 | I35: =C35*E35*F35*H35/1000000 -> 34.609432 | J35: Billable HC × utilization × hours × rate
A36: 46569 | B36: Cybersecurity | C36: ='Headcount Plan'!I36 -> 83.48659 | D36: =Assumptions!D15 -> 0.82 | E36: =MAX(0,MIN(0.95,D36+Assumptions!$B$6)) -> 0.82 | F36: =Assumptions!$B$21 -> 160 | G36: =Assumptions!E15 -> 2600 | H36: =G36*(1+Assumptions!$B$7) -> 2730 | I36: =C36*E36*F36*H36/1000000 -> 29.902893 | J36: Billable HC × utilization × hours × rate
A37: 46569 | B37: Application Development | C37: ='Headcount Plan'!I37 -> 147.14895 | D37: =Assumptions!D16 -> 0.76 | E37: =MAX(0,MIN(0.95,D37+Assumptions!$B$6)) -> 0.76 | F37: =Assumptions!$B$21 -> 160 | G37: =Assumptions!E16 -> 2100 | H37: =G37*(1+Assumptions!$B$7) -> 2205 | I37: =C37*E37*F37*H37/1000000 -> 39.454753 | J37: Billable HC × utilization × hours × rate
A38: 46569 | B38: Managed Services | C38: ='Headcount Plan'!I38 -> 123.5438 | D38: =Assumptions!D17 -> 0.74 | E38: =MAX(0,MIN(0.95,D38+Assumptions!$B$6)) -> 0.74 | F38: =Assumptions!$B$21 -> 160 | G38: =Assumptions!E17 -> 1950 | H38: =G38*(1+Assumptions!$B$7) -> 2047.5 | I38: =C38*E38*F38*H38/1000000 -> 29.949983 | J38: Billable HC × utilization × hours × rate
A39: 46600 | B39: Cloud Services | C39: ='Headcount Plan'!I39 -> 121.90507 | D39: =Assumptions!D13 -> 0.78 | E39: =MAX(0,MIN(0.95,D39+Assumptions!$B$6)) -> 0.78 | F39: =Assumptions!$B$21 -> 160 | G39: =Assumptions!E13 -> 2250 | H39: =G39*(1+Assumptions!$B$7) -> 2362.5 | I39: =C39*E39*F39*H39/1000000 -> 35.94249 | J39: Billable HC × utilization × hours × rate
A40: 46600 | B40: Data & Analytics | C40: ='Headcount Plan'!I40 -> 107.65376 | D40: =Assumptions!D14 -> 0.8 | E40: =MAX(0,MIN(0.95,D40+Assumptions!$B$6)) -> 0.8 | F40: =Assumptions!$B$21 -> 160 | G40: =Assumptions!E14 -> 2400 | H40: =G40*(1+Assumptions!$B$7) -> 2520 | I40: =C40*E40*F40*H40/1000000 -> 34.724797 | J40: Billable HC × utilization × hours × rate
A41: 46600 | B41: Cybersecurity | C41: ='Headcount Plan'!I41 -> 83.764879 | D41: =Assumptions!D15 -> 0.82 | E41: =MAX(0,MIN(0.95,D41+Assumptions!$B$6)) -> 0.82 | F41: =Assumptions!$B$21 -> 160 | G41: =Assumptions!E15 -> 2600 | H41: =G41*(1+Assumptions!$B$7) -> 2730 | I41: =C41*E41*F41*H41/1000000 -> 30.002569 | J41: Billable HC × utilization × hours × rate
A42: 46600 | B42: Application Development | C42: ='Headcount Plan'!I42 -> 147.63944 | D42: =Assumptions!D16 -> 0.76 | E42: =MAX(0,MIN(0.95,D42+Assumptions!$B$6)) -> 0.76 | F42: =Assumptions!$B$21 -> 160 | G42: =Assumptions!E16 -> 2100 | H42: =G42*(1+Assumptions!$B$7) -> 2205 | I42: =C42*E42*F42*H42/1000000 -> 39.586269 | J42: Billable HC × utilization × hours × rate
A43: 46600 | B43: Managed Services | C43: ='Headcount Plan'!I43 -> 123.95562 | D43: =Assumptions!D17 -> 0.74 | E43: =MAX(0,MIN(0.95,D43+Assumptions!$B$6)) -> 0.74 | F43: =Assumptions!$B$21 -> 160 | G43: =Assumptions!E17 -> 1950 | H43: =G43*(1+Assumptions!$B$7) -> 2047.5 | I43: =C43*E43*F43*H43/1000000 -> 30.049816 | J43: Billable HC × utilization × hours × rate
A44: 46631 | B44: Cloud Services | C44: ='Headcount Plan'!I44 -> 122.31142 | D44: =Assumptions!D13 -> 0.78 | E44: =MAX(0,MIN(0.95,D44+Assumptions!$B$6)) -> 0.78 | F44: =Assumptions!$B$21 -> 160 | G44: =Assumptions!E13 -> 2250 | H44: =G44*(1+Assumptions!$B$7) -> 2362.5 | I44: =C44*E44*F44*H44/1000000 -> 36.062299 | J44: Billable HC × utilization × hours × rate
A45: 46631 | B45: Data & Analytics | C45: ='Headcount Plan'!I45 -> 108.01261 | D45: =Assumptions!D14 -> 0.8 | E45: =MAX(0,MIN(0.95,D45+Assumptions!$B$6)) -> 0.8 | F45: =Assumptions!$B$21 -> 160 | G45: =Assumptions!E14 -> 2400 | H45: =G45*(1+Assumptions!$B$7) -> 2520 | I45: =C45*E45*F45*H45/1000000 -> 34.840546 | J45: Billable HC × utilization × hours × rate
A46: 46631 | B46: Cybersecurity | C46: ='Headcount Plan'!I46 -> 84.044095 | D46: =Assumptions!D15 -> 0.82 | E46: =MAX(0,MIN(0.95,D46+Assumptions!$B$6)) -> 0.82 | F46: =Assumptions!$B$21 -> 160 | G46: =Assumptions!E15 -> 2600 | H46: =G46*(1+Assumptions!$B$7) -> 2730 | I46: =C46*E46*F46*H46/1000000 -> 30.102578 | J46: Billable HC × utilization × hours × rate
A47: 46631 | B47: Application Development | C47: ='Headcount Plan'!I47 -> 148.13158 | D47: =Assumptions!D16 -> 0.76 | E47: =MAX(0,MIN(0.95,D47+Assumptions!$B$6)) -> 0.76 | F47: =Assumptions!$B$21 -> 160 | G47: =Assumptions!E16 -> 2100 | H47: =G47*(1+Assumptions!$B$7) -> 2205 | I47: =C47*E47*F47*H47/1000000 -> 39.718223 | J47: Billable HC × utilization × hours × rate
A48: 46631 | B48: Managed Services | C48: ='Headcount Plan'!I48 -> 124.3688 | D48: =Assumptions!D17 -> 0.74 | E48: =MAX(0,MIN(0.95,D48+Assumptions!$B$6)) -> 0.74 | F48: =Assumptions!$B$21 -> 160 | G48: =Assumptions!E17 -> 1950 | H48: =G48*(1+Assumptions!$B$7) -> 2047.5 | I48: =C48*E48*F48*H48/1000000 -> 30.149982 | J48: Billable HC × utilization × hours × rate
A49: 46661 | B49: Cloud Services | C49: ='Headcount Plan'!I49 -> 122.71912 | D49: =Assumptions!D13 -> 0.78 | E49: =MAX(0,MIN(0.95,D49+Assumptions!$B$6)) -> 0.78 | F49: =Assumptions!$B$21 -> 160 | G49: =Assumptions!E13 -> 2250 | H49: =G49*(1+Assumptions!$B$7) -> 2362.5 | I49: =C49*E49*F49*H49/1000000 -> 36.182506 | J49: Billable HC × utilization × hours × rate
A50: 46661 | B50: Data & Analytics | C50: ='Headcount Plan'!I50 -> 108.37265 | D50: =Assumptions!D14 -> 0.8 | E50: =MAX(0,MIN(0.95,D50+Assumptions!$B$6)) -> 0.8 | F50: =Assumptions!$B$21 -> 160 | G50: =Assumptions!E14 -> 2400 | H50: =G50*(1+Assumptions!$B$7) -> 2520 | I50: =C50*E50*F50*H50/1000000 -> 34.956682 | J50: Billable HC × utilization × hours × rate
A51: 46661 | B51: Cybersecurity | C51: ='Headcount Plan'!I51 -> 84.324242 | D51: =Assumptions!D15 -> 0.82 | E51: =MAX(0,MIN(0.95,D51+Assumptions!$B$6)) -> 0.82 | F51: =Assumptions!$B$21 -> 160 | G51: =Assumptions!E15 -> 2600 | H51: =G51*(1+Assumptions!$B$7) -> 2730 | I51: =C51*E51*F51*H51/1000000 -> 30.20292 | J51: Billable HC × utilization × hours × rate
A52: 46661 | B52: Application Development | C52: ='Headcount Plan'!I52 -> 148.62535 | D52: =Assumptions!D16 -> 0.76 | E52: =MAX(0,MIN(0.95,D52+Assumptions!$B$6)) -> 0.76 | F52: =Assumptions!$B$21 -> 160 | G52: =Assumptions!E16 -> 2100 | H52: =G52*(1+Assumptions!$B$7) -> 2205 | I52: =C52*E52*F52*H52/1000000 -> 39.850617 | J52: Billable HC × utilization × hours × rate
A53: 46661 | B53: Managed Services | C53: ='Headcount Plan'!I53 -> 124.78336 | D53: =Assumptions!D17 -> 0.74 | E53: =MAX(0,MIN(0.95,D53+Assumptions!$B$6)) -> 0.74 | F53: =Assumptions!$B$21 -> 160 | G53: =Assumptions!E17 -> 1950 | H53: =G53*(1+Assumptions!$B$7) -> 2047.5 | I53: =C53*E53*F53*H53/1000000 -> 30.250482 | J53: Billable HC × utilization × hours × rate
A54: 46692 | B54: Cloud Services | C54: ='Headcount Plan'!I54 -> 123.12819 | D54: =Assumptions!D13 -> 0.78 | E54: =MAX(0,MIN(0.95,D54+Assumptions!$B$6)) -> 0.78 | F54: =Assumptions!$B$21 -> 160 | G54: =Assumptions!E13 -> 2250 | H54: =G54*(1+Assumptions!$B$7) -> 2362.5 | I54: =C54*E54*F54*H54/1000000 -> 36.303115 | J54: Billable HC × utilization × hours × rate
A55: 46692 | B55: Data & Analytics | C55: ='Headcount Plan'!I55 -> 108.73389 | D55: =Assumptions!D14 -> 0.8 | E55: =MAX(0,MIN(0.95,D55+Assumptions!$B$6)) -> 0.8 | F55: =Assumptions!$B$21 -> 160 | G55: =Assumptions!E14 -> 2400 | H55: =G55*(1+Assumptions!$B$7) -> 2520 | I55: =C55*E55*F55*H55/1000000 -> 35.073204 | J55: Billable HC × utilization × hours × rate
A56: 46692 | B56: Cybersecurity | C56: ='Headcount Plan'!I56 -> 84.605323 | D56: =Assumptions!D15 -> 0.82 | E56: =MAX(0,MIN(0.95,D56+Assumptions!$B$6)) -> 0.82 | F56: =Assumptions!$B$21 -> 160 | G56: =Assumptions!E15 -> 2600 | H56: =G56*(1+Assumptions!$B$7) -> 2730 | I56: =C56*E56*F56*H56/1000000 -> 30.303596 | J56: Billable HC × utilization × hours × rate
A57: 46692 | B57: Application Development | C57: ='Headcount Plan'!I57 -> 149.12076 | D57: =Assumptions!D16 -> 0.76 | E57: =MAX(0,MIN(0.95,D57+Assumptions!$B$6)) -> 0.76 | F57: =Assumptions!$B$21 -> 160 | G57: =Assumptions!E16 -> 2100 | H57: =G57*(1+Assumptions!$B$7) -> 2205 | I57: =C57*E57*F57*H57/1000000 -> 39.983452 | J57: Billable HC × utilization × hours × rate
A58: 46692 | B58: Managed Services | C58: ='Headcount Plan'!I58 -> 125.19931 | D58: =Assumptions!D17 -> 0.74 | E58: =MAX(0,MIN(0.95,D58+Assumptions!$B$6)) -> 0.74 | F58: =Assumptions!$B$21 -> 160 | G58: =Assumptions!E17 -> 1950 | H58: =G58*(1+Assumptions!$B$7) -> 2047.5 | I58: =C58*E58*F58*H58/1000000 -> 30.351317 | J58: Billable HC × utilization × hours × rate
A59: 46722 | B59: Cloud Services | C59: ='Headcount Plan'!I59 -> 123.53861 | D59: =Assumptions!D13 -> 0.78 | E59: =MAX(0,MIN(0.95,D59+Assumptions!$B$6)) -> 0.78 | F59: =Assumptions!$B$21 -> 160 | G59: =Assumptions!E13 -> 2250 | H59: =G59*(1+Assumptions!$B$7) -> 2362.5 | I59: =C59*E59*F59*H59/1000000 -> 36.424125 | J59: Billable HC × utilization × hours × rate
A60: 46722 | B60: Data & Analytics | C60: ='Headcount Plan'!I60 -> 109.09634 | D60: =Assumptions!D14 -> 0.8 | E60: =MAX(0,MIN(0.95,D60+Assumptions!$B$6)) -> 0.8 | F60: =Assumptions!$B$21 -> 160 | G60: =Assumptions!E14 -> 2400 | H60: =G60*(1+Assumptions!$B$7) -> 2520 | I60: =C60*E60*F60*H60/1000000 -> 35.190115 | J60: Billable HC × utilization × hours × rate
A61: 46722 | B61: Cybersecurity | C61: ='Headcount Plan'!I61 -> 84.887341 | D61: =Assumptions!D15 -> 0.82 | E61: =MAX(0,MIN(0.95,D61+Assumptions!$B$6)) -> 0.82 | F61: =Assumptions!$B$21 -> 160 | G61: =Assumptions!E15 -> 2600 | H61: =G61*(1+Assumptions!$B$7) -> 2730 | I61: =C61*E61*F61*H61/1000000 -> 30.404608 | J61: Billable HC × utilization × hours × rate
A62: 46722 | B62: Application Development | C62: ='Headcount Plan'!I62 -> 149.61783 | D62: =Assumptions!D16 -> 0.76 | E62: =MAX(0,MIN(0.95,D62+Assumptions!$B$6)) -> 0.76 | F62: =Assumptions!$B$21 -> 160 | G62: =Assumptions!E16 -> 2100 | H62: =G62*(1+Assumptions!$B$7) -> 2205 | I62: =C62*E62*F62*H62/1000000 -> 40.116731 | J62: Billable HC × utilization × hours × rate
A63: 46722 | B63: Managed Services | C63: ='Headcount Plan'!I63 -> 125.61664 | D63: =Assumptions!D17 -> 0.74 | E63: =MAX(0,MIN(0.95,D63+Assumptions!$B$6)) -> 0.74 | F63: =Assumptions!$B$21 -> 160 | G63: =Assumptions!E17 -> 1950 | H63: =G63*(1+Assumptions!$B$7) -> 2047.5 | I63: =C63*E63*F63*H63/1000000 -> 30.452488 | J63: Billable HC × utilization × hours × rate

Sheet Headcount Plan
A1: 2027 Headcount and Personnel Cost Forecast
A2: Case Selected: | B2: =Assumptions!B3 -> Base
A3: Month | B3: Business Unit | C3: Opening HC | D3: Gross Hires | E3: Attrition | F3: Closing HC | G3: Average HC | H3: Billable % | I3: Billable HC | J3: Avg Salary / Month (₹m) | K3: Personnel Cost (₹m)
A4: 46388 | B4: Cloud Services | C4: =Assumptions!B13 -> 145 | D4: =C4*(Assumptions!$B$22+Assumptions!$B$10)/12 -> 1.6916667 | E4: =C4*Assumptions!$B$22/12 -> 1.2083333 | F4: =C4+D4-E4 -> 145.48333 | G4: =(C4+F4)/2 -> 145.24167 | H4: =Assumptions!C13 -> 0.82 | I4: =G4*H4 -> 119.09817 | J4: =Assumptions!F13*(1+Assumptions!$B$8) -> 0.1219 | K4: =G4*J4 -> 17.704959
A5: 46388 | B5: Data & Analytics | C5: =Assumptions!B14 -> 125 | D5: =C5*(Assumptions!$B$22+Assumptions!$B$10)/12 -> 1.4583333 | E5: =C5*Assumptions!$B$22/12 -> 1.0416667 | F5: =C5+D5-E5 -> 125.41667 | G5: =(C5+F5)/2 -> 125.20833 | H5: =Assumptions!C14 -> 0.84 | I5: =G5*H5 -> 105.175 | J5: =Assumptions!F14*(1+Assumptions!$B$8) -> 0.1272 | K5: =G5*J5 -> 15.9265
A6: 46388 | B6: Cybersecurity | C6: =Assumptions!B15 -> 95 | D6: =C6*(Assumptions!$B$22+Assumptions!$B$10)/12 -> 1.1083333 | E6: =C6*Assumptions!$B$22/12 -> 0.79166667 | F6: =C6+D6-E6 -> 95.316667 | G6: =(C6+F6)/2 -> 95.158333 | H6: =Assumptions!C15 -> 0.86 | I6: =G6*H6 -> 81.836167 | J6: =Assumptions!F15*(1+Assumptions!$B$8) -> 0.1378 | K6: =G6*J6 -> 13.112818
A7: 46388 | B7: Application Development | C7: =Assumptions!B16 -> 180 | D7: =C7*(Assumptions!$B$22+Assumptions!$B$10)/12 -> 2.1 | E7: =C7*Assumptions!$B$22/12 -> 1.5 | F7: =C7+D7-E7 -> 180.6 | G7: =(C7+F7)/2 -> 180.3 | H7: =Assumptions!C16 -> 0.8 | I7: =G7*H7 -> 144.24 | J7: =Assumptions!F16*(1+Assumptions!$B$8) -> 0.1113 | K7: =G7*J7 -> 20.06739
A8: 46388 | B8: Managed Services | C8: =Assumptions!B17 -> 155 | D8: =C8*(Assumptions!$B$22+Assumptions!$B$10)/12 -> 1.8083333 | E8: =C8*Assumptions!$B$22/12 -> 1.2916667 | F8: =C8+D8-E8 -> 155.51667 | G8: =(C8+F8)/2 -> 155.25833 | H8: =Assumptions!C17 -> 0.78 | I8: =G8*H8 -> 121.1015 | J8: =Assumptions!F17*(1+Assumptions!$B$8) -> 0.106 | K8: =G8*J8 -> 16.457383
A9: 46419 | B9: Cloud Services | C9: =F4 -> 145.48333 | D9: =C9*(Assumptions!$B$22+Assumptions!$B$10)/12 -> 1.6973056 | E9: =C9*Assumptions!$B$22/12 -> 1.2123611 | F9: =C9+D9-E9 -> 145.96828 | G9: =(C9+F9)/2 -> 145.72581 | H9: =Assumptions!C13 -> 0.82 | I9: =G9*H9 -> 119.49516 | J9: =Assumptions!F13*(1+Assumptions!$B$8) -> 0.1219 | K9: =G9*J9 -> 17.763976
A10: 46419 | B10: Data & Analytics | C10: =F5 -> 125.41667 | D10: =C10*(Assumptions!$B$22+Assumptions!$B$10)/12 -> 1.4631944 | E10: =C10*Assumptions!$B$22/12 -> 1.0451389 | F10: =C10+D10-E10 -> 125.83472 | G10: =(C10+F10)/2 -> 125.62569 | H10: =Assumptions!C14 -> 0.84 | I10: =G10*H10 -> 105.52558 | J10: =Assumptions!F14*(1+Assumptions!$B$8) -> 0.1272 | K10: =G10*J10 -> 15.979588
A11: 46419 | B11: Cybersecurity | C11: =F6 -> 95.316667 | D11: =C11*(Assumptions!$B$22+Assumptions!$B$10)/12 -> 1.1120278 | E11: =C11*Assumptions!$B$22/12 -> 0.79430556 | F11: =C11+D11-E11 -> 95.634389 | G11: =(C11+F11)/2 -> 95.475528 | H11: =Assumptions!C15 -> 0.86 | I11: =G11*H11 -> 82.108954 | J11: =Assumptions!F15*(1+Assumptions!$B$8) -> 0.1378 | K11: =G11*J11 -> 13.156528
A12: 46419 | B12: Application Development | C12: =F7 -> 180.6 | D12: =C12*(Assumptions!$B$22+Assumptions!$B$10)/12 -> 2.107 | E12: =C12*Assumptions!$B$22/12 -> 1.505 | F12: =C12+D12-E12 -> 181.202 | G12: =(C12+F12)/2 -> 180.901 | H12: =Assumptions!C16 -> 0.8 | I12: =G12*H12 -> 144.7208 | J12: =Assumptions!F16*(1+Assumptions!$B$8) -> 0.1113 | K12: =G12*J12 -> 20.134281
A13: 46419 | B13: Managed Services | C13: =F8 -> 155.51667 | D13: =C13*(Assumptions!$B$22+Assumptions!$B$10)/12 -> 1.8143611 | E13: =C13*Assumptions!$B$22/12 -> 1.2959722 | F13: =C13+D13-E13 -> 156.03506 | G13: =(C13+F13)/2 -> 155.77586 | H13: =Assumptions!C17 -> 0.78 | I13: =G13*H13 -> 121.50517 | J13: =Assumptions!F17*(1+Assumptions!$B$8) -> 0.106 | K13: =G13*J13 -> 16.512241
A14: 46447 | B14: Cloud Services | C14: =F9 -> 145.96828 | D14: =C14*(Assumptions!$B$22+Assumptions!$B$10)/12 -> 1.7029632 | E14: =C14*Assumptions!$B$22/12 -> 1.2164023 | F14: =C14+D14-E14 -> 146.45484 | G14: =(C14+F14)/2 -> 146.21156 | H14: =Assumptions!C13 -> 0.82 | I14: =G14*H14 -> 119.89348 | J14: =Assumptions!F13*(1+Assumptions!$B$8) -> 0.1219 | K14: =G14*J14 -> 17.823189
A15: 46447 | B15: Data & Analytics | C15: =F10 -> 125.83472 | D15: =C15*(Assumptions!$B$22+Assumptions!$B$10)/12 -> 1.4680718 | E15: =C15*Assumptions!$B$22/12 -> 1.0486227 | F15: =C15+D15-E15 -> 126.25417 | G15: =(C15+F15)/2 -> 126.04445 | H15: =Assumptions!C14 -> 0.84 | I15: =G15*H15 -> 105.87734 | J15: =Assumptions!F14*(1+Assumptions!$B$8) -> 0.1272 | K15: =G15*J15 -> 16.032854
A16: 46447 | B16: Cybersecurity | C16: =F11 -> 95.634389 | D16: =C16*(Assumptions!$B$22+Assumptions!$B$10)/12 -> 1.1157345 | E16: =C16*Assumptions!$B$22/12 -> 0.79695324 | F16: =C16+D16-E16 -> 95.95317 | G16: =(C16+F16)/2 -> 95.79378 | H16: =Assumptions!C15 -> 0.86 | I16: =G16*H16 -> 82.38265 | J16: =Assumptions!F15*(1+Assumptions!$B$8) -> 0.1378 | K16: =G16*J16 -> 13.200383
A17: 46447 | B17: Application Development | C17: =F12 -> 181.202 | D17: =C17*(Assumptions!$B$22+Assumptions!$B$10)/12 -> 2.1140233 | E17: =C17*Assumptions!$B$22/12 -> 1.5100167 | F17: =C17+D17-E17 -> 181.80601 | G17: =(C17+F17)/2 -> 181.504 | H17: =Assumptions!C16 -> 0.8 | I17: =G17*H17 -> 145.2032 | J17: =Assumptions!F16*(1+Assumptions!$B$8) -> 0.1113 | K17: =G17*J17 -> 20.201396
A18: 46447 | B18: Managed Services | C18: =F13 -> 156.03506 | D18: =C18*(Assumptions!$B$22+Assumptions!$B$10)/12 -> 1.820409 | E18: =C18*Assumptions!$B$22/12 -> 1.3002921 | F18: =C18+D18-E18 -> 156.55517 | G18: =(C18+F18)/2 -> 156.29511 | H18: =Assumptions!C17 -> 0.78 | I18: =G18*H18 -> 121.91019 | J18: =Assumptions!F17*(1+Assumptions!$B$8) -> 0.106 | K18: =G18*J18 -> 16.567282
A19: 46478 | B19: Cloud Services | C19: =F14 -> 146.45484 | D19: =C19*(Assumptions!$B$22+Assumptions!$B$10)/12 -> 1.7086398 | E19: =C19*Assumptions!$B$22/12 -> 1.220457 | F19: =C19+D19-E19 -> 146.94302 | G19: =(C19+F19)/2 -> 146.69893 | H19: =Assumptions!C13 -> 0.82 | I19: =G19*H19 -> 120.29312 | J19: =Assumptions!F13*(1+Assumptions!$B$8) -> 0.1219 | K19: =G19*J19 -> 17.8826
A20: 46478 | B20: Data & Analytics | C20: =F15 -> 126.25417 | D20: =C20*(Assumptions!$B$22+Assumptions!$B$10)/12 -> 1.4729653 | E20: =C20*Assumptions!$B$22/12 -> 1.0521181 | F20: =C20+D20-E20 -> 126.67502 | G20: =(C20+F20)/2 -> 126.46459 | H20: =Assumptions!C14 -> 0.84 | I20: =G20*H20 -> 106.23026 | J20: =Assumptions!F14*(1+Assumptions!$B$8) -> 0.1272 | K20: =G20*J20 -> 16.086296
A21: 46478 | B21: Cybersecurity | C21: =F16 -> 95.95317 | D21: =C21*(Assumptions!$B$22+Assumptions!$B$10)/12 -> 1.1194537 | E21: =C21*Assumptions!$B$22/12 -> 0.79960975 | F21: =C21+D21-E21 -> 96.273014 | G21: =(C21+F21)/2 -> 96.113092 | H21: =Assumptions!C15 -> 0.86 | I21: =G21*H21 -> 82.657259 | J21: =Assumptions!F15*(1+Assumptions!$B$8) -> 0.1378 | K21: =G21*J21 -> 13.244384
A22: 46478 | B22: Application Development | C22: =F17 -> 181.80601 | D22: =C22*(Assumptions!$B$22+Assumptions!$B$10)/12 -> 2.1210701 | E22: =C22*Assumptions!$B$22/12 -> 1.5150501 | F22: =C22+D22-E22 -> 182.41203 | G22: =(C22+F22)/2 -> 182.10902 | H22: =Assumptions!C16 -> 0.8 | I22: =G22*H22 -> 145.68721 | J22: =Assumptions!F16*(1+Assumptions!$B$8) -> 0.1113 | K22: =G22*J22 -> 20.268734
A23: 46478 | B23: Managed Services | C23: =F18 -> 156.55517 | D23: =C23*(Assumptions!$B$22+Assumptions!$B$10)/12 -> 1.826477 | E23: =C23*Assumptions!$B$22/12 -> 1.3046264 | F23: =C23+D23-E23 -> 157.07702 | G23: =(C23+F23)/2 -> 156.8161 | H23: =Assumptions!C17 -> 0.78 | I23: =G23*H23 -> 122.31656 | J23: =Assumptions!F17*(1+Assumptions!$B$8) -> 0.106 | K23: =G23*J23 -> 16.622506
A24: 46508 | B24: Cloud Services | C24: =F19 -> 146.94302 | D24: =C24*(Assumptions!$B$22+Assumptions!$B$10)/12 -> 1.7143353 | E24: =C24*Assumptions!$B$22/12 -> 1.2245252 | F24: =C24+D24-E24 -> 147.43283 | G24: =(C24+F24)/2 -> 147.18793 | H24: =Assumptions!C13 -> 0.82 | I24: =G24*H24 -> 120.6941 | J24: =Assumptions!F13*(1+Assumptions!$B$8) -> 0.1219 | K24: =G24*J24 -> 17.942208
A25: 46508 | B25: Data & Analytics | C25: =F20 -> 126.67502 | D25: =C25*(Assumptions!$B$22+Assumptions!$B$10)/12 -> 1.4778752 | E25: =C25*Assumptions!$B$22/12 -> 1.0556252 | F25: =C25+D25-E25 -> 127.09727 | G25: =(C25+F25)/2 -> 126.88614 | H25: =Assumptions!C14 -> 0.84 | I25: =G25*H25 -> 106.58436 | J25: =Assumptions!F14*(1+Assumptions!$B$8) -> 0.1272 | K25: =G25*J25 -> 16.139917
A26: 46508 | B26: Cybersecurity | C26: =F21 -> 96.273014 | D26: =C26*(Assumptions!$B$22+Assumptions!$B$10)/12 -> 1.1231852 | E26: =C26*Assumptions!$B$22/12 -> 0.80227512 | F26: =C26+D26-E26 -> 96.593924 | G26: =(C26+F26)/2 -> 96.433469 | H26: =Assumptions!C15 -> 0.86 | I26: =G26*H26 -> 82.932783 | J26: =Assumptions!F15*(1+Assumptions!$B$8) -> 0.1378 | K26: =G26*J26 -> 13.288532
A27: 46508 | B27: Application Development | C27: =F22 -> 182.41203 | D27: =C27*(Assumptions!$B$22+Assumptions!$B$10)/12 -> 2.1281403 | E27: =C27*Assumptions!$B$22/12 -> 1.5201002 | F27: =C27+D27-E27 -> 183.02007 | G27: =(C27+F27)/2 -> 182.71605 | H27: =Assumptions!C16 -> 0.8 | I27: =G27*H27 -> 146.17284 | J27: =Assumptions!F16*(1+Assumptions!$B$8) -> 0.1113 | K27: =G27*J27 -> 20.336296
A28: 46508 | B28: Managed Services | C28: =F23 -> 157.07702 | D28: =C28*(Assumptions!$B$22+Assumptions!$B$10)/12 -> 1.8325653 | E28: =C28*Assumptions!$B$22/12 -> 1.3089752 | F28: =C28+D28-E28 -> 157.60061 | G28: =(C28+F28)/2 -> 157.33882 | H28: =Assumptions!C17 -> 0.78 | I28: =G28*H28 -> 122.72428 | J28: =Assumptions!F17*(1+Assumptions!$B$8) -> 0.106 | K28: =G28*J28 -> 16.677915
A29: 46539 | B29: Cloud Services | C29: =F24 -> 147.43283 | D29: =C29*(Assumptions!$B$22+Assumptions!$B$10)/12 -> 1.7200497 | E29: =C29*Assumptions!$B$22/12 -> 1.2286069 | F29: =C29+D29-E29 -> 147.92427 | G29: =(C29+F29)/2 -> 147.67855 | H29: =Assumptions!C13 -> 0.82 | I29: =G29*H29 -> 121.09641 | J29: =Assumptions!F13*(1+Assumptions!$B$8) -> 0.1219 | K29: =G29*J29 -> 18.002016
A30: 46539 | B30: Data & Analytics | C30: =F25 -> 127.09727 | D30: =C30*(Assumptions!$B$22+Assumptions!$B$10)/12 -> 1.4828015 | E30: =C30*Assumptions!$B$22/12 -> 1.0591439 | F30: =C30+D30-E30 -> 127.52093 | G30: =(C30+F30)/2 -> 127.3091 | H30: =Assumptions!C14 -> 0.84 | I30: =G30*H30 -> 106.93964 | J30: =Assumptions!F14*(1+Assumptions!$B$8) -> 0.1272 | K30: =G30*J30 -> 16.193717
A31: 46539 | B31: Cybersecurity | C31: =F26 -> 96.593924 | D31: =C31*(Assumptions!$B$22+Assumptions!$B$10)/12 -> 1.1269291 | E31: =C31*Assumptions!$B$22/12 -> 0.80494937 | F31: =C31+D31-E31 -> 96.915904 | G31: =(C31+F31)/2 -> 96.754914 | H31: =Assumptions!C15 -> 0.86 | I31: =G31*H31 -> 83.209226 | J31: =Assumptions!F15*(1+Assumptions!$B$8) -> 0.1378 | K31: =G31*J31 -> 13.332827
A32: 46539 | B32: Application Development | C32: =F27 -> 183.02007 | D32: =C32*(Assumptions!$B$22+Assumptions!$B$10)/12 -> 2.1352341 | E32: =C32*Assumptions!$B$22/12 -> 1.5251672 | F32: =C32+D32-E32 -> 183.63013 | G32: =(C32+F32)/2 -> 183.3251 | H32: =Assumptions!C16 -> 0.8 | I32: =G32*H32 -> 146.66008 | J32: =Assumptions!F16*(1+Assumptions!$B$8) -> 0.1113 | K32: =G32*J32 -> 20.404084
A33: 46539 | B33: Managed Services | C33: =F28 -> 157.60061 | D33: =C33*(Assumptions!$B$22+Assumptions!$B$10)/12 -> 1.8386738 | E33: =C33*Assumptions!$B$22/12 -> 1.3133384 | F33: =C33+D33-E33 -> 158.12595 | G33: =(C33+F33)/2 -> 157.86328 | H33: =Assumptions!C17 -> 0.78 | I33: =G33*H33 -> 123.13336 | J33: =Assumptions!F17*(1+Assumptions!$B$8) -> 0.106 | K33: =G33*J33 -> 16.733508
A34: 46569 | B34: Cloud Services | C34: =F29 -> 147.92427 | D34: =C34*(Assumptions!$B$22+Assumptions!$B$10)/12 -> 1.7257832 | E34: =C34*Assumptions!$B$22/12 -> 1.2327023 | F34: =C34+D34-E34 -> 148.41736 | G34: =(C34+F34)/2 -> 148.17081 | H34: =Assumptions!C13 -> 0.82 | I34: =G34*H34 -> 121.50007 | J34: =Assumptions!F13*(1+Assumptions!$B$8) -> 0.1219 | K34: =G34*J34 -> 18.062022
A35: 46569 | B35: Data & Analytics | C35: =F30 -> 127.52093 | D35: =C35*(Assumptions!$B$22+Assumptions!$B$10)/12 -> 1.4877441 | E35: =C35*Assumptions!$B$22/12 -> 1.0626744 | F35: =C35+D35-E35 -> 127.946 | G35: =(C35+F35)/2 -> 127.73346 | H35: =Assumptions!C14 -> 0.84 | I35: =G35*H35 -> 107.29611 | J35: =Assumptions!F14*(1+Assumptions!$B$8) -> 0.1272 | K35: =G35*J35 -> 16.247696
A36: 46569 | B36: Cybersecurity | C36: =F31 -> 96.915904 | D36: =C36*(Assumptions!$B$22+Assumptions!$B$10)/12 -> 1.1306855 | E36: =C36*Assumptions!$B$22/12 -> 0.80763253 | F36: =C36+D36-E36 -> 97.238957 | G36: =(C36+F36)/2 -> 97.07743 | H36: =Assumptions!C15 -> 0.86 | I36: =G36*H36 -> 83.48659 | J36: =Assumptions!F15*(1+Assumptions!$B$8) -> 0.1378 | K36: =G36*J36 -> 13.37727
A37: 46569 | B37: Application Development | C37: =F32 -> 183.63013 | D37: =C37*(Assumptions!$B$22+Assumptions!$B$10)/12 -> 2.1423516 | E37: =C37*Assumptions!$B$22/12 -> 1.5302511 | F37: =C37+D37-E37 -> 184.24223 | G37: =(C37+F37)/2 -> 183.93618 | H37: =Assumptions!C16 -> 0.8 | I37: =G37*H37 -> 147.14895 | J37: =Assumptions!F16*(1+Assumptions!$B$8) -> 0.1113 | K37: =G37*J37 -> 20.472097
A38: 46569 | B38: Managed Services | C38: =F33 -> 158.12595 | D38: =C38*(Assumptions!$B$22+Assumptions!$B$10)/12 -> 1.8448027 | E38: =C38*Assumptions!$B$22/12 -> 1.3177162 | F38: =C38+D38-E38 -> 158.65303 | G38: =(C38+F38)/2 -> 158.38949 | H38: =Assumptions!C17 -> 0.78 | I38: =G38*H38 -> 123.5438 | J38: =Assumptions!F17*(1+Assumptions!$B$8) -> 0.106 | K38: =G38*J38 -> 16.789286
A39: 46600 | B39: Cloud Services | C39: =F34 -> 148.41736 | D39: =C39*(Assumptions!$B$22+Assumptions!$B$10)/12 -> 1.7315358 | E39: =C39*Assumptions!$B$22/12 -> 1.2368113 | F39: =C39+D39-E39 -> 148.91208 | G39: =(C39+F39)/2 -> 148.66472 | H39: =Assumptions!C13 -> 0.82 | I39: =G39*H39 -> 121.90507 | J39: =Assumptions!F13*(1+Assumptions!$B$8) -> 0.1219 | K39: =G39*J39 -> 18.122229
A40: 46600 | B40: Data & Analytics | C40: =F35 -> 127.946 | D40: =C40*(Assumptions!$B$22+Assumptions!$B$10)/12 -> 1.4927033 | E40: =C40*Assumptions!$B$22/12 -> 1.0662166 | F40: =C40+D40-E40 -> 128.37248 | G40: =(C40+F40)/2 -> 128.15924 | H40: =Assumptions!C14 -> 0.84 | I40: =G40*H40 -> 107.65376 | J40: =Assumptions!F14*(1+Assumptions!$B$8) -> 0.1272 | K40: =G40*J40 -> 16.301855
A41: 46600 | B41: Cybersecurity | C41: =F36 -> 97.238957 | D41: =C41*(Assumptions!$B$22+Assumptions!$B$10)/12 -> 1.1344545 | E41: =C41*Assumptions!$B$22/12 -> 0.81032464 | F41: =C41+D41-E41 -> 97.563087 | G41: =(C41+F41)/2 -> 97.401022 | H41: =Assumptions!C15 -> 0.86 | I41: =G41*H41 -> 83.764879 | J41: =Assumptions!F15*(1+Assumptions!$B$8) -> 0.1378 | K41: =G41*J41 -> 13.421861
A42: 46600 | B42: Application Development | C42: =F37 -> 184.24223 | D42: =C42*(Assumptions!$B$22+Assumptions!$B$10)/12 -> 2.1494927 | E42: =C42*Assumptions!$B$22/12 -> 1.535352 | F42: =C42+D42-E42 -> 184.85637 | G42: =(C42+F42)/2 -> 184.5493 | H42: =Assumptions!C16 -> 0.8 | I42: =G42*H42 -> 147.63944 | J42: =Assumptions!F16*(1+Assumptions!$B$8) -> 0.1113 | K42: =G42*J42 -> 20.540338
A43: 46600 | B43: Managed Services | C43: =F38 -> 158.65303 | D43: =C43*(Assumptions!$B$22+Assumptions!$B$10)/12 -> 1.8509521 | E43: =C43*Assumptions!$B$22/12 -> 1.3221086 | F43: =C43+D43-E43 -> 159.18188 | G43: =(C43+F43)/2 -> 158.91746 | H43: =Assumptions!C17 -> 0.78 | I43: =G43*H43 -> 123.95562 | J43: =Assumptions!F17*(1+Assumptions!$B$8) -> 0.106 | K43: =G43*J43 -> 16.84525
A44: 46631 | B44: Cloud Services | C44: =F39 -> 148.91208 | D44: =C44*(Assumptions!$B$22+Assumptions!$B$10)/12 -> 1.7373076 | E44: =C44*Assumptions!$B$22/12 -> 1.240934 | F44: =C44+D44-E44 -> 149.40845 | G44: =(C44+F44)/2 -> 149.16027 | H44: =Assumptions!C13 -> 0.82 | I44: =G44*H44 -> 122.31142 | J44: =Assumptions!F13*(1+Assumptions!$B$8) -> 0.1219 | K44: =G44*J44 -> 18.182636
A45: 46631 | B45: Data & Analytics | C45: =F40 -> 128.37248 | D45: =C45*(Assumptions!$B$22+Assumptions!$B$10)/12 -> 1.497679 | E45: =C45*Assumptions!$B$22/12 -> 1.0697707 | F45: =C45+D45-E45 -> 128.80039 | G45: =(C45+F45)/2 -> 128.58644 | H45: =Assumptions!C14 -> 0.84 | I45: =G45*H45 -> 108.01261 | J45: =Assumptions!F14*(1+Assumptions!$B$8) -> 0.1272 | K45: =G45*J45 -> 16.356195
A46: 46631 | B46: Cybersecurity | C46: =F41 -> 97.563087 | D46: =C46*(Assumptions!$B$22+Assumptions!$B$10)/12 -> 1.138236 | E46: =C46*Assumptions!$B$22/12 -> 0.81302572 | F46: =C46+D46-E46 -> 97.888297 | G46: =(C46+F46)/2 -> 97.725692 | H46: =Assumptions!C15 -> 0.86 | I46: =G46*H46 -> 84.044095 | J46: =Assumptions!F15*(1+Assumptions!$B$8) -> 0.1378 | K46: =G46*J46 -> 13.4666
A47: 46631 | B47: Application Development | C47: =F42 -> 184.85637 | D47: =C47*(Assumptions!$B$22+Assumptions!$B$10)/12 -> 2.1566577 | E47: =C47*Assumptions!$B$22/12 -> 1.5404698 | F47: =C47+D47-E47 -> 185.47256 | G47: =(C47+F47)/2 -> 185.16447 | H47: =Assumptions!C16 -> 0.8 | I47: =G47*H47 -> 148.13158 | J47: =Assumptions!F16*(1+Assumptions!$B$8) -> 0.1113 | K47: =G47*J47 -> 20.608805
A48: 46631 | B48: Managed Services | C48: =F43 -> 159.18188 | D48: =C48*(Assumptions!$B$22+Assumptions!$B$10)/12 -> 1.8571219 | E48: =C48*Assumptions!$B$22/12 -> 1.3265157 | F48: =C48+D48-E48 -> 159.71248 | G48: =(C48+F48)/2 -> 159.44718 | H48: =Assumptions!C17 -> 0.78 | I48: =G48*H48 -> 124.3688 | J48: =Assumptions!F17*(1+Assumptions!$B$8) -> 0.106 | K48: =G48*J48 -> 16.901401
A49: 46661 | B49: Cloud Services | C49: =F44 -> 149.40845 | D49: =C49*(Assumptions!$B$22+Assumptions!$B$10)/12 -> 1.7430986 | E49: =C49*Assumptions!$B$22/12 -> 1.2450704 | F49: =C49+D49-E49 -> 149.90648 | G49: =(C49+F49)/2 -> 149.65747 | H49: =Assumptions!C13 -> 0.82 | I49: =G49*H49 -> 122.71912 | J49: =Assumptions!F13*(1+Assumptions!$B$8) -> 0.1219 | K49: =G49*J49 -> 18.243245
A50: 46661 | B50: Data & Analytics | C50: =F45 -> 128.80039 | D50: =C50*(Assumptions!$B$22+Assumptions!$B$10)/12 -> 1.5026712 | E50: =C50*Assumptions!$B$22/12 -> 1.0733366 | F50: =C50+D50-E50 -> 129.22973 | G50: =(C50+F50)/2 -> 129.01506 | H50: =Assumptions!C14 -> 0.84 | I50: =G50*H50 -> 108.37265 | J50: =Assumptions!F14*(1+Assumptions!$B$8) -> 0.1272 | K50: =G50*J50 -> 16.410715
A51: 46661 | B51: Cybersecurity | C51: =F46 -> 97.888297 | D51: =C51*(Assumptions!$B$22+Assumptions!$B$10)/12 -> 1.1420301 | E51: =C51*Assumptions!$B$22/12 -> 0.81573581 | F51: =C51+D51-E51 -> 98.214591 | G51: =(C51+F51)/2 -> 98.051444 | H51: =Assumptions!C15 -> 0.86 | I51: =G51*H51 -> 84.324242 | J51: =Assumptions!F15*(1+Assumptions!$B$8) -> 0.1378 | K51: =G51*J51 -> 13.511489
A52: 46661 | B52: Application Development | C52: =F47 -> 185.47256 | D52: =C52*(Assumptions!$B$22+Assumptions!$B$10)/12 -> 2.1638466 | E52: =C52*Assumptions!$B$22/12 -> 1.5456047 | F52: =C52+D52-E52 -> 186.0908 | G52: =(C52+F52)/2 -> 185.78168 | H52: =Assumptions!C16 -> 0.8 | I52: =G52*H52 -> 148.62535 | J52: =Assumptions!F16*(1+Assumptions!$B$8) -> 0.1113 | K52: =G52*J52 -> 20.677501
A53: 46661 | B53: Managed Services | C53: =F48 -> 159.71248 | D53: =C53*(Assumptions!$B$22+Assumptions!$B$10)/12 -> 1.8633123 | E53: =C53*Assumptions!$B$22/12 -> 1.3309374 | F53: =C53+D53-E53 -> 160.24486 | G53: =(C53+F53)/2 -> 159.97867 | H53: =Assumptions!C17 -> 0.78 | I53: =G53*H53 -> 124.78336 | J53: =Assumptions!F17*(1+Assumptions!$B$8) -> 0.106 | K53: =G53*J53 -> 16.957739
A54: 46692 | B54: Cloud Services | C54: =F49 -> 149.90648 | D54: =C54*(Assumptions!$B$22+Assumptions!$B$10)/12 -> 1.748909 | E54: =C54*Assumptions!$B$22/12 -> 1.2492207 | F54: =C54+D54-E54 -> 150.40617 | G54: =(C54+F54)/2 -> 150.15633 | H54: =Assumptions!C13 -> 0.82 | I54: =G54*H54 -> 123.12819 | J54: =Assumptions!F13*(1+Assumptions!$B$8) -> 0.1219 | K54: =G54*J54 -> 18.304056
A55: 46692 | B55: Data & Analytics | C55: =F50 -> 129.22973 | D55: =C55*(Assumptions!$B$22+Assumptions!$B$10)/12 -> 1.5076801 | E55: =C55*Assumptions!$B$22/12 -> 1.0769144 | F55: =C55+D55-E55 -> 129.66049 | G55: =(C55+F55)/2 -> 129.44511 | H55: =Assumptions!C14 -> 0.84 | I55: =G55*H55 -> 108.73389 | J55: =Assumptions!F14*(1+Assumptions!$B$8) -> 0.1272 | K55: =G55*J55 -> 16.465418
A56: 46692 | B56: Cybersecurity | C56: =F51 -> 98.214591 | D56: =C56*(Assumptions!$B$22+Assumptions!$B$10)/12 -> 1.1458369 | E56: =C56*Assumptions!$B$22/12 -> 0.81845493 | F56: =C56+D56-E56 -> 98.541973 | G56: =(C56+F56)/2 -> 98.378282 | H56: =Assumptions!C15 -> 0.86 | I56: =G56*H56 -> 84.605323 | J56: =Assumptions!F15*(1+Assumptions!$B$8) -> 0.1378 | K56: =G56*J56 -> 13.556527
A57: 46692 | B57: Application Development | C57: =F52 -> 186.0908 | D57: =C57*(Assumptions!$B$22+Assumptions!$B$10)/12 -> 2.1710594 | E57: =C57*Assumptions!$B$22/12 -> 1.5507567 | F57: =C57+D57-E57 -> 186.71111 | G57: =(C57+F57)/2 -> 186.40096 | H57: =Assumptions!C16 -> 0.8 | I57: =G57*H57 -> 149.12076 | J57: =Assumptions!F16*(1+Assumptions!$B$8) -> 0.1113 | K57: =G57*J57 -> 20.746426
A58: 46692 | B58: Managed Services | C58: =F53 -> 160.24486 | D58: =C58*(Assumptions!$B$22+Assumptions!$B$10)/12 -> 1.8695234 | E58: =C58*Assumptions!$B$22/12 -> 1.3353738 | F58: =C58+D58-E58 -> 160.77901 | G58: =(C58+F58)/2 -> 160.51193 | H58: =Assumptions!C17 -> 0.78 | I58: =G58*H58 -> 125.19931 | J58: =Assumptions!F17*(1+Assumptions!$B$8) -> 0.106 | K58: =G58*J58 -> 17.014265
A59: 46722 | B59: Cloud Services | C59: =F54 -> 150.40617 | D59: =C59*(Assumptions!$B$22+Assumptions!$B$10)/12 -> 1.7547386 | E59: =C59*Assumptions!$B$22/12 -> 1.2533847 | F59: =C59+D59-E59 -> 150.90752 | G59: =(C59+F59)/2 -> 150.65685 | H59: =Assumptions!C13 -> 0.82 | I59: =G59*H59 -> 123.53861 | J59: =Assumptions!F13*(1+Assumptions!$B$8) -> 0.1219 | K59: =G59*J59 -> 18.36507
A60: 46722 | B60: Data & Analytics | C60: =F55 -> 129.66049 | D60: =C60*(Assumptions!$B$22+Assumptions!$B$10)/12 -> 1.5127057 | E60: =C60*Assumptions!$B$22/12 -> 1.0805041 | F60: =C60+D60-E60 -> 130.09269 | G60: =(C60+F60)/2 -> 129.87659 | H60: =Assumptions!C14 -> 0.84 | I60: =G60*H60 -> 109.09634 | J60: =Assumptions!F14*(1+Assumptions!$B$8) -> 0.1272 | K60: =G60*J60 -> 16.520303
A61: 46722 | B61: Cybersecurity | C61: =F56 -> 98.541973 | D61: =C61*(Assumptions!$B$22+Assumptions!$B$10)/12 -> 1.1496564 | E61: =C61*Assumptions!$B$22/12 -> 0.82118311 | F61: =C61+D61-E61 -> 98.870447 | G61: =(C61+F61)/2 -> 98.70621 | H61: =Assumptions!C15 -> 0.86 | I61: =G61*H61 -> 84.887341 | J61: =Assumptions!F15*(1+Assumptions!$B$8) -> 0.1378 | K61: =G61*J61 -> 13.601716
A62: 46722 | B62: Application Development | C62: =F57 -> 186.71111 | D62: =C62*(Assumptions!$B$22+Assumptions!$B$10)/12 -> 2.1782963 | E62: =C62*Assumptions!$B$22/12 -> 1.5559259 | F62: =C62+D62-E62 -> 187.33348 | G62: =(C62+F62)/2 -> 187.02229 | H62: =Assumptions!C16 -> 0.8 | I62: =G62*H62 -> 149.61783 | J62: =Assumptions!F16*(1+Assumptions!$B$8) -> 0.1113 | K62: =G62*J62 -> 20.815581
A63: 46722 | B63: Managed Services | C63: =F58 -> 160.77901 | D63: =C63*(Assumptions!$B$22+Assumptions!$B$10)/12 -> 1.8757551 | E63: =C63*Assumptions!$B$22/12 -> 1.3398251 | F63: =C63+D63-E63 -> 161.31494 | G63: =(C63+F63)/2 -> 161.04697 | H63: =Assumptions!C17 -> 0.78 | I63: =G63*H63 -> 125.61664 | J63: =Assumptions!F17*(1+Assumptions!$B$8) -> 0.106 | K63: =G63*J63 -> 17.070979

Sheet Opex Forecast
A1: 2027 Operating Cost Forecast
A2: Case Selected: | B2: =Assumptions!B3 -> Base
A3: Month | B3: Average HC | C3: Revenue (₹m) | D3: Software (₹m) | E3: Facilities (₹m) | F3: Travel + Marketing + Other (₹m) | G3: Subcontractors (₹m) | H3: Personnel (₹m) | I3: Total Cost (₹m)
A4: 46388 | B4: =SUM('Headcount Plan'!G4:G8) -> 701.16667 | C4: =SUM('Revenue Forecast'!I4:I8) -> 166.3846 | D4: =SUMPRODUCT('Headcount Plan'!G4:G8,Assumptions!$G$13:$G$17)*(1+Assumptions!$B$9) -> 7.1781938 | E4: =B4*Assumptions!$B$24*(1+Assumptions!$B$9) -> 4.41735 | F4: =C4*Assumptions!$B$25*(1+Assumptions!$B$9) -> 7.8616721 | G4: =C4*Assumptions!$B$23 -> 12.478845 | H4: =SUM('Headcount Plan'!K4:K8) -> 83.269051 | I4: =SUM(D4:H4) -> 115.20511
A5: 46419 | B5: =SUM('Headcount Plan'!G9:G13) -> 703.50389 | C5: =SUM('Revenue Forecast'!I9:I13) -> 166.93921 | D5: =SUMPRODUCT('Headcount Plan'!G9:G13,Assumptions!$G$13:$G$17)*(1+Assumptions!$B$9) -> 7.2021211 | E5: =B5*Assumptions!$B$24*(1+Assumptions!$B$9) -> 4.4320745 | F5: =C5*Assumptions!$B$25*(1+Assumptions!$B$9) -> 7.8878777 | G5: =C5*Assumptions!$B$23 -> 12.520441 | H5: =SUM('Headcount Plan'!K9:K13) -> 83.546614 | I5: =SUM(D5:H5) -> 115.58913
A6: 46447 | B6: =SUM('Headcount Plan'!G14:G18) -> 705.8489 | C6: =SUM('Revenue Forecast'!I14:I18) -> 167.49567 | D6: =SUMPRODUCT('Headcount Plan'!G14:G18,Assumptions!$G$13:$G$17)*(1+Assumptions!$B$9) -> 7.2261281 | E6: =B6*Assumptions!$B$24*(1+Assumptions!$B$9) -> 4.4468481 | F6: =C6*Assumptions!$B$25*(1+Assumptions!$B$9) -> 7.9141706 | G6: =C6*Assumptions!$B$23 -> 12.562176 | H6: =SUM('Headcount Plan'!K14:K18) -> 83.825103 | I6: =SUM(D6:H6) -> 115.97443
A7: 46478 | B7: =SUM('Headcount Plan'!G19:G23) -> 708.20173 | C7: =SUM('Revenue Forecast'!I19:I23) -> 168.05399 | D7: =SUMPRODUCT('Headcount Plan'!G19:G23,Assumptions!$G$13:$G$17)*(1+Assumptions!$B$9) -> 7.2502152 | E7: =B7*Assumptions!$B$24*(1+Assumptions!$B$9) -> 4.4616709 | F7: =C7*Assumptions!$B$25*(1+Assumptions!$B$9) -> 7.9405512 | G7: =C7*Assumptions!$B$23 -> 12.604049 | H7: =SUM('Headcount Plan'!K19:K23) -> 84.10452 | I7: =SUM(D7:H7) -> 116.36101
A8: 46508 | B8: =SUM('Headcount Plan'!G24:G28) -> 710.5624 | C8: =SUM('Revenue Forecast'!I24:I28) -> 168.61417 | D8: =SUMPRODUCT('Headcount Plan'!G24:G28,Assumptions!$G$13:$G$17)*(1+Assumptions!$B$9) -> 7.2743826 | E8: =B8*Assumptions!$B$24*(1+Assumptions!$B$9) -> 4.4765431 | F8: =C8*Assumptions!$B$25*(1+Assumptions!$B$9) -> 7.9670197 | G8: =C8*Assumptions!$B$23 -> 12.646063 | H8: =SUM('Headcount Plan'!K24:K28) -> 84.384868 | I8: =SUM(D8:H8) -> 116.74888
A9: 46539 | B9: =SUM('Headcount Plan'!G29:G33) -> 712.93095 | C9: =SUM('Revenue Forecast'!I29:I33) -> 169.17622 | D9: =SUMPRODUCT('Headcount Plan'!G29:G33,Assumptions!$G$13:$G$17)*(1+Assumptions!$B$9) -> 7.2986306 | E9: =B9*Assumptions!$B$24*(1+Assumptions!$B$9) -> 4.491465 | F9: =C9*Assumptions!$B$25*(1+Assumptions!$B$9) -> 7.9935764 | G9: =C9*Assumptions!$B$23 -> 12.688217 | H9: =SUM('Headcount Plan'!K29:K33) -> 84.666151 | I9: =SUM(D9:H9) -> 117.13804
A10: 46569 | B10: =SUM('Headcount Plan'!G34:G38) -> 715.30738 | C10: =SUM('Revenue Forecast'!I34:I38) -> 169.74014 | D10: =SUMPRODUCT('Headcount Plan'!G34:G38,Assumptions!$G$13:$G$17)*(1+Assumptions!$B$9) -> 7.3229593 | E10: =B10*Assumptions!$B$24*(1+Assumptions!$B$9) -> 4.5064365 | F10: =C10*Assumptions!$B$25*(1+Assumptions!$B$9) -> 8.0202217 | G10: =C10*Assumptions!$B$23 -> 12.730511 | H10: =SUM('Headcount Plan'!K34:K38) -> 84.948372 | I10: =SUM(D10:H10) -> 117.5285
A11: 46600 | B11: =SUM('Headcount Plan'!G39:G43) -> 717.69174 | C11: =SUM('Revenue Forecast'!I39:I43) -> 170.30594 | D11: =SUMPRODUCT('Headcount Plan'!G39:G43,Assumptions!$G$13:$G$17)*(1+Assumptions!$B$9) -> 7.3473692 | E11: =B11*Assumptions!$B$24*(1+Assumptions!$B$9) -> 4.521458 | F11: =C11*Assumptions!$B$25*(1+Assumptions!$B$9) -> 8.0469557 | G11: =C11*Assumptions!$B$23 -> 12.772946 | H11: =SUM('Headcount Plan'!K39:K43) -> 85.231533 | I11: =SUM(D11:H11) -> 117.92026
A12: 46631 | B12: =SUM('Headcount Plan'!G44:G48) -> 720.08405 | C12: =SUM('Revenue Forecast'!I44:I48) -> 170.87363 | D12: =SUMPRODUCT('Headcount Plan'!G44:G48,Assumptions!$G$13:$G$17)*(1+Assumptions!$B$9) -> 7.3718604 | E12: =B12*Assumptions!$B$24*(1+Assumptions!$B$9) -> 4.5365295 | F12: =C12*Assumptions!$B$25*(1+Assumptions!$B$9) -> 8.0737789 | G12: =C12*Assumptions!$B$23 -> 12.815522 | H12: =SUM('Headcount Plan'!K44:K48) -> 85.515638 | I12: =SUM(D12:H12) -> 118.31333
A13: 46661 | B13: =SUM('Headcount Plan'!G49:G53) -> 722.48433 | C13: =SUM('Revenue Forecast'!I49:I53) -> 171.44321 | D13: =SUMPRODUCT('Headcount Plan'!G49:G53,Assumptions!$G$13:$G$17)*(1+Assumptions!$B$9) -> 7.3964333 | E13: =B13*Assumptions!$B$24*(1+Assumptions!$B$9) -> 4.5516513 | F13: =C13*Assumptions!$B$25*(1+Assumptions!$B$9) -> 8.1006915 | G13: =C13*Assumptions!$B$23 -> 12.858241 | H13: =SUM('Headcount Plan'!K49:K53) -> 85.80069 | I13: =SUM(D13:H13) -> 118.70771
A14: 46692 | B14: =SUM('Headcount Plan'!G54:G58) -> 724.89261 | C14: =SUM('Revenue Forecast'!I54:I58) -> 172.01468 | D14: =SUMPRODUCT('Headcount Plan'!G54:G58,Assumptions!$G$13:$G$17)*(1+Assumptions!$B$9) -> 7.4210881 | E14: =B14*Assumptions!$B$24*(1+Assumptions!$B$9) -> 4.5668234 | F14: =C14*Assumptions!$B$25*(1+Assumptions!$B$9) -> 8.1276938 | G14: =C14*Assumptions!$B$23 -> 12.901101 | H14: =SUM('Headcount Plan'!K54:K58) -> 86.086693 | I14: =SUM(D14:H14) -> 119.1034
A15: 46722 | B15: =SUM('Headcount Plan'!G59:G63) -> 727.30892 | C15: =SUM('Revenue Forecast'!I59:I63) -> 172.58807 | D15: =SUMPRODUCT('Headcount Plan'!G59:G63,Assumptions!$G$13:$G$17)*(1+Assumptions!$B$9) -> 7.445825 | E15: =B15*Assumptions!$B$24*(1+Assumptions!$B$9) -> 4.5820462 | F15: =C15*Assumptions!$B$25*(1+Assumptions!$B$9) -> 8.1547861 | G15: =C15*Assumptions!$B$23 -> 12.944105 | H15: =SUM('Headcount Plan'!K59:K63) -> 86.373648 | I15: =SUM(D15:H15) -> 119.50041

Sheet P&L
A1: Integrated Monthly P&L (₹m)
A2: Case Selected: | B2: =Assumptions!B3 -> Base
A3: Line Item | B3: 45658 | C3: 45689 | D3: 45717 | E3: 45748 | F3: 45778 | G3: 45809 | H3: 45839 | I3: 45870 | J3: 45901 | K3: 45931 | L3: 45962 | M3: 45992 | N3: 46023 | O3: 46054 | P3: 46082 | Q3: 46113 | R3: 46143 | S3: 46174 | T3: 46204 | U3: 46235 | V3: 46266 | W3: 46296 | X3: 46327 | Y3: 46357 | Z3: 46388 | AA3: 46419 | AB3: 46447 | AC3: 46478 | AD3: 46508 | AE3: 46539 | AF3: 46569 | AG3: 46600 | AH3: 46631 | AI3: 46661 | AJ3: 46692 | AK3: 46722 | AL3: 2025 Actual | AM3: 2026 Actual | AN3: 2027 Forecast
A4: Revenue | B4: =SUMIFS(Actuals!$I$4:$I$123,Actuals!$A$4:$A$123,B$3) -> 116.61212 | C4: =SUMIFS(Actuals!$I$4:$I$123,Actuals!$A$4:$A$123,C$3) -> 117.8441 | D4: =SUMIFS(Actuals!$I$4:$I$123,Actuals!$A$4:$A$123,D$3) -> 119.75911 | E4: =SUMIFS(Actuals!$I$4:$I$123,Actuals!$A$4:$A$123,E$3) -> 117.74867 | F4: =SUMIFS(Actuals!$I$4:$I$123,Actuals!$A$4:$A$123,F$3) -> 122.75101 | G4: =SUMIFS(Actuals!$I$4:$I$123,Actuals!$A$4:$A$123,G$3) -> 124.77301 | H4: =SUMIFS(Actuals!$I$4:$I$123,Actuals!$A$4:$A$123,H$3) -> 126.16668 | I4: =SUMIFS(Actuals!$I$4:$I$123,Actuals!$A$4:$A$123,I$3) -> 128.27071 | ... Y4: =SUMIFS(Actuals!$I$4:$I$123,Actuals!$A$4:$A$123,Y$3) -> 154.59837 | Z4: ='Opex Forecast'!C4 -> 166.3846 | AA4: ='Opex Forecast'!C5 -> 166.93921 | AB4: ='Opex Forecast'!C6 -> 167.49567 | AC4: ='Opex Forecast'!C7 -> 168.05399 | AD4: ='Opex Forecast'!C8 -> 168.61417 | AE4: ='Opex Forecast'!C9 -> 169.17622 | AF4: ='Opex Forecast'!C10 -> 169.74014 | AG4: ='Opex Forecast'!C11 -> 170.30594 | AH4: ='Opex Forecast'!C12 -> 170.87363 | AI4: ='Opex Forecast'!C13 -> 171.44321 | AJ4: ='Opex Forecast'!C14 -> 172.01468 | AK4: ='Opex Forecast'!C15 -> 172.58807 | AL4: =SUM(B4:M4) -> 1504.4942 | AM4: =SUM(N4:Y4) -> 1785.9819 | AN4: =SUM(Z4:AK4) -> 2033.6295
A5: Personnel Cost | B5: =SUMIFS(Actuals!$J$4:$J$123,Actuals!$A$4:$A$123,B$3) -> 59.964 | C5: =SUMIFS(Actuals!$J$4:$J$123,Actuals!$A$4:$A$123,C$3) -> 60.675 | D5: =SUMIFS(Actuals!$J$4:$J$123,Actuals!$A$4:$A$123,D$3) -> 61.198 | E5: =SUMIFS(Actuals!$J$4:$J$123,Actuals!$A$4:$A$123,E$3) -> 61.789 | F5: =SUMIFS(Actuals!$J$4:$J$123,Actuals!$A$4:$A$123,F$3) -> 62.097 | G5: =SUMIFS(Actuals!$J$4:$J$123,Actuals!$A$4:$A$123,G$3) -> 62.808 | H5: =SUMIFS(Actuals!$J$4:$J$123,Actuals!$A$4:$A$123,H$3) -> 63.331 | I5: =SUMIFS(Actuals!$J$4:$J$123,Actuals!$A$4:$A$123,I$3) -> 64.042 | ... Y5: =SUMIFS(Actuals!$J$4:$J$123,Actuals!$A$4:$A$123,Y$3) -> 77.40014 | Z5: ='Opex Forecast'!H4 -> 83.269051 | AA5: ='Opex Forecast'!H5 -> 83.546614 | AB5: ='Opex Forecast'!H6 -> 83.825103 | AC5: ='Opex Forecast'!H7 -> 84.10452 | AD5: ='Opex Forecast'!H8 -> 84.384868 | AE5: ='Opex Forecast'!H9 -> 84.666151 | AF5: ='Opex Forecast'!H10 -> 84.948372 | AG5: ='Opex Forecast'!H11 -> 85.231533 | AH5: ='Opex Forecast'!H12 -> 85.515638 | AI5: ='Opex Forecast'!H13 -> 85.80069 | AJ5: ='Opex Forecast'!H14 -> 86.086693 | AK5: ='Opex Forecast'!H15 -> 86.373648 | AL5: =SUM(B5:M5) -> 757.484 | AM5: =SUM(N5:Y5) -> 889.44388 | AN5: =SUM(Z5:AK5) -> 1017.7529
A6: Subcontractor Cost | B6: =SUMIFS(Actuals!$K$4:$K$123,Actuals!$A$4:$A$123,B$3) -> 8.5062605 | C6: =SUMIFS(Actuals!$K$4:$K$123,Actuals!$A$4:$A$123,C$3) -> 8.5972359 | D6: =SUMIFS(Actuals!$K$4:$K$123,Actuals!$A$4:$A$123,D$3) -> 8.7384995 | E6: =SUMIFS(Actuals!$K$4:$K$123,Actuals!$A$4:$A$123,E$3) -> 8.5896774 | F6: =SUMIFS(Actuals!$K$4:$K$123,Actuals!$A$4:$A$123,F$3) -> 8.9539695 | G6: =SUMIFS(Actuals!$K$4:$K$123,Actuals!$A$4:$A$123,G$3) -> 9.1083197 | H6: =SUMIFS(Actuals!$K$4:$K$123,Actuals!$A$4:$A$123,H$3) -> 9.2067876 | I6: =SUMIFS(Actuals!$K$4:$K$123,Actuals!$A$4:$A$123,I$3) -> 9.3639501 | ... Y6: =SUMIFS(Actuals!$K$4:$K$123,Actuals!$A$4:$A$123,Y$3) -> 11.305365 | Z6: ='Opex Forecast'!G4 -> 12.478845 | AA6: ='Opex Forecast'!G5 -> 12.520441 | AB6: ='Opex Forecast'!G6 -> 12.562176 | AC6: ='Opex Forecast'!G7 -> 12.604049 | AD6: ='Opex Forecast'!G8 -> 12.646063 | AE6: ='Opex Forecast'!G9 -> 12.688217 | AF6: ='Opex Forecast'!G10 -> 12.730511 | AG6: ='Opex Forecast'!G11 -> 12.772946 | AH6: ='Opex Forecast'!G12 -> 12.815522 | AI6: ='Opex Forecast'!G13 -> 12.858241 | AJ6: ='Opex Forecast'!G14 -> 12.901101 | AK6: ='Opex Forecast'!G15 -> 12.944105 | AL6: =SUM(B6:M6) -> 109.80065 | AM6: =SUM(N6:Y6) -> 130.50687 | AN6: =SUM(Z6:AK6) -> 152.52222
A7: Gross Profit | B7: =B4-B5-B6 -> 48.141856 | C7: =C4-C5-C6 -> 48.571864 | D7: =D4-D5-D6 -> 49.822615 | E7: =E4-E5-E6 -> 47.369995 | F7: =F4-F5-F6 -> 51.700043 | G7: =G4-G5-G6 -> 52.856685 | H7: =H4-H5-H6 -> 53.628895 | I7: =I4-I5-I6 -> 54.864762 | ... AN7: =AN4-AN5-AN6 -> 863.35444
A8: Gross Margin % | B8: =IFERROR(B7/B4,0) -> 0.41283751 | C8: =IFERROR(C7/C4,0) -> 0.41217052 | D8: =IFERROR(D7/D4,0) -> 0.41602358 | E8: =IFERROR(E7/E4,0) -> 0.40229749 | F8: =IFERROR(F7/F4,0) -> 0.42117814 | G8: =IFERROR(G7/G4,0) -> 0.42362276 | H8: =IFERROR(H7/H4,0) -> 0.42506385 | I8: =IFERROR(I7/I4,0) -> 0.42772634 | ... AM8: =IFERROR(AM7/AM4,0) -> 0.42891316 | AN8: =AN7/AN4 -> 0.4245387
A9: Software Cost | B9: =SUMIFS(Actuals!$L$4:$L$123,Actuals!$A$4:$A$123,B$3) -> 5.1 | C9: =SUMIFS(Actuals!$L$4:$L$123,Actuals!$A$4:$A$123,C$3) -> 5.16 | D9: =SUMIFS(Actuals!$L$4:$L$123,Actuals!$A$4:$A$123,D$3) -> 5.205 | E9: =SUMIFS(Actuals!$L$4:$L$123,Actuals!$A$4:$A$123,E$3) -> 5.254 | F9: =SUMIFS(Actuals!$L$4:$L$123,Actuals!$A$4:$A$123,F$3) -> 5.28 | G9: =SUMIFS(Actuals!$L$4:$L$123,Actuals!$A$4:$A$123,G$3) -> 5.34 | H9: =SUMIFS(Actuals!$L$4:$L$123,Actuals!$A$4:$A$123,H$3) -> 5.385 | I9: =SUMIFS(Actuals!$L$4:$L$123,Actuals!$A$4:$A$123,I$3) -> 5.445 | ... Y9: =SUMIFS(Actuals!$L$4:$L$123,Actuals!$A$4:$A$123,Y$3) -> 6.51525 | Z9: ='Opex Forecast'!D4 -> 7.1781938 | AA9: ='Opex Forecast'!D5 -> 7.2021211 | AB9: ='Opex Forecast'!D6 -> 7.2261281 | AC9: ='Opex Forecast'!D7 -> 7.2502152 | AD9: ='Opex Forecast'!D8 -> 7.2743826 | AE9: ='Opex Forecast'!D9 -> 7.2986306 | AF9: ='Opex Forecast'!D10 -> 7.3229593 | AG9: ='Opex Forecast'!D11 -> 7.3473692 | AH9: ='Opex Forecast'!D12 -> 7.3718604 | AI9: ='Opex Forecast'!D13 -> 7.3964333 | AJ9: ='Opex Forecast'!D14 -> 7.4210881 | AK9: ='Opex Forecast'!D15 -> 7.445825 | AL9: =SUM(B9:M9) -> 64.408 | AM9: =SUM(N9:Y9) -> 74.88285 | AN9: =SUM(Z9:AK9) -> 87.735207
A10: Facilities Cost | B10: =SUMIFS(Actuals!$M$4:$M$123,Actuals!$A$4:$A$123,B$3) -> 3.2175 | C10: =SUMIFS(Actuals!$M$4:$M$123,Actuals!$A$4:$A$123,C$3) -> 3.256 | D10: =SUMIFS(Actuals!$M$4:$M$123,Actuals!$A$4:$A$123,D$3) -> 3.2835 | E10: =SUMIFS(Actuals!$M$4:$M$123,Actuals!$A$4:$A$123,E$3) -> 3.3165 | F10: =SUMIFS(Actuals!$M$4:$M$123,Actuals!$A$4:$A$123,F$3) -> 3.333 | G10: =SUMIFS(Actuals!$M$4:$M$123,Actuals!$A$4:$A$123,G$3) -> 3.3715 | H10: =SUMIFS(Actuals!$M$4:$M$123,Actuals!$A$4:$A$123,H$3) -> 3.399 | I10: =SUMIFS(Actuals!$M$4:$M$123,Actuals!$A$4:$A$123,I$3) -> 3.4375 | ... Y10: =SUMIFS(Actuals!$M$4:$M$123,Actuals!$A$4:$A$123,Y$3) -> 3.9215 | Z10: ='Opex Forecast'!E4 -> 4.41735 | AA10: ='Opex Forecast'!E5 -> 4.4320745 | AB10: ='Opex Forecast'!E6 -> 4.4468481 | AC10: ='Opex Forecast'!E7 -> 4.4616709 | AD10: ='Opex Forecast'!E8 -> 4.4765431 | AE10: ='Opex Forecast'!E9 -> 4.491465 | AF10: ='Opex Forecast'!E10 -> 4.5064365 | AG10: ='Opex Forecast'!E11 -> 4.521458 | AH10: ='Opex Forecast'!E12 -> 4.5365295 | AI10: ='Opex Forecast'!E13 -> 4.5516513 | AJ10: ='Opex Forecast'!E14 -> 4.5668234 | AK10: ='Opex Forecast'!E15 -> 4.5820462 | AL10: =SUM(B10:M10) -> 40.656 | AM10: =SUM(N10:Y10) -> 45.056 | AN10: =SUM(Z10:AK10) -> 53.990896
A11: Travel + Marketing + Other Opex | B11: =SUMIFS(Actuals!$N$4:$N$123,Actuals!$A$4:$A$123,B$3)+SUMIFS(Actuals!$O$4:$O$123,Actuals!$A$4:$A$123,B$3)+SUMIFS(Actuals!$P$4:$P$123,Actuals!$A$4:$A$123,B$3) -> 4.1980362 | C11: =SUMIFS(Actuals!$N$4:$N$123,Actuals!$A$4:$A$123,C$3)+SUMIFS(Actuals!$O$4:$O$123,Actuals!$A$4:$A$123,C$3)+SUMIFS(Actuals!$P$4:$P$123,Actuals!$A$4:$A$123,C$3) -> 4.5959199 | D11: =SUMIFS(Actuals!$N$4:$N$123,Actuals!$A$4:$A$123,D$3)+SUMIFS(Actuals!$O$4:$O$123,Actuals!$A$4:$A$123,D$3)+SUMIFS(Actuals!$P$4:$P$123,Actuals!$A$4:$A$123,D$3) -> 4.6706055 | E11: =SUMIFS(Actuals!$N$4:$N$123,Actuals!$A$4:$A$123,E$3)+SUMIFS(Actuals!$O$4:$O$123,Actuals!$A$4:$A$123,E$3)+SUMIFS(Actuals!$P$4:$P$123,Actuals!$A$4:$A$123,E$3) -> 4.2389522 | F11: =SUMIFS(Actuals!$N$4:$N$123,Actuals!$A$4:$A$123,F$3)+SUMIFS(Actuals!$O$4:$O$123,Actuals!$A$4:$A$123,F$3)+SUMIFS(Actuals!$P$4:$P$123,Actuals!$A$4:$A$123,F$3) -> 4.4190365 | G11: =SUMIFS(Actuals!$N$4:$N$123,Actuals!$A$4:$A$123,G$3)+SUMIFS(Actuals!$O$4:$O$123,Actuals!$A$4:$A$123,G$3)+SUMIFS(Actuals!$P$4:$P$123,Actuals!$A$4:$A$123,G$3) -> 4.4918282 | H11: =SUMIFS(Actuals!$N$4:$N$123,Actuals!$A$4:$A$123,H$3)+SUMIFS(Actuals!$O$4:$O$123,Actuals!$A$4:$A$123,H$3)+SUMIFS(Actuals!$P$4:$P$123,Actuals!$A$4:$A$123,H$3) -> 4.5420006 | I11: =SUMIFS(Actuals!$N$4:$N$123,Actuals!$A$4:$A$123,I$3)+SUMIFS(Actuals!$O$4:$O$123,Actuals!$A$4:$A$123,I$3)+SUMIFS(Actuals!$P$4:$P$123,Actuals!$A$4:$A$123,I$3) -> 4.6177457 | ... Y11: =SUMIFS(Actuals!$N$4:$N$123,Actuals!$A$4:$A$123,Y$3)+SUMIFS(Actuals!$O$4:$O$123,Actuals!$A$4:$A$123,Y$3)+SUMIFS(Actuals!$P$4:$P$123,Actuals!$A$4:$A$123,Y$3) -> 5.5655414 | Z11: ='Opex Forecast'!F4 -> 7.8616721 | AA11: ='Opex Forecast'!F5 -> 7.8878777 | AB11: ='Opex Forecast'!F6 -> 7.9141706 | AC11: ='Opex Forecast'!F7 -> 7.9405512 | AD11: ='Opex Forecast'!F8 -> 7.9670197 | AE11: ='Opex Forecast'!F9 -> 7.9935764 | AF11: ='Opex Forecast'!F10 -> 8.0202217 | AG11: ='Opex Forecast'!F11 -> 8.0469557 | AH11: ='Opex Forecast'!F12 -> 8.0737789 | AI11: ='Opex Forecast'!F13 -> 8.1006915 | AJ11: ='Opex Forecast'!F14 -> 8.1276938 | AK11: ='Opex Forecast'!F15 -> 8.1547861 | AL11: =SUM(B11:M11) -> 55.675818 | AM11: =SUM(N11:Y11) -> 66.09189 | AN11: =SUM(Z11:AK11) -> 96.088996
A12: EBITDA | B12: =SUMIFS(Actuals!$T$4:$T$123,Actuals!$A$4:$A$123,B$3) -> 35.62632 | C12: 35.559944 | D12: 36.66351 | E12: 34.560543 | F12: 38.668007 | G12: 39.653357 | H12: 40.302895 | I12: 41.364517 | J12: 44.153686 | K12: 45.292438 | L12: 43.626823 | M12: 40.997745 | N12: 44.270067 | O12: 44.565589 | P12: 45.655222 | Q12: 41.788095 | R12: 46.6388 | S12: 47.787236 | T12: 49.658454 | U12: 50.198411 | V12: 52.759221 | W12: 53.579609 | X12: 53.209119 | Y12: 49.890575 | Z12: 51.179484 | AA12: 51.350082 | AB12: 51.521249 | AC12: 51.692986 | AD12: 51.865296 | AE12: 52.038181 | AF12: 52.211641 | AG12: 52.38568 | AH12: 52.560299 | AI12: 52.7355 | AJ12: 52.911285 | AK12: 53.087656 | AL12: 476.46978 | AM12: 580.0004 | AN12: =AN7-AN9-AN10-AN11 -> 625.53934
A13: EBITDA Margin % | B13: =IFERROR(B12/B4,0) -> 0.30551131 | C13: =IFERROR(C12/C4,0) -> 0.30175413 | D13: =IFERROR(D12/D4,0) -> 0.3061438 | E13: =IFERROR(E12/E4,0) -> 0.29351111 | F13: =IFERROR(F12/F4,0) -> 0.31501171 | G13: =IFERROR(G12/G4,0) -> 0.31780398 | H13: =IFERROR(H12/H4,0) -> 0.31944166 | I13: =IFERROR(I12/I4,0) -> 0.32247826 | ... AM13: =IFERROR(AM12/AM4,0) -> 0.32475156 | AN13: =AN12/AN4 -> 0.30759749

Sheet P&L- Detailed View
A1: Monthly P&L by Business Unit (₹m)
A2: Case Selected: | B2: =Assumptions!B3 -> Base
A3: Business Unit / Line Item | B3: 45658 | C3: 45689 | D3: 45717 | E3: 45748 | F3: 45778 | G3: 45809 | H3: 45839 | I3: 45870 | J3: 45901 | K3: 45931 | L3: 45962 | M3: 45992 | N3: 46023 | O3: 46054 | P3: 46082 | Q3: 46113 | R3: 46143 | S3: 46174 | T3: 46204 | U3: 46235 | V3: 46266 | W3: 46296 | X3: 46327 | Y3: 46357 | Z3: 46388 | AA3: 46419 | AB3: 46447 | AC3: 46478 | AD3: 46508 | AE3: 46539 | AF3: 46569 | AG3: 46600 | AH3: 46631 | AI3: 46661 | AJ3: 46692 | AK3: 46722
A4: Cloud Services — Revenue | B4: =SUMIFS(Actuals!$I$4:$I$123,Actuals!$D$4:$D$123,"Cloud Services",Actuals!$A$4:$A$123,B$3) -> 24.338836 | C4: 24.706962 | D4: 24.899863 | E4: 24.497568 | F4: 25.833514 | G4: 25.727615 | H4: 26.111648 | I4: 26.233833 | J4: 27.249722 | K4: 27.686496 | L4: 27.494707 | M4: 26.696697 | N4: 28.753731 | O4: 28.619838 | P4: 28.765513 | Q4: 28.341106 | R4: 29.325206 | S4: 29.758564 | T4: 30.332252 | U4: 30.640843 | V4: 31.195636 | W4: 31.649857 | X4: 31.615074 | Y4: 30.444454 | Z4: 35.114903 | AA4: 35.231953 | AB4: 35.349393 | AC4: 35.467224 | AD4: 35.585448 | AE4: 35.704067 | AF4: 35.82308 | AG4: 35.94249 | AH4: 36.062299 | AI4: 36.182506 | AJ4: 36.303115 | AK4: 36.424125
A5: Personnel Cost | B5: =SUMIFS(Actuals!$J$4:$J$123,Actuals!$D$4:$D$123,"Cloud Services",Actuals!$A$4:$A$123,B$3) -> 12.6 | C5: =SUMIFS(Actuals!$J$4:$J$123,Actuals!$D$4:$D$123,"Cloud Services",Actuals!$A$4:$A$123,C$3) -> 12.705 | D5: =SUMIFS(Actuals!$J$4:$J$123,Actuals!$D$4:$D$123,"Cloud Services",Actuals!$A$4:$A$123,D$3) -> 12.81 | E5: =SUMIFS(Actuals!$J$4:$J$123,Actuals!$D$4:$D$123,"Cloud Services",Actuals!$A$4:$A$123,E$3) -> 12.915 | F5: =SUMIFS(Actuals!$J$4:$J$123,Actuals!$D$4:$D$123,"Cloud Services",Actuals!$A$4:$A$123,F$3) -> 12.915 | G5: =SUMIFS(Actuals!$J$4:$J$123,Actuals!$D$4:$D$123,"Cloud Services",Actuals!$A$4:$A$123,G$3) -> 13.02 | H5: =SUMIFS(Actuals!$J$4:$J$123,Actuals!$D$4:$D$123,"Cloud Services",Actuals!$A$4:$A$123,H$3) -> 13.125 | I5: =SUMIFS(Actuals!$J$4:$J$123,Actuals!$D$4:$D$123,"Cloud Services",Actuals!$A$4:$A$123,I$3) -> 13.23 | ... Y5: =SUMIFS(Actuals!$J$4:$J$123,Actuals!$D$4:$D$123,"Cloud Services",Actuals!$A$4:$A$123,Y$3) -> 15.4707 | Z5: ='Headcount Plan'!K4 -> 17.704959 | AA5: ='Headcount Plan'!K9 -> 17.763976 | AB5: ='Headcount Plan'!K14 -> 17.823189 | AC5: ='Headcount Plan'!K19 -> 17.8826 | AD5: ='Headcount Plan'!K24 -> 17.942208 | AE5: ='Headcount Plan'!K29 -> 18.002016 | AF5: ='Headcount Plan'!K34 -> 18.062022 | AG5: ='Headcount Plan'!K39 -> 18.122229 | AH5: ='Headcount Plan'!K44 -> 18.182636 | AI5: ='Headcount Plan'!K49 -> 18.243245 | AJ5: ='Headcount Plan'!K54 -> 18.304056 | AK5: ='Headcount Plan'!K59 -> 18.36507 | AL5: =SUM(C5:M5) -> 144.48 | AM5: =SUM(N5:Y5) -> 179.8608 | AN5: =SUM(Z5:AK5) -> 216.39821
A6: Subcontractor Cost | B6: =SUMIFS(Actuals!$K$4:$K$123,Actuals!$D$4:$D$123,"Cloud Services",Actuals!$A$4:$A$123,B$3) -> 1.5820244 | C6: =SUMIFS(Actuals!$K$4:$K$123,Actuals!$D$4:$D$123,"Cloud Services",Actuals!$A$4:$A$123,C$3) -> 1.6059525 | D6: =SUMIFS(Actuals!$K$4:$K$123,Actuals!$D$4:$D$123,"Cloud Services",Actuals!$A$4:$A$123,D$3) -> 1.6184911 | E6: =SUMIFS(Actuals!$K$4:$K$123,Actuals!$D$4:$D$123,"Cloud Services",Actuals!$A$4:$A$123,E$3) -> 1.5923419 | F6: =SUMIFS(Actuals!$K$4:$K$123,Actuals!$D$4:$D$123,"Cloud Services",Actuals!$A$4:$A$123,F$3) -> 1.6791784 | G6: =SUMIFS(Actuals!$K$4:$K$123,Actuals!$D$4:$D$123,"Cloud Services",Actuals!$A$4:$A$123,G$3) -> 1.6722949 | H6: =SUMIFS(Actuals!$K$4:$K$123,Actuals!$D$4:$D$123,"Cloud Services",Actuals!$A$4:$A$123,H$3) -> 1.6972571 | I6: =SUMIFS(Actuals!$K$4:$K$123,Actuals!$D$4:$D$123,"Cloud Services",Actuals!$A$4:$A$123,I$3) -> 1.7051991 | ... Y6: =SUMIFS(Actuals!$K$4:$K$123,Actuals!$D$4:$D$123,"Cloud Services",Actuals!$A$4:$A$123,Y$3) -> 1.9788895 | Z6: =Z4*Assumptions!$B$23 -> 2.6336178 | AA6: =AA4*Assumptions!$B$23 -> 2.6423965 | AB6: =AB4*Assumptions!$B$23 -> 2.6512045 | AC6: =AC4*Assumptions!$B$23 -> 2.6600418 | AD6: =AD4*Assumptions!$B$23 -> 2.6689086 | AE6: =AE4*Assumptions!$B$23 -> 2.677805 | AF6: =AF4*Assumptions!$B$23 -> 2.686731 | AG6: =AG4*Assumptions!$B$23 -> 2.6956868 | ... AK6: =AK4*Assumptions!$B$23 -> 2.7318094 | AL6: =SUM(C6:M6) -> 18.664011 | AM6: =SUM(N6:Y6) -> 23.363735 | AN6: =SUM(Z6:AK6) -> 32.189295
A7: Gross Profit | B7: =B4-B5-B6 -> 10.156812 | C7: =C4-C5-C6 -> 10.396009 | D7: =D4-D5-D6 -> 10.471372 | E7: =E4-E5-E6 -> 9.9902262 | F7: =F4-F5-F6 -> 11.239336 | G7: =G4-G5-G6 -> 11.03532 | H7: =H4-H5-H6 -> 11.289391 | I7: =I4-I5-I6 -> 11.298633 | ... AK7: =AK4-AK5-AK6 -> 15.327246 | AL7: =SUM(C7:M7) -> 123.99461 | AM7: =SUM(N7:Y7) -> 156.21754 | AN7: =SUM(Z7:AK7) -> 180.6031
A8: Gross Margin % | B8: =IFERROR(B7/B4,0) -> 0.41730886 | C8: =IFERROR(C7/C4,0) -> 0.42077247 | D8: =IFERROR(D7/D4,0) -> 0.42053933 | E8: =IFERROR(E7/E4,0) -> 0.40780481 | F8: =IFERROR(F7/F4,0) -> 0.43506801 | G8: =IFERROR(G7/G4,0) -> 0.42892899 | H8: =IFERROR(H7/H4,0) -> 0.43235076 | I8: =IFERROR(I7/I4,0) -> 0.43068939 | ... AK8: =IFERROR(AK7/AK4,0) -> 0.42079929 | AL8: =SUM(C8:M8) -> 4.7451683 | AM8: =SUM(N8:Y8) -> 5.2109036 | AN8: =SUM(Z8:AK8) -> 5.0495915
A9: Software Cost | B9: =SUMIFS(Actuals!$L$4:$L$123,Actuals!$D$4:$D$123,"Cloud Services",Actuals!$A$4:$A$123,B$3) -> 1.08 | C9: =SUMIFS(Actuals!$L$4:$L$123,Actuals!$D$4:$D$123,"Cloud Services",Actuals!$A$4:$A$123,C$3) -> 1.089 | D9: =SUMIFS(Actuals!$L$4:$L$123,Actuals!$D$4:$D$123,"Cloud Services",Actuals!$A$4:$A$123,D$3) -> 1.098 | E9: =SUMIFS(Actuals!$L$4:$L$123,Actuals!$D$4:$D$123,"Cloud Services",Actuals!$A$4:$A$123,E$3) -> 1.107 | F9: =SUMIFS(Actuals!$L$4:$L$123,Actuals!$D$4:$D$123,"Cloud Services",Actuals!$A$4:$A$123,F$3) -> 1.107 | G9: =SUMIFS(Actuals!$L$4:$L$123,Actuals!$D$4:$D$123,"Cloud Services",Actuals!$A$4:$A$123,G$3) -> 1.116 | H9: =SUMIFS(Actuals!$L$4:$L$123,Actuals!$D$4:$D$123,"Cloud Services",Actuals!$A$4:$A$123,H$3) -> 1.125 | I9: =SUMIFS(Actuals!$L$4:$L$123,Actuals!$D$4:$D$123,"Cloud Services",Actuals!$A$4:$A$123,I$3) -> 1.134 | ... Y9: =SUMIFS(Actuals!$L$4:$L$123,Actuals!$D$4:$D$123,"Cloud Services",Actuals!$A$4:$A$123,Y$3) -> 1.31355 | Z9: ='Headcount Plan'!G4*Assumptions!G13*(1+Assumptions!$B$9) -> 1.5250375 | AA9: ='Headcount Plan'!G9*Assumptions!G13*(1+Assumptions!$B$9) -> 1.530121 | AB9: ='Headcount Plan'!G14*Assumptions!G13*(1+Assumptions!$B$9) -> 1.5352214 | AC9: ='Headcount Plan'!G19*Assumptions!G13*(1+Assumptions!$B$9) -> 1.5403388 | AD9: ='Headcount Plan'!G24*Assumptions!G13*(1+Assumptions!$B$9) -> 1.5454732 | AE9: ='Headcount Plan'!G29*Assumptions!G13*(1+Assumptions!$B$9) -> 1.5506248 | AF9: ='Headcount Plan'!G34*Assumptions!G13*(1+Assumptions!$B$9) -> 1.5557936 | AG9: ='Headcount Plan'!G39*Assumptions!G13*(1+Assumptions!$B$9) -> 1.5609795 | AH9: ='Headcount Plan'!G44*Assumptions!G13*(1+Assumptions!$B$9) -> 1.5661828 | AI9: ='Headcount Plan'!G49*Assumptions!G13*(1+Assumptions!$B$9) -> 1.5714034 | AJ9: ='Headcount Plan'!G54*Assumptions!G13*(1+Assumptions!$B$9) -> 1.5766414 | AK9: ='Headcount Plan'!G59*Assumptions!G13*(1+Assumptions!$B$9) -> 1.5818969 | AL9: =SUM(C9:M9) -> 12.384 | AM9: =SUM(N9:Y9) -> 15.2712 | AN9: =SUM(Z9:AK9) -> 18.639714
A10: Facilities Cost | B10: =SUMIFS(Actuals!$M$4:$M$123,Actuals!$D$4:$D$123,"Cloud Services",Actuals!$A$4:$A$123,B$3) -> 0.66 | C10: 0.6655 | D10: 0.671 | E10: 0.6765 | F10: 0.6765 | G10: 0.682 | H10: 0.6875 | I10: 0.693 | J10: 0.6985 | K10: 0.704 | L10: 0.704 | M10: 0.7095 | N10: 0.715 | O10: 0.7205 | P10: 0.726 | Q10: 0.7315 | R10: 0.7315 | S10: 0.737 | T10: 0.7425 | U10: 0.748 | V10: 0.7535 | W10: 0.759 | X10: 0.759 | Y10: 0.7645 | Z10: 0.9150225 | AA10: 0.91807258 | AB10: 0.92113282 | AC10: 0.92420326 | AD10: 0.92728394 | AE10: 0.93037488 | AF10: 0.93347613 | AG10: 0.93658772 | AH10: 0.93970968 | AI10: 0.94284205 | AJ10: 0.94598485 | AK10: 0.94913813 | AL10: =SUM(C10:M10) -> 7.568 | AM10: =SUM(N10:Y10) -> 8.888 | AN10: =SUM(Z10:AK10) -> 11.183829
A11: Other Opex | B11: =SUMIFS(Actuals!$N$4:$N$123,Actuals!$D$4:$D$123,"Cloud Services",Actuals!$A$4:$A$123,B$3)+SUMIFS(Actuals!$O$4:$O$123,Actuals!$D$4:$D$123,"Cloud Services",Actuals!$A$4:$A$123,B$3)+SUMIFS(Actuals!$P$4:$P$123,Actuals!$D$4:$D$123,"Cloud Services",Actuals!$A$4:$A$123,B$3) -> 0.87619811 | C11: =SUMIFS(Actuals!$N$4:$N$123,Actuals!$D$4:$D$123,"Cloud Services",Actuals!$A$4:$A$123,C$3)+SUMIFS(Actuals!$O$4:$O$123,Actuals!$D$4:$D$123,"Cloud Services",Actuals!$A$4:$A$123,C$3)+SUMIFS(Actuals!$P$4:$P$123,Actuals!$D$4:$D$123,"Cloud Services",Actuals!$A$4:$A$123,C$3) -> 0.96357151 | D11: =SUMIFS(Actuals!$N$4:$N$123,Actuals!$D$4:$D$123,"Cloud Services",Actuals!$A$4:$A$123,D$3)+SUMIFS(Actuals!$O$4:$O$123,Actuals!$D$4:$D$123,"Cloud Services",Actuals!$A$4:$A$123,D$3)+SUMIFS(Actuals!$P$4:$P$123,Actuals!$D$4:$D$123,"Cloud Services",Actuals!$A$4:$A$123,D$3) -> 0.97109465 | E11: =SUMIFS(Actuals!$N$4:$N$123,Actuals!$D$4:$D$123,"Cloud Services",Actuals!$A$4:$A$123,E$3)+SUMIFS(Actuals!$O$4:$O$123,Actuals!$D$4:$D$123,"Cloud Services",Actuals!$A$4:$A$123,E$3)+SUMIFS(Actuals!$P$4:$P$123,Actuals!$D$4:$D$123,"Cloud Services",Actuals!$A$4:$A$123,E$3) -> 0.88191245 | F11: =SUMIFS(Actuals!$N$4:$N$123,Actuals!$D$4:$D$123,"Cloud Services",Actuals!$A$4:$A$123,F$3)+SUMIFS(Actuals!$O$4:$O$123,Actuals!$D$4:$D$123,"Cloud Services",Actuals!$A$4:$A$123,F$3)+SUMIFS(Actuals!$P$4:$P$123,Actuals!$D$4:$D$123,"Cloud Services",Actuals!$A$4:$A$123,F$3) -> 0.9300065 | G11: =SUMIFS(Actuals!$N$4:$N$123,Actuals!$D$4:$D$123,"Cloud Services",Actuals!$A$4:$A$123,G$3)+SUMIFS(Actuals!$O$4:$O$123,Actuals!$D$4:$D$123,"Cloud Services",Actuals!$A$4:$A$123,G$3)+SUMIFS(Actuals!$P$4:$P$123,Actuals!$D$4:$D$123,"Cloud Services",Actuals!$A$4:$A$123,G$3) -> 0.92619412 | H11: =SUMIFS(Actuals!$N$4:$N$123,Actuals!$D$4:$D$123,"Cloud Services",Actuals!$A$4:$A$123,H$3)+SUMIFS(Actuals!$O$4:$O$123,Actuals!$D$4:$D$123,"Cloud Services",Actuals!$A$4:$A$123,H$3)+SUMIFS(Actuals!$P$4:$P$123,Actuals!$D$4:$D$123,"Cloud Services",Actuals!$A$4:$A$123,H$3) -> 0.94001933 | I11: =SUMIFS(Actuals!$N$4:$N$123,Actuals!$D$4:$D$123,"Cloud Services",Actuals!$A$4:$A$123,I$3)+SUMIFS(Actuals!$O$4:$O$123,Actuals!$D$4:$D$123,"Cloud Services",Actuals!$A$4:$A$123,I$3)+SUMIFS(Actuals!$P$4:$P$123,Actuals!$D$4:$D$123,"Cloud Services",Actuals!$A$4:$A$123,I$3) -> 0.94441797 | ... Y11: =SUMIFS(Actuals!$N$4:$N$123,Actuals!$D$4:$D$123,"Cloud Services",Actuals!$A$4:$A$123,Y$3)+SUMIFS(Actuals!$O$4:$O$123,Actuals!$D$4:$D$123,"Cloud Services",Actuals!$A$4:$A$123,Y$3)+SUMIFS(Actuals!$P$4:$P$123,Actuals!$D$4:$D$123,"Cloud Services",Actuals!$A$4:$A$123,Y$3) -> 1.0960004 | Z11: =Z4*Assumptions!$B$25*(1+Assumptions!$B$9) -> 1.6591792 | AA11: =AA4*Assumptions!$B$25*(1+Assumptions!$B$9) -> 1.6647098 | AB11: =AB4*Assumptions!$B$25*(1+Assumptions!$B$9) -> 1.6702588 | AC11: =AC4*Assumptions!$B$25*(1+Assumptions!$B$9) -> 1.6758263 | AD11: =AD4*Assumptions!$B$25*(1+Assumptions!$B$9) -> 1.6814124 | AE11: =AE4*Assumptions!$B$25*(1+Assumptions!$B$9) -> 1.6870171 | AF11: =AF4*Assumptions!$B$25*(1+Assumptions!$B$9) -> 1.6926405 | AG11: =AG4*Assumptions!$B$25*(1+Assumptions!$B$9) -> 1.6982827 | ... AK11: =AK4*Assumptions!$B$25*(1+Assumptions!$B$9) -> 1.7210399 | AL11: =SUM(C11:M11) -> 10.65062 | AM11: =SUM(N11:Y11) -> 13.300607 | AN11: =SUM(Z11:AK11) -> 20.279256
A12: EBITDA | B12: =B7-B9-B10-B11 -> 7.540614 | C12: =C7-C9-C10-C11 -> 7.6779377 | D12: =D7-D9-D10-D11 -> 7.731277 | E12: =E7-E9-E10-E11 -> 7.3248137 | F12: =F7-F9-F10-F11 -> 8.525829 | G12: =G7-G9-G10-G11 -> 8.3111255 | H12: =H7-H9-H10-H11 -> 8.5368717 | I12: =I7-I9-I10-I11 -> 8.5272155 | ... AK12: =AK7-AK9-AK10-AK11 -> 11.075171 | AL12: =SUM(C12:M12) -> 93.391993 | AM12: =SUM(N12:Y12) -> 118.75773 | AN12: =SUM(Z12:AK12) -> 130.5003
A13: EBITDA Margin % | B13: =IFERROR(B12/B4,0) -> 0.30981818 | C13: =IFERROR(C12/C4,0) -> 0.31076009 | D13: =IFERROR(D12/D4,0) -> 0.31049477 | E13: =IFERROR(E12/E4,0) -> 0.29900167 | F13: =IFERROR(F12/F4,0) -> 0.33002978 | G13: =IFERROR(G12/G4,0) -> 0.32304299 | H13: =IFERROR(H12/H4,0) -> 0.3269373 | I13: =IFERROR(I12/I4,0) -> 0.3250465 | ... AK13: =IFERROR(AK12/AK4,0) -> 0.30406142 | AL13: =SUM(C13:M13) -> 3.5721439 | AM13: =SUM(N13:Y13) -> 3.9597519 | AN13: =SUM(Z13:AK13) -> 3.648737
AL14: =SUM(C14:M14) -> 0 | AM14: =SUM(N14:Y14) -> 0 | AN14: =SUM(Z14:AK14) -> 0
AL15: =SUM(C15:M15) -> 0 | AM15: =SUM(N15:Y15) -> 0 | AN15: =SUM(Z15:AK15) -> 0
A16: Data & Analytics — Revenue | B16: =SUMIFS(Actuals!$I$4:$I$123,Actuals!$D$4:$D$123,"Data & Analytics",Actuals!$A$4:$A$123,B$3) -> 23.170455 | C16: 23.217227 | D16: 23.598756 | E16: 23.461296 | F16: 24.039083 | G16: 24.541667 | H16: 24.949678 | I16: 25.486364 | J16: 25.871694 | K16: 26.37718 | L16: 26.058331 | M16: 25.56479 | N16: 27.196933 | O16: 27.888025 | P16: 28.215856 | Q16: 27.26836 | R16: 28.400421 | S16: 28.965155 | T16: 29.663865 | U16: 29.4705 | V16: 30.365349 | W16: 30.652095 | X16: 30.617856 | Y16: 30.219387 | Z16: 33.925248 | AA16: 34.038332 | AB16: 34.151793 | AC16: 34.265633 | AD16: 34.379851 | AE16: 34.494451 | AF16: 34.609432 | AG16: 34.724797 | AH16: 34.840546 | AI16: 34.956682 | AJ16: 35.073204 | AK16: 35.190115 | AL16: =SUM(C16:M16) -> 273.16607 | AM16: =SUM(N16:Y16) -> 348.9238 | AN16: =SUM(Z16:AK16) -> 414.65008
A17: Personnel Cost | B17: =SUMIFS(Actuals!$J$4:$J$123,Actuals!$D$4:$D$123,"Data & Analytics",Actuals!$A$4:$A$123,B$3) -> 11.22 | C17: =SUMIFS(Actuals!$J$4:$J$123,Actuals!$D$4:$D$123,"Data & Analytics",Actuals!$A$4:$A$123,C$3) -> 11.33 | D17: =SUMIFS(Actuals!$J$4:$J$123,Actuals!$D$4:$D$123,"Data & Analytics",Actuals!$A$4:$A$123,D$3) -> 11.44 | E17: =SUMIFS(Actuals!$J$4:$J$123,Actuals!$D$4:$D$123,"Data & Analytics",Actuals!$A$4:$A$123,E$3) -> 11.55 | F17: =SUMIFS(Actuals!$J$4:$J$123,Actuals!$D$4:$D$123,"Data & Analytics",Actuals!$A$4:$A$123,F$3) -> 11.55 | G17: =SUMIFS(Actuals!$J$4:$J$123,Actuals!$D$4:$D$123,"Data & Analytics",Actuals!$A$4:$A$123,G$3) -> 11.66 | H17: =SUMIFS(Actuals!$J$4:$J$123,Actuals!$D$4:$D$123,"Data & Analytics",Actuals!$A$4:$A$123,H$3) -> 11.77 | I17: =SUMIFS(Actuals!$J$4:$J$123,Actuals!$D$4:$D$123,"Data & Analytics",Actuals!$A$4:$A$123,I$3) -> 11.88 | ... Y17: =SUMIFS(Actuals!$J$4:$J$123,Actuals!$D$4:$D$123,"Data & Analytics",Actuals!$A$4:$A$123,Y$3) -> 14.2252 | Z17: ='Headcount Plan'!K5 -> 15.9265 | AA17: ='Headcount Plan'!K10 -> 15.979588 | AB17: ='Headcount Plan'!K15 -> 16.032854 | AC17: ='Headcount Plan'!K20 -> 16.086296 | AD17: ='Headcount Plan'!K25 -> 16.139917 | AE17: ='Headcount Plan'!K30 -> 16.193717 | AF17: ='Headcount Plan'!K35 -> 16.247696 | AG17: ='Headcount Plan'!K40 -> 16.301855 | AH17: ='Headcount Plan'!K45 -> 16.356195 | AI17: ='Headcount Plan'!K50 -> 16.410715 | AJ17: ='Headcount Plan'!K55 -> 16.465418 | AK17: ='Headcount Plan'!K60 -> 16.520303 | AL17: =SUM(C17:M17) -> 129.8 | AM17: =SUM(N17:Y17) -> 163.823 | AN17: =SUM(Z17:AK17) -> 194.66105
A18: Subcontractor Cost | B18: =SUMIFS(Actuals!$K$4:$K$123,Actuals!$D$4:$D$123,"Data & Analytics",Actuals!$A$4:$A$123,B$3) -> 1.5987614 | C18: =SUMIFS(Actuals!$K$4:$K$123,Actuals!$D$4:$D$123,"Data & Analytics",Actuals!$A$4:$A$123,C$3) -> 1.6019887 | D18: =SUMIFS(Actuals!$K$4:$K$123,Actuals!$D$4:$D$123,"Data & Analytics",Actuals!$A$4:$A$123,D$3) -> 1.6283142 | E18: =SUMIFS(Actuals!$K$4:$K$123,Actuals!$D$4:$D$123,"Data & Analytics",Actuals!$A$4:$A$123,E$3) -> 1.6188295 | F18: =SUMIFS(Actuals!$K$4:$K$123,Actuals!$D$4:$D$123,"Data & Analytics",Actuals!$A$4:$A$123,F$3) -> 1.6586967 | G18: =SUMIFS(Actuals!$K$4:$K$123,Actuals!$D$4:$D$123,"Data & Analytics",Actuals!$A$4:$A$123,G$3) -> 1.693375 | H18: =SUMIFS(Actuals!$K$4:$K$123,Actuals!$D$4:$D$123,"Data & Analytics",Actuals!$A$4:$A$123,H$3) -> 1.7215277 | I18: =SUMIFS(Actuals!$K$4:$K$123,Actuals!$D$4:$D$123,"Data & Analytics",Actuals!$A$4:$A$123,I$3) -> 1.7585591 | ... Y18: =SUMIFS(Actuals!$K$4:$K$123,Actuals!$D$4:$D$123,"Data & Analytics",Actuals!$A$4:$A$123,Y$3) -> 2.0851377 | Z18: =Z16*Assumptions!$B$23 -> 2.5443936 | AA18: =AA16*Assumptions!$B$23 -> 2.5528749 | AB18: =AB16*Assumptions!$B$23 -> 2.5613845 | AC18: =AC16*Assumptions!$B$23 -> 2.5699224 | AD18: =AD16*Assumptions!$B$23 -> 2.5784889 | AE18: =AE16*Assumptions!$B$23 -> 2.5870838 | AF18: =AF16*Assumptions!$B$23 -> 2.5957074 | AG18: =AG16*Assumptions!$B$23 -> 2.6043598 | ... AK18: =AK16*Assumptions!$B$23 -> 2.6392586 | AL18: =SUM(C18:M18) -> 18.848459 | AM18: =SUM(N18:Y18) -> 24.075742 | AN18: =SUM(Z18:AK18) -> 31.098756
A19: Gross Profit | B19: =B16-B17-B18 -> 10.351693 | C19: =C16-C17-C18 -> 10.285238 | D19: =D16-D17-D18 -> 10.530442 | E19: =E16-E17-E18 -> 10.292467 | F19: =F16-F17-F18 -> 10.830386 | G19: =G16-G17-G18 -> 11.188292 | H19: =H16-H17-H18 -> 11.45815 | I19: =I16-I17-I18 -> 11.847805 | ... AK19: =AK16-AK17-AK18 -> 16.030553 | AL19: =SUM(C19:M19) -> 124.51761 | AM19: =SUM(N19:Y19) -> 161.02506 | AN19: =SUM(Z19:AK19) -> 188.89027
A20: Gross Margin % | B20: =IFERROR(B19/B16,0) -> 0.44676263 | C20: =IFERROR(C19/C16,0) -> 0.44300029 | D20: =IFERROR(D19/D16,0) -> 0.44622868 | E20: =IFERROR(E19/E16,0) -> 0.43869984 | F20: =IFERROR(F19/F16,0) -> 0.45053242 | G20: =IFERROR(G19/G16,0) -> 0.45588966 | H20: =IFERROR(H19/H16,0) -> 0.45925042 | I20: =IFERROR(I19/I16,0) -> 0.46486838 | ... AK20: =IFERROR(AK19/AK16,0) -> 0.45554138 | AL20: =SUM(C20:M20) -> 5.009822 | AM20: =SUM(N20:Y20) -> 5.5336585 | AN20: =SUM(Z20:AK20) -> 5.4664966
A21: Software Cost | B21: =SUMIFS(Actuals!$L$4:$L$123,Actuals!$D$4:$D$123,"Data & Analytics",Actuals!$A$4:$A$123,B$3) -> 1.02 | C21: =SUMIFS(Actuals!$L$4:$L$123,Actuals!$D$4:$D$123,"Data & Analytics",Actuals!$A$4:$A$123,C$3) -> 1.03 | D21: =SUMIFS(Actuals!$L$4:$L$123,Actuals!$D$4:$D$123,"Data & Analytics",Actuals!$A$4:$A$123,D$3) -> 1.04 | E21: =SUMIFS(Actuals!$L$4:$L$123,Actuals!$D$4:$D$123,"Data & Analytics",Actuals!$A$4:$A$123,E$3) -> 1.05 | F21: =SUMIFS(Actuals!$L$4:$L$123,Actuals!$D$4:$D$123,"Data & Analytics",Actuals!$A$4:$A$123,F$3) -> 1.05 | G21: =SUMIFS(Actuals!$L$4:$L$123,Actuals!$D$4:$D$123,"Data & Analytics",Actuals!$A$4:$A$123,G$3) -> 1.06 | H21: =SUMIFS(Actuals!$L$4:$L$123,Actuals!$D$4:$D$123,"Data & Analytics",Actuals!$A$4:$A$123,H$3) -> 1.07 | I21: =SUMIFS(Actuals!$L$4:$L$123,Actuals!$D$4:$D$123,"Data & Analytics",Actuals!$A$4:$A$123,I$3) -> 1.08 | ... Y21: =SUMIFS(Actuals!$L$4:$L$123,Actuals!$D$4:$D$123,"Data & Analytics",Actuals!$A$4:$A$123,Y$3) -> 1.281 | Z21: ='Headcount Plan'!G5*Assumptions!G14*(1+Assumptions!$B$9) -> 1.4461563 | AA21: ='Headcount Plan'!G10*Assumptions!G14*(1+Assumptions!$B$9) -> 1.4509768 | AB21: ='Headcount Plan'!G15*Assumptions!G14*(1+Assumptions!$B$9) -> 1.4558134 | AC21: ='Headcount Plan'!G20*Assumptions!G14*(1+Assumptions!$B$9) -> 1.4606661 | AD21: ='Headcount Plan'!G25*Assumptions!G14*(1+Assumptions!$B$9) -> 1.465535 | AE21: ='Headcount Plan'!G30*Assumptions!G14*(1+Assumptions!$B$9) -> 1.4704201 | AF21: ='Headcount Plan'!G35*Assumptions!G14*(1+Assumptions!$B$9) -> 1.4753215 | AG21: ='Headcount Plan'!G40*Assumptions!G14*(1+Assumptions!$B$9) -> 1.4802392 | AH21: ='Headcount Plan'!G45*Assumptions!G14*(1+Assumptions!$B$9) -> 1.4851733 | AI21: ='Headcount Plan'!G50*Assumptions!G14*(1+Assumptions!$B$9) -> 1.4901239 | AJ21: ='Headcount Plan'!G55*Assumptions!G14*(1+Assumptions!$B$9) -> 1.495091 | AK21: ='Headcount Plan'!G60*Assumptions!G14*(1+Assumptions!$B$9) -> 1.5000746 | AL21: =SUM(C21:M21) -> 11.8 | AM21: =SUM(N21:Y21) -> 14.7525 | AN21: =SUM(Z21:AK21) -> 17.675591
A22: Facilities Cost | B22: =SUMIFS(Actuals!$M$4:$M$123,Actuals!$D$4:$D$123,"Data & Analytics",Actuals!$A$4:$A$123,B$3) -> 0.561 | C22: 0.5665 | D22: 0.572 | E22: 0.5775 | F22: 0.5775 | G22: 0.583 | H22: 0.5885 | I22: 0.594 | J22: 0.5995 | K22: 0.605 | L22: 0.6105 | M22: 0.616 | N22: 0.616 | O22: 0.6215 | P22: 0.627 | Q22: 0.6325 | R22: 0.638 | S22: 0.6435 | T22: 0.649 | U22: 0.649 | V22: 0.6545 | W22: 0.66 | X22: 0.6655 | Y22: 0.671 | Z22: 0.7888125 | AA22: 0.79144187 | AB22: 0.79408001 | AC22: 0.79672695 | AD22: 0.7993827 | AE22: 0.80204731 | AF22: 0.8047208 | AG22: 0.80740321 | AH22: 0.81009455 | AI22: 0.81279487 | AJ22: 0.81550418 | AK22: 0.81822253 | AL22: =SUM(C22:M22) -> 6.49 | AM22: =SUM(N22:Y22) -> 7.7275 | AN22: =SUM(Z22:AK22) -> 9.6412315
A23: Other Opex | B23: 0.83413636 | C23: 0.90547185 | D23: 0.92035148 | E23: 0.84460667 | F23: 0.86540699 | G23: 0.88350002 | H23: 0.89818839 | I23: 0.9175091 | J23: 1.0089961 | K23: 1.02871 | L23: 0.93809991 | M23: 0.92033245 | N23: 0.9790896 | O23: 1.087633 | P23: 1.1004184 | Q23: 0.98166098 | R23: 1.0224152 | S23: 1.0427456 | T23: 1.0678991 | U23: 1.060938 | V23: 1.1842486 | W23: 1.1954317 | X23: 1.1022428 | Y23: 1.0878979 | Z23: 1.602968 | AA23: 1.6083112 | AB23: 1.6136722 | AC23: 1.6190511 | AD23: 1.624448 | AE23: 1.6298628 | AF23: 1.6352957 | AG23: 1.6407467 | AH23: 1.6462158 | AI23: 1.6517032 | AJ23: 1.6572089 | AK23: 1.6627329 | AL23: =SUM(C23:M23) -> 10.131173 | AM23: =SUM(N23:Y23) -> 12.912621 | AN23: =SUM(Z23:AK23) -> 19.592216
A24: EBITDA | B24: 7.9365568 | C24: =C19-C21-C22-C23 -> 7.7832665 | D24: =D19-D21-D22-D23 -> 7.9980903 | E24: =E19-E21-E22-E23 -> 7.8203603 | F24: =F19-F21-F22-F23 -> 8.3374794 | G24: =G19-G21-G22-G23 -> 8.6617923 | H24: =H19-H21-H22-H23 -> 8.9014614 | I24: =I19-I21-I22-I23 -> 9.2562957 | J24: =J19-J21-J22-J23 -> 9.3980512 | ... AK24: =AK19-AK21-AK22-AK23 -> 12.049523 | AL24: =SUM(C24:M24) -> 96.096435 | AM24: =SUM(N24:Y24) -> 125.63244 | AN24: =SUM(Z24:AK24) -> 141.98123
A25: EBITDA Margin % | B25: 0.34252918 | C25: =IFERROR(C24/C16,0) -> 0.3352367 | D25: =IFERROR(D24/D16,0) -> 0.33892 | E25: =IFERROR(E24/E16,0) -> 0.33333027 | F25: =IFERROR(F24/F16,0) -> 0.34683017 | G25: =IFERROR(G24/G16,0) -> 0.35294229 | H25: =IFERROR(H24/H16,0) -> 0.35677661 | I25: =IFERROR(I24/I16,0) -> 0.3631862 | J25: =IFERROR(J24/J16,0) -> 0.36325612 | ... AK25: =IFERROR(AK24/AK16,0) -> 0.34241217 | AL25: =SUM(C25:M25) -> 3.8647015 | AM25: =SUM(N25:Y25) -> 4.3159581 | AN25: =SUM(Z25:AK25) -> 4.108946
C26: =C8-C14-C20 -> -0.022227827 | D26: =D8-D14-D20 -> -0.02568935 | E26: =E8-E14-E20 -> -0.030895027 | F26: =F8-F14-F20 -> -0.015464413 | G26: =G8-G14-G20 -> -0.026960671 | H26: =H8-H14-H20 -> -0.026899652 | I26: =I8-I14-I20 -> -0.034178989 | J26: =J8-J14-J20 -> -0.02192194 | ... AK26: =AK8-AK14-AK20 -> -0.034742091 | AL26: =SUM(C26:M26) -> -0.26465374 | AM26: =SUM(N26:Y26) -> -0.32275487 | AN26: =SUM(Z26:AK26) -> -0.41690509
C27: =C9-C15-C21 -> 0.059 | D27: =D9-D15-D21 -> 0.058 | E27: =E9-E15-E21 -> 0.057 | F27: =F9-F15-F21 -> 0.057 | G27: =G9-G15-G21 -> 0.056 | H27: =H9-H15-H21 -> 0.055 | I27: =I9-I15-I21 -> 0.054 | J27: =J9-J15-J21 -> 0.053 | ... AK27: =AK9-AK15-AK21 -> 0.081822253 | AL27: =SUM(C27:M27) -> 0.584 | AM27: =SUM(N27:Y27) -> 0.5187 | AN27: =SUM(Z27:AK27) -> 0.96412315
A28: Cybersecurity — Revenue | B28: =SUMIFS(Actuals!$I$4:$I$123,Actuals!$D$4:$D$123,"Cybersecurity",Actuals!$A$4:$A$123,B$3) -> 20.028277 | C28: 20.048426 | D28: 20.401907 | E28: 20.056819 | F28: 21.051405 | G28: 21.42969 | H28: 21.712971 | I28: 22.05967 | J28: 23.038555 | K28: 23.161402 | L28: 22.628132 | M28: 22.440877 | N28: 24.053568 | O28: 24.59519 | P28: 24.878782 | Q28: 24.227269 | R28: 25.113864 | S28: 25.61031 | T28: 26.019485 | U28: 26.490061 | V28: 27.078625 | W28: 27.276176 | X28: 27.284241 | Y28: 27.039391 | Z28: 29.311751 | AA28: 29.409457 | AB28: 29.507488 | AC28: 29.605846 | AD28: 29.704533 | AE28: 29.803548 | AF28: 29.902893 | AG28: 30.002569 | AH28: 30.102578 | AI28: 30.20292 | AJ28: 30.303596 | AK28: 30.404608 | AL28: =SUM(C28:M28) -> 238.02985 | AM28: =SUM(N28:Y28) -> 309.66696 | AN28: =SUM(Z28:AK28) -> 358.26179
A29: Personnel Cost | B29: 9.12 | C29: 9.24 | D29: 9.36 | E29: 9.36 | F29: 9.48 | G29: 9.6 | H29: 9.72 | I29: 9.84 | J29: 9.96 | K29: 9.96 | L29: 10.08 | M29: 10.2 | N29: 10.9392 | O29: 11.0664 | P29: 11.1936 | Q29: 11.1936 | R29: 11.3208 | S29: 11.448 | T29: 11.5752 | U29: 11.7024 | V29: 11.8296 | W29: 11.8296 | X29: 11.9568 | Y29: 12.084 | Z29: 13.112818 | AA29: 13.156528 | AB29: 13.200383 | AC29: 13.244384 | AD29: 13.288532 | AE29: 13.332827 | AF29: 13.37727 | AG29: 13.421861 | AH29: 13.4666 | AI29: 13.511489 | AJ29: 13.556527 | AK29: 13.601716 | AL29: =SUM(C29:M29) -> 106.8 | AM29: =SUM(N29:Y29) -> 138.1392 | AN29: =SUM(Z29:AK29) -> 160.27094
A30: Subcontractor Cost | B30: 1.4620642 | C30: 1.4635351 | D30: 1.4893392 | E30: 1.4641478 | F30: 1.5367526 | G30: 1.5643674 | H30: 1.5850469 | I30: 1.6103559 | J30: 1.6818145 | K30: 1.6907823 | L30: 1.6518536 | M30: 1.638184 | N30: 1.7559105 | O30: 1.7954489 | P30: 1.8161511 | Q30: 1.7685906 | R30: 1.8333121 | S30: 1.8695526 | T30: 1.8994224 | U30: 1.9337744 | V30: 1.9767396 | W30: 1.9911609 | X30: 1.9917496 | Y30: 1.9738755 | Z30: 2.1983813 | AA30: 2.2057093 | AB30: 2.2130616 | AC30: 2.2204385 | AD30: 2.2278399 | AE30: 2.2352661 | AF30: 2.242717 | AG30: 2.2501927 | AH30: 2.2576933 | AI30: 2.265219 | AJ30: 2.2727697 | AK30: 2.2803456 | AL30: =SUM(C30:M30) -> 17.376179 | AM30: =SUM(N30:Y30) -> 22.605688 | AN30: =SUM(Z30:AK30) -> 26.869634
A31: Gross Profit | B31: =B28-B29-B30 -> 9.446213 | C31: =C28-C29-C30 -> 9.3448912 | D31: =D28-D29-D30 -> 9.5525675 | E31: =E28-E29-E30 -> 9.2326712 | F31: =F28-F29-F30 -> 10.034653 | G31: =G28-G29-G30 -> 10.265323 | H31: =H28-H29-H30 -> 10.407924 | I31: =I28-I29-I30 -> 10.609314 | ... AK31: =AK28-AK29-AK30 -> 14.522547 | AL31: =SUM(C31:M31) -> 113.85368 | AM31: =SUM(N31:Y31) -> 148.92207 | AN31: =SUM(Z31:AK31) -> 171.12122
A32: Gross Margin % | B32: =IFERROR(B31/B28,0) -> 0.47164381 | C32: =IFERROR(C31/C28,0) -> 0.46611595 | D32: =IFERROR(D31/D28,0) -> 0.46821935 | E32: =IFERROR(E31/E28,0) -> 0.4603258 | F32: =IFERROR(F31/F28,0) -> 0.47667377 | G32: =IFERROR(G31/G28,0) -> 0.47902339 | H32: =IFERROR(H31/H28,0) -> 0.47934131 | I32: =IFERROR(I31/I28,0) -> 0.48093712 | ... AK32: =IFERROR(AK31/AK28,0) -> 0.47764295 | AL32: =SUM(C32:M32) -> 5.2563012 | AM32: =SUM(N32:Y32) -> 5.7672115 | AN32: =SUM(Z32:AK32) -> 5.7317154
A33: Software Cost | B33: 0.836 | C33: 0.847 | D33: 0.858 | E33: 0.858 | F33: 0.869 | G33: 0.88 | H33: 0.891 | I33: 0.902 | J33: 0.913 | K33: 0.913 | L33: 0.924 | M33: 0.935 | N33: 0.9933 | O33: 1.00485 | P33: 1.0164 | Q33: 1.0164 | R33: 1.02795 | S33: 1.0395 | T33: 1.05105 | U33: 1.0626 | V33: 1.07415 | W33: 1.07415 | X33: 1.0857 | Y33: 1.09725 | Z33: 1.198995 | AA33: 1.2029917 | AB33: 1.2070016 | AC33: 1.211025 | AD33: 1.2150617 | AE33: 1.2191119 | AF33: 1.2231756 | AG33: 1.2272529 | AH33: 1.2313437 | AI33: 1.2354482 | AJ33: 1.2395664 | AK33: 1.2436982 | AL33: =SUM(C33:M33) -> 9.79 | AM33: =SUM(N33:Y33) -> 12.5433 | AN33: =SUM(Z33:AK33) -> 14.654672
A34: Facilities Cost | B34: =SUMIFS(Actuals!$M$4:$M$123,Actuals!$D$4:$D$123,"Cybersecurity",Actuals!$A$4:$A$123,B$3) -> 0.418 | C34: 0.4235 | D34: 0.429 | E34: 0.429 | F34: 0.4345 | G34: 0.44 | H34: 0.4455 | I34: 0.451 | J34: 0.4565 | K34: 0.4565 | L34: 0.462 | M34: 0.4675 | N34: 0.473 | O34: 0.4785 | P34: 0.484 | Q34: 0.484 | R34: 0.4895 | S34: 0.495 | T34: 0.5005 | U34: 0.506 | V34: 0.5115 | W34: 0.5115 | X34: 0.517 | Y34: 0.5225 | Z34: 0.5994975 | AA34: 0.60149583 | AB34: 0.60350081 | AC34: 0.60551248 | AD34: 0.60753086 | AE34: 0.60955596 | AF34: 0.61158781 | AG34: 0.61362644 | AH34: 0.61567186 | AI34: 0.6177241 | AJ34: 0.61978318 | AK34: 0.62184912 | AL34: =SUM(C34:M34) -> 4.895 | AM34: =SUM(N34:Y34) -> 5.973 | AN34: =SUM(Z34:AK34) -> 7.3273359
A35: Other Opex | B35: =SUMIFS(Actuals!$N$4:$N$123,Actuals!$D$4:$D$123,"Cybersecurity",Actuals!$A$4:$A$123,B$3)+SUMIFS(Actuals!$O$4:$O$123,Actuals!$D$4:$D$123,"Cybersecurity",Actuals!$A$4:$A$123,B$3)+SUMIFS(Actuals!$P$4:$P$123,Actuals!$D$4:$D$123,"Cybersecurity",Actuals!$A$4:$A$123,B$3) -> 0.72101798 | C35: =SUMIFS(Actuals!$N$4:$N$123,Actuals!$D$4:$D$123,"Cybersecurity",Actuals!$A$4:$A$123,C$3)+SUMIFS(Actuals!$O$4:$O$123,Actuals!$D$4:$D$123,"Cybersecurity",Actuals!$A$4:$A$123,C$3)+SUMIFS(Actuals!$P$4:$P$123,Actuals!$D$4:$D$123,"Cybersecurity",Actuals!$A$4:$A$123,C$3) -> 0.78188863 | D35: =SUMIFS(Actuals!$N$4:$N$123,Actuals!$D$4:$D$123,"Cybersecurity",Actuals!$A$4:$A$123,D$3)+SUMIFS(Actuals!$O$4:$O$123,Actuals!$D$4:$D$123,"Cybersecurity",Actuals!$A$4:$A$123,D$3)+SUMIFS(Actuals!$P$4:$P$123,Actuals!$D$4:$D$123,"Cybersecurity",Actuals!$A$4:$A$123,D$3) -> 0.79567436 | E35: =SUMIFS(Actuals!$N$4:$N$123,Actuals!$D$4:$D$123,"Cybersecurity",Actuals!$A$4:$A$123,E$3)+SUMIFS(Actuals!$O$4:$O$123,Actuals!$D$4:$D$123,"Cybersecurity",Actuals!$A$4:$A$123,E$3)+SUMIFS(Actuals!$P$4:$P$123,Actuals!$D$4:$D$123,"Cybersecurity",Actuals!$A$4:$A$123,E$3) -> 0.72204548 | F35: =SUMIFS(Actuals!$N$4:$N$123,Actuals!$D$4:$D$123,"Cybersecurity",Actuals!$A$4:$A$123,F$3)+SUMIFS(Actuals!$O$4:$O$123,Actuals!$D$4:$D$123,"Cybersecurity",Actuals!$A$4:$A$123,F$3)+SUMIFS(Actuals!$P$4:$P$123,Actuals!$D$4:$D$123,"Cybersecurity",Actuals!$A$4:$A$123,F$3) -> 0.7578506 | G35: =SUMIFS(Actuals!$N$4:$N$123,Actuals!$D$4:$D$123,"Cybersecurity",Actuals!$A$4:$A$123,G$3)+SUMIFS(Actuals!$O$4:$O$123,Actuals!$D$4:$D$123,"Cybersecurity",Actuals!$A$4:$A$123,G$3)+SUMIFS(Actuals!$P$4:$P$123,Actuals!$D$4:$D$123,"Cybersecurity",Actuals!$A$4:$A$123,G$3) -> 0.77146885 | H35: =SUMIFS(Actuals!$N$4:$N$123,Actuals!$D$4:$D$123,"Cybersecurity",Actuals!$A$4:$A$123,H$3)+SUMIFS(Actuals!$O$4:$O$123,Actuals!$D$4:$D$123,"Cybersecurity",Actuals!$A$4:$A$123,H$3)+SUMIFS(Actuals!$P$4:$P$123,Actuals!$D$4:$D$123,"Cybersecurity",Actuals!$A$4:$A$123,H$3) -> 0.78166694 | I35: =SUMIFS(Actuals!$N$4:$N$123,Actuals!$D$4:$D$123,"Cybersecurity",Actuals!$A$4:$A$123,I$3)+SUMIFS(Actuals!$O$4:$O$123,Actuals!$D$4:$D$123,"Cybersecurity",Actuals!$A$4:$A$123,I$3)+SUMIFS(Actuals!$P$4:$P$123,Actuals!$D$4:$D$123,"Cybersecurity",Actuals!$A$4:$A$123,I$3) -> 0.79414813 | ... Y35: =SUMIFS(Actuals!$N$4:$N$123,Actuals!$D$4:$D$123,"Cybersecurity",Actuals!$A$4:$A$123,Y$3)+SUMIFS(Actuals!$O$4:$O$123,Actuals!$D$4:$D$123,"Cybersecurity",Actuals!$A$4:$A$123,Y$3)+SUMIFS(Actuals!$P$4:$P$123,Actuals!$D$4:$D$123,"Cybersecurity",Actuals!$A$4:$A$123,Y$3) -> 0.97341807 | Z35: =Z28*Assumptions!$B$25*(1+Assumptions!$B$9) -> 1.3849802 | AA35: =AA28*Assumptions!$B$25*(1+Assumptions!$B$9) -> 1.3895968 | AB35: =AB28*Assumptions!$B$25*(1+Assumptions!$B$9) -> 1.3942288 | AC35: =AC28*Assumptions!$B$25*(1+Assumptions!$B$9) -> 1.3988762 | AD35: =AD28*Assumptions!$B$25*(1+Assumptions!$B$9) -> 1.4035392 | AE35: =AE28*Assumptions!$B$25*(1+Assumptions!$B$9) -> 1.4082176 | AF35: =AF28*Assumptions!$B$25*(1+Assumptions!$B$9) -> 1.4129117 | AG35: =AG28*Assumptions!$B$25*(1+Assumptions!$B$9) -> 1.4176214 | ... AK35: =AK28*Assumptions!$B$25*(1+Assumptions!$B$9) -> 1.4366177 | AL35: =SUM(C35:M35) -> 8.8290256 | AM35: =SUM(N35:Y35) -> 11.459497 | AN35: =SUM(Z35:AK35) -> 16.927869
A36: EBITDA | B36: =B31-B33-B34-B35 -> 7.471195 | C36: =C31-C33-C34-C35 -> 7.2925026 | D36: =D31-D33-D34-D35 -> 7.4698932 | E36: =E31-E33-E34-E35 -> 7.2236257 | F36: =F31-F33-F34-F35 -> 7.9733023 | G36: =G31-G33-G34-G35 -> 8.173854 | H36: =H31-H33-H34-H35 -> 8.2897569 | I36: =I31-I33-I34-I35 -> 8.4621662 | ... AK36: =AK31-AK33-AK34-AK35 -> 11.220382 | AL36: =SUM(C36:M36) -> 90.33965 | AM36: =SUM(N36:Y36) -> 118.94628 | AN36: =SUM(Z36:AK36) -> 132.21134
A37: EBITDA Margin % | B37: =IFERROR(B36/B28,0) -> 0.37303233 | C37: =IFERROR(C36/C28,0) -> 0.36374439 | D37: =IFERROR(D36/D28,0) -> 0.36613701 | E37: =IFERROR(E36/E28,0) -> 0.36015809 | F37: =IFERROR(F36/F28,0) -> 0.37875392 | G37: =IFERROR(G36/G28,0) -> 0.3814266 | H37: =IFERROR(H36/H28,0) -> 0.38178824 | I37: =IFERROR(I36/I28,0) -> 0.38360348 | ... AK37: =IFERROR(AK36/AK28,0) -> 0.36903556 | AL37: =SUM(C37:M37) -> 4.1689552 | AM37: =SUM(N37:Y37) -> 4.6051829 | AN37: =SUM(Z37:AK37) -> 4.4284268
AL38: =SUM(C38:M38) -> 0 | AM38: =SUM(N38:Y38) -> 0 | AN38: =SUM(Z38:AK38) -> 0
AL39: =SUM(C39:M39) -> 0 | AM39: =SUM(N39:Y39) -> 0 | AN39: =SUM(Z39:AK39) -> 0
A40: Application Development — Revenue | B40: =SUMIFS(Actuals!$I$4:$I$123,Actuals!$D$4:$D$123,"Application Development",Actuals!$A$4:$A$123,B$3) -> 27.906963 | C40: 28.45766 | D40: 29.29768 | E40: 28.503482 | F40: 29.661529 | G40: 30.178576 | H40: 30.456856 | I40: 30.980638 | J40: 32.226762 | K40: 32.864023 | L40: 32.37179 | M40: 31.905438 | N40: 33.925394 | O40: 34.22224 | P40: 34.985118 | Q40: 33.754225 | R40: 35.854686 | S40: 35.731356 | T40: 36.974291 | U40: 37.191174 | V40: 38.213644 | W40: 38.532077 | X40: 38.396586 | Y40: 37.76096 | Z40: 38.674783 | AA40: 38.803699 | AB40: 38.933044 | AC40: 39.062821 | AD40: 39.193031 | AE40: 39.323674 | AF40: 39.454753 | AG40: 39.586269 | AH40: 39.718223 | AI40: 39.850617 | AJ40: 39.983452 | AK40: 40.116731 | AL40: =SUM(C40:M40) -> 336.90443 | AM40: =SUM(N40:Y40) -> 435.54175 | AN40: =SUM(Z40:AK40) -> 472.7011
A41: Personnel Cost | B41: =SUMIFS(Actuals!$J$4:$J$123,Actuals!$D$4:$D$123,"Application Development",Actuals!$A$4:$A$123,B$3) -> 14.88 | C41: =SUMIFS(Actuals!$J$4:$J$123,Actuals!$D$4:$D$123,"Application Development",Actuals!$A$4:$A$123,C$3) -> 15.072 | D41: =SUMIFS(Actuals!$J$4:$J$123,Actuals!$D$4:$D$123,"Application Development",Actuals!$A$4:$A$123,D$3) -> 15.168 | E41: =SUMIFS(Actuals!$J$4:$J$123,Actuals!$D$4:$D$123,"Application Development",Actuals!$A$4:$A$123,E$3) -> 15.36 | F41: =SUMIFS(Actuals!$J$4:$J$123,Actuals!$D$4:$D$123,"Application Development",Actuals!$A$4:$A$123,F$3) -> 15.456 | G41: =SUMIFS(Actuals!$J$4:$J$123,Actuals!$D$4:$D$123,"Application Development",Actuals!$A$4:$A$123,G$3) -> 15.648 | H41: =SUMIFS(Actuals!$J$4:$J$123,Actuals!$D$4:$D$123,"Application Development",Actuals!$A$4:$A$123,H$3) -> 15.744 | I41: =SUMIFS(Actuals!$J$4:$J$123,Actuals!$D$4:$D$123,"Application Development",Actuals!$A$4:$A$123,I$3) -> 15.936 | ... Y41: =SUMIFS(Actuals!$J$4:$J$123,Actuals!$D$4:$D$123,"Application Development",Actuals!$A$4:$A$123,Y$3) -> 19.3344 | Z41: ='Headcount Plan'!K7 -> 20.06739 | AA41: ='Headcount Plan'!K12 -> 20.134281 | AB41: ='Headcount Plan'!K17 -> 20.201396 | AC41: ='Headcount Plan'!K22 -> 20.268734 | AD41: ='Headcount Plan'!K27 -> 20.336296 | AE41: ='Headcount Plan'!K32 -> 20.404084 | AF41: ='Headcount Plan'!K37 -> 20.472097 | AG41: ='Headcount Plan'!K42 -> 20.540338 | AH41: ='Headcount Plan'!K47 -> 20.608805 | AI41: ='Headcount Plan'!K52 -> 20.677501 | AJ41: ='Headcount Plan'!K57 -> 20.746426 | AK41: ='Headcount Plan'!K62 -> 20.815581 | AL41: =SUM(C41:M41) -> 173.472 | AM41: =SUM(N41:Y41) -> 222.04032 | AN41: =SUM(Z41:AK41) -> 245.27293
A42: Subcontractor Cost | B42: =SUMIFS(Actuals!$K$4:$K$123,Actuals!$D$4:$D$123,"Application Development",Actuals!$A$4:$A$123,B$3) -> 2.1488362 | C42: =SUMIFS(Actuals!$K$4:$K$123,Actuals!$D$4:$D$123,"Application Development",Actuals!$A$4:$A$123,C$3) -> 2.1912398 | D42: =SUMIFS(Actuals!$K$4:$K$123,Actuals!$D$4:$D$123,"Application Development",Actuals!$A$4:$A$123,D$3) -> 2.2559213 | E42: =SUMIFS(Actuals!$K$4:$K$123,Actuals!$D$4:$D$123,"Application Development",Actuals!$A$4:$A$123,E$3) -> 2.1947681 | F42: =SUMIFS(Actuals!$K$4:$K$123,Actuals!$D$4:$D$123,"Application Development",Actuals!$A$4:$A$123,F$3) -> 2.2839377 | G42: =SUMIFS(Actuals!$K$4:$K$123,Actuals!$D$4:$D$123,"Application Development",Actuals!$A$4:$A$123,G$3) -> 2.3237503 | H42: =SUMIFS(Actuals!$K$4:$K$123,Actuals!$D$4:$D$123,"Application Development",Actuals!$A$4:$A$123,H$3) -> 2.3451779 | I42: =SUMIFS(Actuals!$K$4:$K$123,Actuals!$D$4:$D$123,"Application Development",Actuals!$A$4:$A$123,I$3) -> 2.3855091 | ... Y42: =SUMIFS(Actuals!$K$4:$K$123,Actuals!$D$4:$D$123,"Application Development",Actuals!$A$4:$A$123,Y$3) -> 2.9075939 | Z42: =Z40*Assumptions!$B$23 -> 2.9006087 | AA42: =AA40*Assumptions!$B$23 -> 2.9102774 | AB42: =AB40*Assumptions!$B$23 -> 2.9199783 | AC42: =AC40*Assumptions!$B$23 -> 2.9297116 | AD42: =AD40*Assumptions!$B$23 -> 2.9394773 | AE42: =AE40*Assumptions!$B$23 -> 2.9492755 | AF42: =AF40*Assumptions!$B$23 -> 2.9591065 | AG42: =AG40*Assumptions!$B$23 -> 2.9689702 | ... AK42: =AK40*Assumptions!$B$23 -> 3.0087548 | AL42: =SUM(C42:M42) -> 25.941641 | AM42: =SUM(N42:Y42) -> 33.536715 | AN42: =SUM(Z42:AK42) -> 35.452582
A43: Gross Profit | B43: =B40-B41-B42 -> 10.878127 | C43: =C40-C41-C42 -> 11.19442 | D43: =D40-D41-D42 -> 11.873758 | E43: =E40-E41-E42 -> 10.948714 | F43: =F40-F41-F42 -> 11.921591 | G43: =G40-G41-G42 -> 12.206825 | H43: =H40-H41-H42 -> 12.367678 | I43: =I40-I41-I42 -> 12.659129 | ... AK43: =AK40-AK41-AK42 -> 16.292395 | AL43: =SUM(C43:M43) -> 137.49079 | AM43: =SUM(N43:Y43) -> 179.96472 | AN43: =SUM(Z43:AK43) -> 191.97558
A44: Gross Margin % | B44: =IFERROR(B43/B40,0) -> 0.38979975 | C44: =IFERROR(C43/C40,0) -> 0.39337107 | D44: =IFERROR(D43/D40,0) -> 0.40527982 | E44: =IFERROR(E43/E40,0) -> 0.38411847 | F44: =IFERROR(F43/F40,0) -> 0.40192099 | G44: =IFERROR(G43/G40,0) -> 0.40448647 | H44: =IFERROR(H43/H40,0) -> 0.40607205 | I44: =IFERROR(I43/I40,0) -> 0.4086142 | ... AK44: =IFERROR(AK43/AK40,0) -> 0.40612469 | AL44: =SUM(C44:M44) -> 4.4830458 | AM44: =SUM(N44:Y44) -> 4.9526676 | AN44: =SUM(Z44:AK44) -> 4.8734962
A45: Software Cost | B45: =SUMIFS(Actuals!$L$4:$L$123,Actuals!$D$4:$D$123,"Application Development",Actuals!$A$4:$A$123,B$3) -> 1.24 | C45: =SUMIFS(Actuals!$L$4:$L$123,Actuals!$D$4:$D$123,"Application Development",Actuals!$A$4:$A$123,C$3) -> 1.256 | D45: =SUMIFS(Actuals!$L$4:$L$123,Actuals!$D$4:$D$123,"Application Development",Actuals!$A$4:$A$123,D$3) -> 1.264 | E45: =SUMIFS(Actuals!$L$4:$L$123,Actuals!$D$4:$D$123,"Application Development",Actuals!$A$4:$A$123,E$3) -> 1.28 | F45: =SUMIFS(Actuals!$L$4:$L$123,Actuals!$D$4:$D$123,"Application Development",Actuals!$A$4:$A$123,F$3) -> 1.288 | G45: =SUMIFS(Actuals!$L$4:$L$123,Actuals!$D$4:$D$123,"Application Development",Actuals!$A$4:$A$123,G$3) -> 1.304 | H45: =SUMIFS(Actuals!$L$4:$L$123,Actuals!$D$4:$D$123,"Application Development",Actuals!$A$4:$A$123,H$3) -> 1.312 | I45: =SUMIFS(Actuals!$L$4:$L$123,Actuals!$D$4:$D$123,"Application Development",Actuals!$A$4:$A$123,I$3) -> 1.328 | ... Y45: =SUMIFS(Actuals!$L$4:$L$123,Actuals!$D$4:$D$123,"Application Development",Actuals!$A$4:$A$123,Y$3) -> 1.596 | Z45: ='Headcount Plan'!G7*Assumptions!G16*(1+Assumptions!$B$9) -> 1.703835 | AA45: ='Headcount Plan'!G12*Assumptions!G16*(1+Assumptions!$B$9) -> 1.7095145 | AB45: ='Headcount Plan'!G17*Assumptions!G16*(1+Assumptions!$B$9) -> 1.7152128 | AC45: ='Headcount Plan'!G22*Assumptions!G16*(1+Assumptions!$B$9) -> 1.7209302 | AD45: ='Headcount Plan'!G27*Assumptions!G16*(1+Assumptions!$B$9) -> 1.7266666 | AE45: ='Headcount Plan'!G32*Assumptions!G16*(1+Assumptions!$B$9) -> 1.7324222 | AF45: ='Headcount Plan'!G37*Assumptions!G16*(1+Assumptions!$B$9) -> 1.7381969 | AG45: ='Headcount Plan'!G42*Assumptions!G16*(1+Assumptions!$B$9) -> 1.7439909 | AH45: ='Headcount Plan'!G47*Assumptions!G16*(1+Assumptions!$B$9) -> 1.7498042 | AI45: ='Headcount Plan'!G52*Assumptions!G16*(1+Assumptions!$B$9) -> 1.7556369 | AJ45: ='Headcount Plan'!G57*Assumptions!G16*(1+Assumptions!$B$9) -> 1.761489 | AK45: ='Headcount Plan'!G62*Assumptions!G16*(1+Assumptions!$B$9) -> 1.7673607 | AL45: =SUM(C45:M45) -> 14.456 | AM45: =SUM(N45:Y45) -> 18.3288 | AN45: =SUM(Z45:AK45) -> 20.82506
A46: Facilities Cost | B46: =SUMIFS(Actuals!$M$4:$M$123,Actuals!$D$4:$D$123,"Application Development",Actuals!$A$4:$A$123,B$3) -> 0.8525 | C46: 0.8635 | D46: 0.869 | E46: 0.88 | F46: 0.8855 | G46: 0.8965 | H46: 0.902 | I46: 0.913 | J46: 0.9185 | K46: 0.9295 | L46: 0.935 | M46: 0.946 | N46: 0.9515 | O46: 0.9625 | P46: 0.968 | Q46: 0.979 | R46: 0.99 | S46: 0.9955 | T46: 1.0065 | U46: 1.012 | V46: 1.023 | W46: 1.0285 | X46: 1.0395 | Y46: 1.045 | Z46: 1.13589 | AA46: 1.1396763 | AB46: 1.1434752 | AC46: 1.1472868 | AD46: 1.1511111 | AE46: 1.1549481 | AF46: 1.158798 | AG46: 1.1626606 | AH46: 1.1665362 | AI46: 1.1704246 | AJ46: 1.174326 | AK46: 1.1782404 | AL46: =SUM(C46:M46) -> 9.9385 | AM46: =SUM(N46:Y46) -> 12.001 | AN46: =SUM(Z46:AK46) -> 13.883373
A47: Other Opex | B47: =SUMIFS(Actuals!$N$4:$N$123,Actuals!$D$4:$D$123,"Application Development",Actuals!$A$4:$A$123,B$3)+SUMIFS(Actuals!$O$4:$O$123,Actuals!$D$4:$D$123,"Application Development",Actuals!$A$4:$A$123,B$3)+SUMIFS(Actuals!$P$4:$P$123,Actuals!$D$4:$D$123,"Application Development",Actuals!$A$4:$A$123,B$3) -> 1.0046507 | C47: =SUMIFS(Actuals!$N$4:$N$123,Actuals!$D$4:$D$123,"Application Development",Actuals!$A$4:$A$123,C$3)+SUMIFS(Actuals!$O$4:$O$123,Actuals!$D$4:$D$123,"Application Development",Actuals!$A$4:$A$123,C$3)+SUMIFS(Actuals!$P$4:$P$123,Actuals!$D$4:$D$123,"Application Development",Actuals!$A$4:$A$123,C$3) -> 1.1098487 | D47: =SUMIFS(Actuals!$N$4:$N$123,Actuals!$D$4:$D$123,"Application Development",Actuals!$A$4:$A$123,D$3)+SUMIFS(Actuals!$O$4:$O$123,Actuals!$D$4:$D$123,"Application Development",Actuals!$A$4:$A$123,D$3)+SUMIFS(Actuals!$P$4:$P$123,Actuals!$D$4:$D$123,"Application Development",Actuals!$A$4:$A$123,D$3) -> 1.1426095 | E47: =SUMIFS(Actuals!$N$4:$N$123,Actuals!$D$4:$D$123,"Application Development",Actuals!$A$4:$A$123,E$3)+SUMIFS(Actuals!$O$4:$O$123,Actuals!$D$4:$D$123,"Application Development",Actuals!$A$4:$A$123,E$3)+SUMIFS(Actuals!$P$4:$P$123,Actuals!$D$4:$D$123,"Application Development",Actuals!$A$4:$A$123,E$3) -> 1.0261254 | F47: =SUMIFS(Actuals!$N$4:$N$123,Actuals!$D$4:$D$123,"Application Development",Actuals!$A$4:$A$123,F$3)+SUMIFS(Actuals!$O$4:$O$123,Actuals!$D$4:$D$123,"Application Development",Actuals!$A$4:$A$123,F$3)+SUMIFS(Actuals!$P$4:$P$123,Actuals!$D$4:$D$123,"Application Development",Actuals!$A$4:$A$123,F$3) -> 1.067815 | G47: =SUMIFS(Actuals!$N$4:$N$123,Actuals!$D$4:$D$123,"Application Development",Actuals!$A$4:$A$123,G$3)+SUMIFS(Actuals!$O$4:$O$123,Actuals!$D$4:$D$123,"Application Development",Actuals!$A$4:$A$123,G$3)+SUMIFS(Actuals!$P$4:$P$123,Actuals!$D$4:$D$123,"Application Development",Actuals!$A$4:$A$123,G$3) -> 1.0864287 | H47: =SUMIFS(Actuals!$N$4:$N$123,Actuals!$D$4:$D$123,"Application Development",Actuals!$A$4:$A$123,H$3)+SUMIFS(Actuals!$O$4:$O$123,Actuals!$D$4:$D$123,"Application Development",Actuals!$A$4:$A$123,H$3)+SUMIFS(Actuals!$P$4:$P$123,Actuals!$D$4:$D$123,"Application Development",Actuals!$A$4:$A$123,H$3) -> 1.0964468 | I47: =SUMIFS(Actuals!$N$4:$N$123,Actuals!$D$4:$D$123,"Application Development",Actuals!$A$4:$A$123,I$3)+SUMIFS(Actuals!$O$4:$O$123,Actuals!$D$4:$D$123,"Application Development",Actuals!$A$4:$A$123,I$3)+SUMIFS(Actuals!$P$4:$P$123,Actuals!$D$4:$D$123,"Application Development",Actuals!$A$4:$A$123,I$3) -> 1.115303 | ... Y47: =SUMIFS(Actuals!$N$4:$N$123,Actuals!$D$4:$D$123,"Application Development",Actuals!$A$4:$A$123,Y$3)+SUMIFS(Actuals!$O$4:$O$123,Actuals!$D$4:$D$123,"Application Development",Actuals!$A$4:$A$123,Y$3)+SUMIFS(Actuals!$P$4:$P$123,Actuals!$D$4:$D$123,"Application Development",Actuals!$A$4:$A$123,Y$3) -> 1.3593946 | Z47: =Z40*Assumptions!$B$25*(1+Assumptions!$B$9) -> 1.8273835 | AA47: =AA40*Assumptions!$B$25*(1+Assumptions!$B$9) -> 1.8334748 | AB47: =AB40*Assumptions!$B$25*(1+Assumptions!$B$9) -> 1.8395863 | AC47: =AC40*Assumptions!$B$25*(1+Assumptions!$B$9) -> 1.8457183 | AD47: =AD40*Assumptions!$B$25*(1+Assumptions!$B$9) -> 1.8518707 | AE47: =AE40*Assumptions!$B$25*(1+Assumptions!$B$9) -> 1.8580436 | AF47: =AF40*Assumptions!$B$25*(1+Assumptions!$B$9) -> 1.8642371 | AG47: =AG40*Assumptions!$B$25*(1+Assumptions!$B$9) -> 1.8704512 | ... AK47: =AK40*Assumptions!$B$25*(1+Assumptions!$B$9) -> 1.8955155 | AL47: =SUM(C47:M47) -> 12.497098 | AM47: =SUM(N47:Y47) -> 16.117362 | AN47: =SUM(Z47:AK47) -> 22.335127
A48: EBITDA | B48: =B43-B45-B46-B47 -> 7.7809766 | C48: =C43-C45-C46-C47 -> 7.9650713 | D48: =D43-D45-D46-D47 -> 8.5981487 | E48: =E43-E45-E46-E47 -> 7.7625886 | F48: =F43-F45-F46-F47 -> 8.6802759 | G48: =G43-G45-G46-G47 -> 8.9198967 | H48: =H43-H45-H46-H47 -> 9.0572313 | I48: =I43-I45-I46-I47 -> 9.3028257 | ... AK48: =AK43-AK45-AK46-AK47 -> 11.451278 | AL48: =SUM(C48:M48) -> 100.59919 | AM48: =SUM(N48:Y48) -> 133.51755 | AN48: =SUM(Z48:AK48) -> 134.93202
A49: EBITDA Margin % | B49: =IFERROR(B48/B40,0) -> 0.27881846 | C49: =IFERROR(C48/C40,0) -> 0.279892 | D49: =IFERROR(D48/D40,0) -> 0.29347542 | E49: =IFERROR(E48/E40,0) -> 0.27233825 | F49: =IFERROR(F48/F40,0) -> 0.29264425 | G49: =IFERROR(G48/G40,0) -> 0.2955705 | H49: =IFERROR(H48/H40,0) -> 0.29737906 | I49: =IFERROR(I48/I40,0) -> 0.3002787 | ... AK49: =IFERROR(AK48/AK40,0) -> 0.28544893 | AL49: =SUM(C49:M49) -> 3.2777085 | AM49: =SUM(N49:Y49) -> 3.6722455 | AN49: =SUM(Z49:AK49) -> 3.4253872
AL50: =SUM(C50:M50) -> 0 | AM50: =SUM(N50:Y50) -> 0 | AN50: =SUM(Z50:AK50) -> 0
AL51: =SUM(C51:M51) -> 0 | AM51: =SUM(N51:Y51) -> 0 | AN51: =SUM(Z51:AK51) -> 0
A52: Managed Services — Revenue | B52: =SUMIFS(Actuals!$I$4:$I$123,Actuals!$D$4:$D$123,"Managed Services",Actuals!$A$4:$A$123,B$3) -> 21.167585 | C52: 21.413825 | D52: 21.56091 | E52: 21.229507 | F52: 22.165482 | G52: 22.895457 | H52: 22.935531 | I52: 23.510208 | J52: 24.129192 | K52: 24.466787 | L52: 24.213399 | M52: 24.122857 | N52: 25.809212 | O52: 26.184258 | P52: 26.604255 | Q52: 25.828816 | R52: 26.86877 | S52: 27.61619 | T52: 27.625087 | U52: 28.113013 | V52: 29.294272 | W52: 29.630587 | X52: 29.698659 | Y52: 29.134179 | Z52: 29.35791 | AA52: 29.45577 | AB52: 29.553956 | AC52: 29.652469 | AD52: 29.75131 | AE52: 29.850481 | AF52: 29.949983 | AG52: 30.049816 | AH52: 30.149982 | AI52: 30.250482 | AJ52: 30.351317 | AK52: 30.452488 | AL52: =SUM(C52:M52) -> 252.64315 | AM52: =SUM(N52:Y52) -> 332.4073 | AN52: =SUM(Z52:AK52) -> 358.82597
A53: Personnel Cost | B53: 12.144 | C53: 12.328 | D53: 12.42 | E53: 12.604 | F53: 12.696 | G53: 12.88 | H53: 12.972 | I53: 13.156 | J53: 13.248 | K53: 13.432 | L53: 13.524 | M53: 13.708 | N53: 14.628 | O53: 14.82304 | P53: 14.92056 | Q53: 15.1156 | R53: 15.21312 | S53: 15.40816 | T53: 15.50568 | U53: 15.70072 | V53: 15.79824 | W53: 15.99328 | X53: 16.18832 | Y53: 16.28584 | Z53: 16.457383 | AA53: 16.512241 | AB53: 16.567282 | AC53: 16.622506 | AD53: 16.677915 | AE53: 16.733508 | AF53: 16.789286 | AG53: 16.84525 | AH53: 16.901401 | AI53: 16.957739 | AJ53: 17.014265 | AK53: 17.070979 | AL53: =SUM(C53:M53) -> 142.968 | AM53: =SUM(N53:Y53) -> 185.58056 | AN53: =SUM(Z53:AK53) -> 201.14976
A54: Subcontractor Cost | B54: 1.7145744 | C54: 1.7345198 | D54: 1.7464337 | E54: 1.7195901 | F54: 1.795404 | G54: 1.854532 | H54: 1.857778 | I54: 1.9043269 | J54: 1.9544645 | K54: 1.9818097 | L54: 1.9612854 | M54: 1.9539514 | N54: 2.0905461 | O54: 2.1209249 | P54: 2.1549447 | Q54: 2.0921341 | R54: 2.1763704 | S54: 2.2369113 | T54: 2.237632 | U54: 2.277154 | V54: 2.3728361 | W54: 2.4000776 | X54: 2.4055914 | Y54: 2.3598685 | Z54: 2.2018433 | AA54: 2.2091827 | AB54: 2.2165467 | AC54: 2.2239352 | AD54: 2.2313483 | AE54: 2.2387861 | AF54: 2.2462487 | AG54: 2.2537362 | AH54: 2.2612487 | AI54: 2.2687862 | AJ54: 2.2763488 | AK54: 2.2839366 | AL54: =SUM(C54:M54) -> 20.464095 | AM54: =SUM(N54:Y54) -> 26.924991 | AN54: =SUM(Z54:AK54) -> 26.911947
A55: Gross Profit | B55: 7.3090107 | C55: 7.351305 | D55: 7.3944762 | E55: 6.9059171 | F55: 7.6740776 | G55: 8.1609251 | H55: 8.1057528 | I55: 8.4498813 | J55: 8.9267272 | K55: 9.0529769 | L55: 8.7281141 | M55: 8.4609052 | N55: 9.0906655 | O55: 9.2402926 | P55: 9.5287505 | Q55: 8.621082 | R55: 9.4792794 | S55: 9.9711182 | T55: 9.8817749 | U55: 10.135139 | V55: 11.123196 | W55: 11.23723 | X55: 11.104748 | Y55: 10.488471 | Z55: =Z52-Z53-Z54 -> 10.698683 | AA55: =AA52-AA53-AA54 -> 10.734346 | AB55: =AB52-AB53-AB54 -> 10.770127 | AC55: =AC52-AC53-AC54 -> 10.806027 | AD55: =AD52-AD53-AD54 -> 10.842047 | AE55: =AE52-AE53-AE54 -> 10.878188 | AF55: =AF52-AF53-AF54 -> 10.914448 | AG55: =AG52-AG53-AG54 -> 10.95083 | ... AK55: =AK52-AK53-AK54 -> 11.097572 | AL55: =SUM(C55:M55) -> 89.211059 | AM55: =SUM(N55:Y55) -> 119.90175 | AN55: =SUM(Z55:AK55) -> 130.76426
A56: Gross Margin % | B56: 0.34529261 | C56: 0.34329715 | D56: 0.34295752 | E56: 0.32529804 | F56: 0.3462175 | G56: 0.35644299 | H56: 0.35341466 | I56: 0.35941329 | J56: 0.3699555 | K56: 0.37001087 | L56: 0.36046628 | M56: 0.35074226 | N56: 0.35222562 | O56: 0.35289497 | P56: 0.35816641 | Q56: 0.33377767 | R56: 0.35279916 | S56: 0.36106061 | T56: 0.35771018 | U56: 0.36051414 | V56: 0.3797055 | W56: 0.37924425 | X56: 0.37391411 | Y56: 0.3600057 | Z56: =IFERROR(Z55/Z52,0) -> 0.36442252 | AA56: =IFERROR(AA55/AA52,0) -> 0.36442252 | AB56: =IFERROR(AB55/AB52,0) -> 0.36442252 | AC56: =IFERROR(AC55/AC52,0) -> 0.36442252 | AD56: =IFERROR(AD55/AD52,0) -> 0.36442252 | AE56: =IFERROR(AE55/AE52,0) -> 0.36442252 | AF56: =IFERROR(AF55/AF52,0) -> 0.36442252 | AG56: =IFERROR(AG55/AG52,0) -> 0.36442252 | ... AK56: =IFERROR(AK55/AK52,0) -> 0.36442252 | AL56: =SUM(C56:M56) -> 3.8782161 | AM56: =SUM(N56:Y56) -> 4.3220183 | AN56: =SUM(Z56:AK56) -> 4.3730702
A57: Software Cost | B57: 0.924 | C57: 0.938 | D57: 0.945 | E57: 0.959 | F57: 0.966 | G57: 0.98 | H57: 0.987 | I57: 1.001 | J57: 1.008 | K57: 1.022 | L57: 1.029 | M57: 1.043 | N57: 1.1025 | O57: 1.1172 | P57: 1.12455 | Q57: 1.13925 | R57: 1.1466 | S57: 1.1613 | T57: 1.16865 | U57: 1.18335 | V57: 1.1907 | W57: 1.2054 | X57: 1.2201 | Y57: 1.22745 | Z57: 1.30417 | AA57: 1.3085172 | AB57: 1.312879 | AC57: 1.3172552 | AD57: 1.3216461 | AE57: 1.3260516 | AF57: 1.3304717 | AG57: 1.3349066 | AH57: 1.3393563 | AI57: 1.3438208 | AJ57: 1.3483002 | AK57: 1.3527946 | AL57: =SUM(C57:M57) -> 10.878 | AM57: =SUM(N57:Y57) -> 13.98705 | AN57: =SUM(Z57:AK57) -> 15.940169
A58: Facilities Cost | B58: =SUMIFS(Actuals!$M$4:$M$123,Actuals!$D$4:$D$123,"Managed Services",Actuals!$A$4:$A$123,B$3) -> 0.726 | C58: 0.737 | D58: 0.7425 | E58: 0.7535 | F58: 0.759 | G58: 0.77 | H58: 0.7755 | I58: 0.7865 | J58: 0.792 | K58: 0.803 | L58: 0.8085 | M58: 0.8195 | N58: 0.825 | O58: 0.836 | P58: 0.8415 | Q58: 0.8525 | R58: 0.858 | S58: 0.869 | T58: 0.8745 | U58: 0.8855 | V58: 0.891 | W58: 0.902 | X58: 0.913 | Y58: 0.9185 | Z58: 0.9781275 | AA58: 0.98138793 | AB58: 0.98465922 | AC58: 0.98794142 | AD58: 0.99123455 | AE58: 0.99453867 | AF58: 0.9978538 | AG58: 1.00118 | AH58: 1.0045172 | AI58: 1.0078656 | AJ58: 1.0112252 | AK58: 1.0145959 | AL58: =SUM(C58:M58) -> 8.547 | AM58: =SUM(N58:Y58) -> 10.4665 | AN58: =SUM(Z58:AK58) -> 11.955127
A59: Other Opex | B59: 0.76203306 | C59: 0.83513917 | D59: 0.84087549 | E59: 0.76426226 | F59: 0.79795734 | G59: 0.82423646 | H59: 0.82567911 | I59: 0.84636749 | J59: 0.94103848 | K59: 0.95420468 | L59: 0.87168238 | M59: 0.86842284 | N59: 0.92913162 | O59: 1.021186 | P59: 1.037566 | Q59: 0.92983738 | R59: 0.96727571 | S59: 0.99418282 | T59: 0.99450313 | U59: 1.0120685 | V59: 1.1424766 | W59: 1.1555929 | X59: 1.0691517 | Y59: 1.0488304 | Z59: 1.3871612 | AA59: 1.3917851 | AB59: 1.3964244 | AC59: 1.4010792 | AD59: 1.4057494 | AE59: 1.4104352 | AF59: 1.4151367 | AG59: 1.4198538 | AH59: 1.4245867 | AI59: 1.4293353 | AJ59: 1.4340997 | AK59: 1.4388801 | AL59: =SUM(C59:M59) -> 9.3698657 | AM59: =SUM(N59:Y59) -> 12.301803 | AN59: =SUM(Z59:AK59) -> 16.954527
A60: EBITDA | B60: 4.8969777 | C60: 4.8411658 | D60: 4.8661007 | E60: 4.4291549 | F60: 5.1511203 | G60: 5.5866887 | H60: 5.5175737 | I60: 5.8160138 | J60: 6.1856887 | K60: 6.2737722 | L60: 6.0189318 | M60: 5.7299824 | N60: 6.2340339 | O60: 6.2659066 | P60: 6.5251346 | Q60: 5.6994946 | R60: 6.5074037 | S60: 6.9466353 | T60: 6.8441218 | U60: 7.0542203 | V60: 7.8990197 | W60: 7.9742369 | X60: 7.9024959 | Y60: 7.2936901 | Z60: =Z55-Z57-Z58-Z59 -> 7.0292247 | AA60: =AA55-AA57-AA58-AA59 -> 7.0526554 | AB60: =AB55-AB57-AB58-AB59 -> 7.0761643 | AC60: =AC55-AC57-AC58-AC59 -> 7.0997515 | AD60: =AD55-AD57-AD58-AD59 -> 7.1234174 | AE60: =AE55-AE57-AE58-AE59 -> 7.1471621 | AF60: =AF55-AF57-AF58-AF59 -> 7.170986 | AG60: =AG55-AG57-AG58-AG59 -> 7.1948892 | ... AK60: =AK55-AK57-AK58-AK59 -> 7.2913018 | AL60: =SUM(C60:M60) -> 60.416193 | AM60: =SUM(N60:Y60) -> 83.146394 | AN60: =SUM(Z60:AK60) -> 85.914438
A61: EBITDA Margin % | B61: 0.23134324 | C61: 0.22607665 | D61: 0.22569088 | E61: 0.20863202 | F61: 0.23239379 | G61: 0.24400861 | H61: 0.24056883 | I61: 0.24738249 | J61: 0.25635706 | K61: 0.25641995 | L61: 0.24857855 | M61: 0.23753333 | N61: 0.24154298 | O61: 0.23930053 | P61: 0.24526658 | Q61: 0.22066418 | R61: 0.2421921 | S61: 0.25154214 | T61: 0.24775024 | U61: 0.25092367 | V61: 0.26964383 | W61: 0.2691218 | X61: 0.26608932 | Y61: 0.25034823 | Z61: =IFERROR(Z60/Z52,0) -> 0.23943205 | AA61: =IFERROR(AA60/AA52,0) -> 0.23943205 | AB61: =IFERROR(AB60/AB52,0) -> 0.23943205 | AC61: =IFERROR(AC60/AC52,0) -> 0.23943205 | AD61: =IFERROR(AD60/AD52,0) -> 0.23943205 | AE61: =IFERROR(AE60/AE52,0) -> 0.23943205 | AF61: =IFERROR(AF60/AF52,0) -> 0.23943205 | AG61: =IFERROR(AG60/AG52,0) -> 0.23943205 | ... AK61: =IFERROR(AK60/AK52,0) -> 0.23943205 | AL61: =SUM(C61:M61) -> 2.6236422 | AM61: =SUM(N61:Y61) -> 2.9943856 | AN61: =SUM(Z61:AK61) -> 2.8731846
Z62: =Z56/Z8 -> 0.86602455 | AA62: =AA56/AA8 -> 0.86602455 | AB62: =AB56/AB8 -> 0.86602455 | AC62: =AC56/AC8 -> 0.86602455 | AD62: =AD56/AD8 -> 0.86602455 | AE62: =AE56/AE8 -> 0.86602455 | AF62: =AF56/AF8 -> 0.86602455 | AG62: =AG56/AG8 -> 0.86602455 | ... AK62: =AK56/AK8 -> 0.86602455 | AL62: =SUM(C62:M62) -> 0 | AM62: =SUM(N62:Y62) -> 0 | AN62: =SUM(Z62:AK62) -> 10.392295
Z63: =Z57/Z9 -> 0.85517241 | AA63: =AA57/AA9 -> 0.85517241 | AB63: =AB57/AB9 -> 0.85517241 | AC63: =AC57/AC9 -> 0.85517241 | AD63: =AD57/AD9 -> 0.85517241 | AE63: =AE57/AE9 -> 0.85517241 | AF63: =AF57/AF9 -> 0.85517241 | AG63: =AG57/AG9 -> 0.85517241 | ... AK63: =AK57/AK9 -> 0.85517241 | AL63: =SUM(C63:M63) -> 0 | AM63: =SUM(N63:Y63) -> 0 | AN63: =SUM(Z63:AK63) -> 10.262069

Sheet Fct vs Bud Var Analysis
A1: 2027 Forecast vs Budget Variance Analysis
A2: Case Selected: | B2: =Assumptions!B3 -> Base
A3: Month | B3: Revenue Budget | C3: Revenue Forecast | D3: Revenue Var | E3: Revenue Var % | F3: Cost Budget | G3: Cost Forecast | H3: Cost Var | I3: Cost Var % | J3: EBITDA Budget | K3: EBITDA Forecast | L3: EBITDA Var | M3: EBITDA Var %
A4: 46388 | B4: =SUM('Budget 2027'!K4:K8) -> 160.98471 | C4: ='P&L'!Z4 -> 166.3846 | D4: =C4-B4 -> 5.3998859 | E4: =IFERROR(D4/B4,0) -> 0.03354285 | F4: =SUM('Budget 2027'!P4:P8) -> 113.49836 | G4: ='Opex Forecast'!I4 -> 115.20511 | H4: =G4-F4 -> 1.7067469 | I4: =IFERROR(H4/F4,0) -> 0.015037634 | J4: =SUM('Budget 2027'!Q4:Q8) -> 47.486345 | K4: ='P&L'!Z12 -> 51.179484 | L4: =K4-J4 -> 3.6931391 | M4: =IFERROR(L4/J4,0) -> 0.077772654
A5: 46419 | B5: =SUM('Budget 2027'!K9:K13) -> 161.25302 | C5: ='P&L'!AA4 -> 166.93921 | D5: =C5-B5 -> 5.6861934 | E5: =IFERROR(D5/B5,0) -> 0.035262555 | F5: 113.68753 | G5: ='Opex Forecast'!I5 -> 115.58913 | H5: =G5-F5 -> 1.9016 | I5: =IFERROR(H5/F5,0) -> 0.016726549 | J5: =SUM('Budget 2027'!Q9:Q13) -> 47.565489 | K5: ='P&L'!AA12 -> 51.350082 | L5: =K5-J5 -> 3.7845934 | M5: =IFERROR(L5/J5,0) -> 0.079565953
A6: 46447 | B6: =SUM('Budget 2027'!K14:K18) -> 161.52177 | C6: ='P&L'!AB4 -> 167.49567 | D6: =C6-B6 -> 5.9739024 | E6: =IFERROR(D6/B6,0) -> 0.036985122 | F6: 113.87701 | G6: ='Opex Forecast'!I6 -> 115.97443 | H6: =G6-F6 -> 2.0974179 | I6: =IFERROR(H6/F6,0) -> 0.018418273 | J6: =SUM('Budget 2027'!Q14:Q18) -> 47.644764 | K6: ='P&L'!AB12 -> 51.521249 | L6: =K6-J6 -> 3.8764846 | M6: =IFERROR(L6/J6,0) -> 0.081362236
A7: 46478 | B7: =SUM('Budget 2027'!K19:K23) -> 161.79097 | C7: ='P&L'!AC4 -> 168.05399 | D7: =C7-B7 -> 6.2630184 | E7: =IFERROR(D7/B7,0) -> 0.038710555 | F7: 114.0668 | G7: ='Opex Forecast'!I7 -> 116.36101 | H7: =G7-F7 -> 2.2942043 | I7: =IFERROR(H7/F7,0) -> 0.020112813 | J7: =SUM('Budget 2027'!Q19:Q23) -> 47.724172 | K7: ='P&L'!AC12 -> 51.692986 | L7: =K7-J7 -> 3.9688141 | M7: =IFERROR(L7/J7,0) -> 0.083161507
A8: 46508 | B8: =SUM('Budget 2027'!K24:K28) -> 162.06063 | C8: ='P&L'!AD4 -> 168.61417 | D8: =C8-B8 -> 6.5535467 | E8: =IFERROR(D8/B8,0) -> 0.040438858 | F8: 114.25691 | G8: ='Opex Forecast'!I8 -> 116.74888 | H8: =G8-F8 -> 2.491963 | I8: =IFERROR(H8/F8,0) -> 0.021810172 | J8: =SUM('Budget 2027'!Q24:Q28) -> 47.803713 | K8: ='P&L'!AD12 -> 51.865296 | L8: =K8-J8 -> 4.0615838 | M8: =IFERROR(L8/J8,0) -> 0.084963773
A9: 46539 | B9: =SUM('Budget 2027'!K29:K33) -> 162.33073 | C9: ='P&L'!AE4 -> 169.17622 | D9: =C9-B9 -> 6.8454929 | E9: =IFERROR(D9/B9,0) -> 0.042170038 | F9: 114.44734 | G9: ='Opex Forecast'!I9 -> 117.13804 | H9: =G9-F9 -> 2.6906977 | I9: =IFERROR(H9/F9,0) -> 0.023510355 | J9: =SUM('Budget 2027'!Q29:Q33) -> 47.883385 | K9: ='P&L'!AE12 -> 52.038181 | L9: =K9-J9 -> 4.1547952 | M9: =IFERROR(L9/J9,0) -> 0.086769037
A10: 46569 | B10: =SUM('Budget 2027'!K34:K38) -> 162.60128 | C10: ='P&L'!AF4 -> 169.74014 | D10: =C10-B10 -> 7.1388625 | E10: =IFERROR(D10/B10,0) -> 0.043904098 | F10: 114.63809 | G10: ='Opex Forecast'!I10 -> 117.5285 | H10: =G10-F10 -> 2.8904122 | I10: =IFERROR(H10/F10,0) -> 0.025213368 | J10: =SUM('Budget 2027'!Q34:Q38) -> 47.963191 | K10: ='P&L'!AF12 -> 52.211641 | L10: =K10-J10 -> 4.2484502 | M10: =IFERROR(L10/J10,0) -> 0.088577305
A11: 46600 | B11: =SUM('Budget 2027'!K39:K43) -> 162.87228 | C11: ='P&L'!AG4 -> 170.30594 | D11: =C11-B11 -> 7.4336608 | E11: =IFERROR(D11/B11,0) -> 0.045641043 | F11: 114.82915 | G11: ='Opex Forecast'!I11 -> 117.92026 | H11: =G11-F11 -> 3.0911104 | I11: =IFERROR(H11/F11,0) -> 0.026919213 | J11: =SUM('Budget 2027'!Q39:Q43) -> 48.04313 | K11: ='P&L'!AG12 -> 52.38568 | L11: =K11-J11 -> 4.3425504 | M11: =IFERROR(L11/J11,0) -> 0.090388582
A12: 46631 | B12: =SUM('Budget 2027'!K44:K48) -> 163.14373 | C12: ='P&L'!AH4 -> 170.87363 | D12: =C12-B12 -> 7.7298935 | E12: =IFERROR(D12/B12,0) -> 0.047380878 | F12: 115.02053 | G12: ='Opex Forecast'!I12 -> 118.31333 | H12: =G12-F12 -> 3.2927961 | I12: =IFERROR(H12/F12,0) -> 0.028627898 | J12: =SUM('Budget 2027'!Q44:Q48) -> 48.123202 | K12: ='P&L'!AH12 -> 52.560299 | L12: =K12-J12 -> 4.4370974 | M12: =IFERROR(L12/J12,0) -> 0.092202872
A13: 46661 | B13: =SUM('Budget 2027'!K49:K53) -> 163.41564 | C13: ='P&L'!AI4 -> 171.44321 | D13: =C13-B13 -> 8.027566 | E13: =IFERROR(D13/B13,0) -> 0.049123609 | F13: 115.21223 | G13: ='Opex Forecast'!I13 -> 118.70771 | H13: =G13-F13 -> 3.4954729 | I13: =IFERROR(H13/F13,0) -> 0.030339425 | J13: =SUM('Budget 2027'!Q49:Q53) -> 48.203407 | K13: ='P&L'!AI12 -> 52.7355 | L13: =K13-J13 -> 4.5320931 | M13: =IFERROR(L13/J13,0) -> 0.094020181
A14: 46692 | B14: =SUM('Budget 2027'!K54:K58) -> 163.688 | C14: ='P&L'!AJ4 -> 172.01468 | D14: =C14-B14 -> 8.326684 | E14: =IFERROR(D14/B14,0) -> 0.050869239 | F14: 115.40425 | G14: ='Opex Forecast'!I14 -> 119.1034 | H14: =G14-F14 -> 3.6991449 | I14: =IFERROR(H14/F14,0) -> 0.0320538 | J14: =SUM('Budget 2027'!Q54:Q58) -> 48.283746 | K14: ='P&L'!AJ12 -> 52.911285 | L14: =K14-J14 -> 4.6275391 | M14: =IFERROR(L14/J14,0) -> 0.095840515
A15: 46722 | B15: =SUM('Budget 2027'!K59:K63) -> 163.96081 | C15: ='P&L'!AK4 -> 172.58807 | D15: =C15-B15 -> 8.6272529 | E15: =IFERROR(D15/B15,0) -> 0.052617773 | F15: 115.59659 | G15: ='Opex Forecast'!I15 -> 119.50041 | H15: =G15-F15 -> 3.9038158 | I15: =IFERROR(H15/F15,0) -> 0.033771028 | J15: =SUM('Budget 2027'!Q59:Q63) -> 48.364219 | K15: ='P&L'!AK12 -> 53.087656 | L15: =K15-J15 -> 4.7234371 | M15: =IFERROR(L15/J15,0) -> 0.097663877

Sheet Scenarios
A1: Scenario Assumptions
A3: Scenario | B3: Utilization Change | C3: Billing Rate Growth | D3: Salary Inflation | E3: Other Opex Growth | F3: Annual HC Growth
A4: Base | B4: 0 | C4: 0.05 | D4: 0.06 | E4: 0.05 | F4: 0.04
A5: Upside | B5: 0.04 | C5: 0.08 | D5: 0.06 | E5: 0.04 | F5: 0.08
A6: Downside | B6: -0.06 | C6: 0.02 | D6: 0.07 | E6: 0.08 | F6: -0.02
A8: Source / Note
A9: All assumptions are fictional portfolio inputs designed to demonstrate scenario modelling.

Sheet Budget 2027
A1: Independent 2027 Budget Build
A3: Month | B3: Business Unit | C3: Opening HC | D3: Gross Hires | E3: Attrition | F3: Closing HC | G3: Average HC | H3: Billable HC | I3: Utilization | J3: Billing Rate | K3: Revenue (₹m) | L3: Personnel (₹m) | M3: Subcontractors (₹m) | N3: Software + Facilities (₹m) | O3: Other Opex (₹m) | P3: Total Cost (₹m) | Q3: EBITDA (₹m)
A4: 46388 | B4: Cloud Services | C4: =Assumptions!B13 -> 145 | D4: =C4*(Assumptions!$B$29+Assumptions!$B$28)/12 -> 1.45 | E4: =C4*Assumptions!$B$29/12 -> 1.2083333 | F4: =C4+D4-E4 -> 145.24167 | G4: =(C4+F4)/2 -> 145.12083 | H4: =G4*Assumptions!C13 -> 118.99908 | I4: =MAX(0,MIN(0.95,Assumptions!D13+Assumptions!$B$30)) -> 0.77 | J4: =Assumptions!E13*(1+Assumptions!$B$31) -> 2317.5 | K4: =H4*I4*Assumptions!$B$21*J4/1000000 -> 33.976142 | L4: =G4*Assumptions!F13*(1+Assumptions!$B$32) -> 17.523341 | M4: =K4*Assumptions!$B$34 -> 2.5482107 | N4: =G4*(Assumptions!G13*(1+Assumptions!$B$33)+Assumptions!$B$35*(1+Assumptions!$B$33)) -> 2.4148107 | O4: =K4*Assumptions!$B$36*(1+Assumptions!$B$33) -> 1.5900835 | P4: =SUM(L4:O4) -> 24.076445 | Q4: =K4-P4 -> 9.8996969
A5: 46388 | B5: Data & Analytics | C5: =Assumptions!B14 -> 125 | D5: =C5*(Assumptions!$B$29+Assumptions!$B$28)/12 -> 1.25 | E5: =C5*Assumptions!$B$29/12 -> 1.0416667 | F5: =C5+D5-E5 -> 125.20833 | G5: =(C5+F5)/2 -> 125.10417 | H5: =G5*Assumptions!C14 -> 105.0875 | I5: =MAX(0,MIN(0.95,Assumptions!D14+Assumptions!$B$30)) -> 0.79 | J5: =Assumptions!E14*(1+Assumptions!$B$31) -> 2472 | K5: =H5*I5*Assumptions!$B$21*J5/1000000 -> 32.835724 | L5: =G5*Assumptions!F14*(1+Assumptions!$B$32) -> 15.763125 | M5: =K5*Assumptions!$B$34 -> 2.4626793 | N5: =G5*(Assumptions!G14*(1+Assumptions!$B$33)+Assumptions!$B$35*(1+Assumptions!$B$33)) -> 2.2118417 | O5: =K5*Assumptions!$B$36*(1+Assumptions!$B$33) -> 1.5367119 | P5: =SUM(L5:O5) -> 21.974358 | Q5: =K5-P5 -> 10.861366
A6: 46388 | B6: Cybersecurity | C6: =Assumptions!B15 -> 95 | D6: =C6*(Assumptions!$B$29+Assumptions!$B$28)/12 -> 0.95 | E6: =C6*Assumptions!$B$29/12 -> 0.79166667 | F6: =C6+D6-E6 -> 95.158333 | G6: =(C6+F6)/2 -> 95.079167 | H6: =G6*Assumptions!C15 -> 81.768083 | I6: =MAX(0,MIN(0.95,Assumptions!D15+Assumptions!$B$30)) -> 0.81 | J6: =Assumptions!E15*(1+Assumptions!$B$31) -> 2678 | K6: =H6*I6*Assumptions!$B$21*J6/1000000 -> 28.379151 | L6: =G6*Assumptions!F15*(1+Assumptions!$B$32) -> 12.978306 | M6: =K6*Assumptions!$B$34 -> 2.1284363 | N6: =G6*(Assumptions!G15*(1+Assumptions!$B$33)+Assumptions!$B$35*(1+Assumptions!$B$33)) -> 1.779882 | O6: =K6*Assumptions!$B$36*(1+Assumptions!$B$33) -> 1.3281442 | P6: =SUM(L6:O6) -> 18.214769 | Q6: =K6-P6 -> 10.164382
A7: 46388 | B7: Application Development | C7: =Assumptions!B16 -> 180 | D7: =C7*(Assumptions!$B$29+Assumptions!$B$28)/12 -> 1.8 | E7: =C7*Assumptions!$B$29/12 -> 1.5 | F7: =C7+D7-E7 -> 180.3 | G7: =(C7+F7)/2 -> 180.15 | H7: =G7*Assumptions!C16 -> 144.12 | I7: =MAX(0,MIN(0.95,Assumptions!D16+Assumptions!$B$30)) -> 0.75 | J7: =Assumptions!E16*(1+Assumptions!$B$31) -> 2163 | K7: =H7*I7*Assumptions!$B$21*J7/1000000 -> 37.407787 | L7: =G7*Assumptions!F16*(1+Assumptions!$B$32) -> 19.861538 | M7: =K7*Assumptions!$B$34 -> 2.805584 | N7: =G7*(Assumptions!G16*(1+Assumptions!$B$33)+Assumptions!$B$35*(1+Assumptions!$B$33)) -> 2.81034 | O7: =K7*Assumptions!$B$36*(1+Assumptions!$B$33) -> 1.7506844 | P7: =SUM(L7:O7) -> 27.228146 | Q7: =K7-P7 -> 10.179641
A8: 46388 | B8: Managed Services | C8: =Assumptions!B17 -> 155 | D8: =C8*(Assumptions!$B$29+Assumptions!$B$28)/12 -> 1.55 | E8: =C8*Assumptions!$B$29/12 -> 1.2916667 | F8: =C8+D8-E8 -> 155.25833 | G8: =(C8+F8)/2 -> 155.12917 | H8: =G8*Assumptions!C17 -> 121.00075 | I8: =MAX(0,MIN(0.95,Assumptions!D17+Assumptions!$B$30)) -> 0.73 | J8: =Assumptions!E17*(1+Assumptions!$B$31) -> 2008.5 | K8: =H8*I8*Assumptions!$B$21*J8/1000000 -> 28.385905 | L8: =G8*Assumptions!F17*(1+Assumptions!$B$32) -> 16.288563 | M8: =K8*Assumptions!$B$34 -> 2.1289429 | N8: =G8*(Assumptions!G17*(1+Assumptions!$B$33)+Assumptions!$B$35*(1+Assumptions!$B$33)) -> 2.2586807 | O8: =K8*Assumptions!$B$36*(1+Assumptions!$B$33) -> 1.3284603 | P8: =SUM(L8:O8) -> 22.004646 | Q8: =K8-P8 -> 6.3812584
A9: 46419 | B9: Cloud Services | C9: =F4 -> 145.24167 | D9: =C9*(Assumptions!$B$29+Assumptions!$B$28)/12 -> 1.4524167 | E9: =C9*Assumptions!$B$29/12 -> 1.2103472 | F9: =C9+D9-E9 -> 145.48374 | G9: =(C9+F9)/2 -> 145.3627 | H9: =G9*Assumptions!C13 -> 119.19742 | I9: =MAX(0,MIN(0.95,Assumptions!D13+Assumptions!$B$30)) -> 0.77 | J9: =Assumptions!E13*(1+Assumptions!$B$31) -> 2317.5 | K9: =H9*I9*Assumptions!$B$21*J9/1000000 -> 34.032769 | L9: =G9*Assumptions!F13*(1+Assumptions!$B$32) -> 17.552546 | M9: =K9*Assumptions!$B$34 -> 2.5524577 | N9: =G9*(Assumptions!G13*(1+Assumptions!$B$33)+Assumptions!$B$35*(1+Assumptions!$B$33)) -> 2.4188354 | O9: =K9*Assumptions!$B$36*(1+Assumptions!$B$33) -> 1.5927336 | P9: =SUM(L9:O9) -> 24.116573 | Q9: =K9-P9 -> 9.9161964
A10: 46419 | B10: Data & Analytics | C10: =F5 -> 125.20833 | D10: =C10*(Assumptions!$B$29+Assumptions!$B$28)/12 -> 1.2520833 | E10: =C10*Assumptions!$B$29/12 -> 1.0434028 | F10: =C10+D10-E10 -> 125.41701 | G10: =(C10+F10)/2 -> 125.31267 | H10: =G10*Assumptions!C14 -> 105.26265 | I10: =MAX(0,MIN(0.95,Assumptions!D14+Assumptions!$B$30)) -> 0.79 | J10: =Assumptions!E14*(1+Assumptions!$B$31) -> 2472 | K10: =H10*I10*Assumptions!$B$21*J10/1000000 -> 32.890451 | L10: =G10*Assumptions!F14*(1+Assumptions!$B$32) -> 15.789397 | M10: =K10*Assumptions!$B$34 -> 2.4667838 | N10: =G10*(Assumptions!G14*(1+Assumptions!$B$33)+Assumptions!$B$35*(1+Assumptions!$B$33)) -> 2.2155281 | O10: =K10*Assumptions!$B$36*(1+Assumptions!$B$33) -> 1.5392731 | P10: =SUM(L10:O10) -> 22.010982 | Q10: =K10-P10 -> 10.879469
A11: 46419 | B11: Cybersecurity | C11: =F6 -> 95.158333 | D11: =C11*(Assumptions!$B$29+Assumptions!$B$28)/12 -> 0.95158333 | E11: =C11*Assumptions!$B$29/12 -> 0.79298611 | F11: =C11+D11-E11 -> 95.316931 | G11: =(C11+F11)/2 -> 95.237632 | H11: =G11*Assumptions!C15 -> 81.904363 | I11: =MAX(0,MIN(0.95,Assumptions!D15+Assumptions!$B$30)) -> 0.81 | J11: =Assumptions!E15*(1+Assumptions!$B$31) -> 2678 | K11: =H11*I11*Assumptions!$B$21*J11/1000000 -> 28.426449 | L11: =G11*Assumptions!F15*(1+Assumptions!$B$32) -> 12.999937 | M11: =K11*Assumptions!$B$34 -> 2.1319837 | N11: =G11*(Assumptions!G15*(1+Assumptions!$B$33)+Assumptions!$B$35*(1+Assumptions!$B$33)) -> 1.7828485 | O11: =K11*Assumptions!$B$36*(1+Assumptions!$B$33) -> 1.3303578 | P11: =SUM(L11:O11) -> 18.245127 | Q11: =K11-P11 -> 10.181322
A12: 46419 | B12: Application Development | C12: =F7 -> 180.3 | D12: =C12*(Assumptions!$B$29+Assumptions!$B$28)/12 -> 1.803 | E12: =C12*Assumptions!$B$29/12 -> 1.5025 | F12: =C12+D12-E12 -> 180.6005 | G12: =(C12+F12)/2 -> 180.45025 | H12: =G12*Assumptions!C16 -> 144.3602 | I12: =MAX(0,MIN(0.95,Assumptions!D16+Assumptions!$B$30)) -> 0.75 | J12: =Assumptions!E16*(1+Assumptions!$B$31) -> 2163 | K12: =H12*I12*Assumptions!$B$21*J12/1000000 -> 37.470134 | L12: =G12*Assumptions!F16*(1+Assumptions!$B$32) -> 19.89464 | M12: =K12*Assumptions!$B$34 -> 2.81026 | N12: =G12*(Assumptions!G16*(1+Assumptions!$B$33)+Assumptions!$B$35*(1+Assumptions!$B$33)) -> 2.8150239 | O12: =K12*Assumptions!$B$36*(1+Assumptions!$B$33) -> 1.7536022 | P12: =SUM(L12:O12) -> 27.273526 | Q12: =K12-P12 -> 10.196607
A13: 46419 | B13: Managed Services | C13: =F8 -> 155.25833 | D13: =C13*(Assumptions!$B$29+Assumptions!$B$28)/12 -> 1.5525833 | E13: =C13*Assumptions!$B$29/12 -> 1.2938194 | F13: =C13+D13-E13 -> 155.5171 | G13: =(C13+F13)/2 -> 155.38772 | H13: =G13*Assumptions!C17 -> 121.20242 | I13: =MAX(0,MIN(0.95,Assumptions!D17+Assumptions!$B$30)) -> 0.73 | J13: =Assumptions!E17*(1+Assumptions!$B$31) -> 2008.5 | K13: =H13*I13*Assumptions!$B$21*J13/1000000 -> 28.433215 | L13: =G13*Assumptions!F17*(1+Assumptions!$B$32) -> 16.31571 | M13: =K13*Assumptions!$B$34 -> 2.1324911 | N13: =G13*(Assumptions!G17*(1+Assumptions!$B$33)+Assumptions!$B$35*(1+Assumptions!$B$33)) -> 2.2624451 | O13: =K13*Assumptions!$B$36*(1+Assumptions!$B$33) -> 1.3306744 | P13: =SUM(L13:O13) -> 22.041321 | Q13: =K13-P13 -> 6.3918938
A14: 46447 | B14: Cloud Services | C14: =F9 -> 145.48374 | D14: =C14*(Assumptions!$B$29+Assumptions!$B$28)/12 -> 1.4548374 | E14: =C14*Assumptions!$B$29/12 -> 1.2123645 | F14: =C14+D14-E14 -> 145.72621 | G14: =(C14+F14)/2 -> 145.60497 | H14: =G14*Assumptions!C13 -> 119.39608 | I14: =MAX(0,MIN(0.95,Assumptions!D13+Assumptions!$B$30)) -> 0.77 | J14: =Assumptions!E13*(1+Assumptions!$B$31) -> 2317.5 | K14: =H14*I14*Assumptions!$B$21*J14/1000000 -> 34.08949 | L14: =G14*Assumptions!F13*(1+Assumptions!$B$32) -> 17.5818 | M14: =K14*Assumptions!$B$34 -> 2.5567118 | N14: =G14*(Assumptions!G13*(1+Assumptions!$B$33)+Assumptions!$B$35*(1+Assumptions!$B$33)) -> 2.4228667 | O14: =K14*Assumptions!$B$36*(1+Assumptions!$B$33) -> 1.5953882 | P14: =SUM(L14:O14) -> 24.156767 | Q14: =K14-P14 -> 9.9327233
A15: 46447 | B15: Data & Analytics | C15: =F10 -> 125.41701 | D15: =C15*(Assumptions!$B$29+Assumptions!$B$28)/12 -> 1.2541701 | E15: =C15*Assumptions!$B$29/12 -> 1.0451418 | F15: =C15+D15-E15 -> 125.62604 | G15: =(C15+F15)/2 -> 125.52153 | H15: =G15*Assumptions!C14 -> 105.43808 | I15: =MAX(0,MIN(0.95,Assumptions!D14+Assumptions!$B$30)) -> 0.79 | J15: =Assumptions!E14*(1+Assumptions!$B$31) -> 2472 | K15: =H15*I15*Assumptions!$B$21*J15/1000000 -> 32.945268 | L15: =G15*Assumptions!F14*(1+Assumptions!$B$32) -> 15.815713 | M15: =K15*Assumptions!$B$34 -> 2.4708951 | N15: =G15*(Assumptions!G14*(1+Assumptions!$B$33)+Assumptions!$B$35*(1+Assumptions!$B$33)) -> 2.2192206 | O15: =K15*Assumptions!$B$36*(1+Assumptions!$B$33) -> 1.5418385 | P15: =SUM(L15:O15) -> 22.047667 | Q15: =K15-P15 -> 10.897601
A16: 46447 | B16: Cybersecurity | C16: =F11 -> 95.316931 | D16: =C16*(Assumptions!$B$29+Assumptions!$B$28)/12 -> 0.95316931 | E16: =C16*Assumptions!$B$29/12 -> 0.79430775 | F16: =C16+D16-E16 -> 95.475792 | G16: =(C16+F16)/2 -> 95.396361 | H16: =G16*Assumptions!C15 -> 82.040871 | I16: =MAX(0,MIN(0.95,Assumptions!D15+Assumptions!$B$30)) -> 0.81 | J16: =Assumptions!E15*(1+Assumptions!$B$31) -> 2678 | K16: =H16*I16*Assumptions!$B$21*J16/1000000 -> 28.473827 | L16: =G16*Assumptions!F15*(1+Assumptions!$B$32) -> 13.021603 | M16: =K16*Assumptions!$B$34 -> 2.135537 | N16: =G16*(Assumptions!G15*(1+Assumptions!$B$33)+Assumptions!$B$35*(1+Assumptions!$B$33)) -> 1.7858199 | O16: =K16*Assumptions!$B$36*(1+Assumptions!$B$33) -> 1.3325751 | P16: =SUM(L16:O16) -> 18.275535 | Q16: =K16-P16 -> 10.198291
A17: 46447 | B17: Application Development | C17: =F12 -> 180.6005 | D17: =C17*(Assumptions!$B$29+Assumptions!$B$28)/12 -> 1.806005 | E17: =C17*Assumptions!$B$29/12 -> 1.5050042 | F17: =C17+D17-E17 -> 180.9015 | G17: =(C17+F17)/2 -> 180.751 | H17: =G17*Assumptions!C16 -> 144.6008 | I17: =MAX(0,MIN(0.95,Assumptions!D16+Assumptions!$B$30)) -> 0.75 | J17: =Assumptions!E16*(1+Assumptions!$B$31) -> 2163 | K17: =H17*I17*Assumptions!$B$21*J17/1000000 -> 37.532584 | L17: =G17*Assumptions!F16*(1+Assumptions!$B$32) -> 19.927798 | M17: =K17*Assumptions!$B$34 -> 2.8149438 | N17: =G17*(Assumptions!G16*(1+Assumptions!$B$33)+Assumptions!$B$35*(1+Assumptions!$B$33)) -> 2.8197156 | O17: =K17*Assumptions!$B$36*(1+Assumptions!$B$33) -> 1.7565249 | P17: =SUM(L17:O17) -> 27.318982 | Q17: =K17-P17 -> 10.213602
A18: 46447 | B18: Managed Services | C18: =F13 -> 155.5171 | D18: =C18*(Assumptions!$B$29+Assumptions!$B$28)/12 -> 1.555171 | E18: =C18*Assumptions!$B$29/12 -> 1.2959758 | F18: =C18+D18-E18 -> 155.77629 | G18: =(C18+F18)/2 -> 155.64669 | H18: =G18*Assumptions!C17 -> 121.40442 | I18: =MAX(0,MIN(0.95,Assumptions!D17+Assumptions!$B$30)) -> 0.73 | J18: =Assumptions!E17*(1+Assumptions!$B$31) -> 2008.5 | K18: =H18*I18*Assumptions!$B$21*J18/1000000 -> 28.480603 | L18: =G18*Assumptions!F17*(1+Assumptions!$B$32) -> 16.342903 | M18: =K18*Assumptions!$B$34 -> 2.1360452 | N18: =G18*(Assumptions!G17*(1+Assumptions!$B$33)+Assumptions!$B$35*(1+Assumptions!$B$33)) -> 2.2662159 | O18: =K18*Assumptions!$B$36*(1+Assumptions!$B$33) -> 1.3328922 | P18: =SUM(L18:O18) -> 22.078056 | Q18: =K18-P18 -> 6.402547
A19: 46478 | B19: Cloud Services | C19: =F14 -> 145.72621 | D19: =C19*(Assumptions!$B$29+Assumptions!$B$28)/12 -> 1.4572621 | E19: =C19*Assumptions!$B$29/12 -> 1.2143851 | F19: =C19+D19-E19 -> 145.96909 | G19: =(C19+F19)/2 -> 145.84765 | H19: =G19*Assumptions!C13 -> 119.59507 | I19: =MAX(0,MIN(0.95,Assumptions!D13+Assumptions!$B$30)) -> 0.77 | J19: =Assumptions!E13*(1+Assumptions!$B$31) -> 2317.5 | K19: =H19*I19*Assumptions!$B$21*J19/1000000 -> 34.146306 | L19: =G19*Assumptions!F13*(1+Assumptions!$B$32) -> 17.611103 | M19: =K19*Assumptions!$B$34 -> 2.560973 | N19: =G19*(Assumptions!G13*(1+Assumptions!$B$33)+Assumptions!$B$35*(1+Assumptions!$B$33)) -> 2.4269049 | O19: =K19*Assumptions!$B$36*(1+Assumptions!$B$33) -> 1.5980471 | P19: =SUM(L19:O19) -> 24.197028 | Q19: =K19-P19 -> 9.9492779
A20: 46478 | B20: Data & Analytics | C20: =F15 -> 125.62604 | D20: =C20*(Assumptions!$B$29+Assumptions!$B$28)/12 -> 1.2562604 | E20: =C20*Assumptions!$B$29/12 -> 1.0468837 | F20: =C20+D20-E20 -> 125.83542 | G20: =(C20+F20)/2 -> 125.73073 | H20: =G20*Assumptions!C14 -> 105.61381 | I20: =MAX(0,MIN(0.95,Assumptions!D14+Assumptions!$B$30)) -> 0.79 | J20: =Assumptions!E14*(1+Assumptions!$B$31) -> 2472 | K20: =H20*I20*Assumptions!$B$21*J20/1000000 -> 33.000177 | L20: =G20*Assumptions!F14*(1+Assumptions!$B$32) -> 15.842072 | M20: =K20*Assumptions!$B$34 -> 2.4750133 | N20: =G20*(Assumptions!G14*(1+Assumptions!$B$33)+Assumptions!$B$35*(1+Assumptions!$B$33)) -> 2.2229193 | O20: =K20*Assumptions!$B$36*(1+Assumptions!$B$33) -> 1.5444083 | P20: =SUM(L20:O20) -> 22.084413 | Q20: =K20-P20 -> 10.915764
A21: 46478 | B21: Cybersecurity | C21: =F16 -> 95.475792 | D21: =C21*(Assumptions!$B$29+Assumptions!$B$28)/12 -> 0.95475792 | E21: =C21*Assumptions!$B$29/12 -> 0.7956316 | F21: =C21+D21-E21 -> 95.634918 | G21: =(C21+F21)/2 -> 95.555355 | H21: =G21*Assumptions!C15 -> 82.177606 | I21: =MAX(0,MIN(0.95,Assumptions!D15+Assumptions!$B$30)) -> 0.81 | J21: =Assumptions!E15*(1+Assumptions!$B$31) -> 2678 | K21: =H21*I21*Assumptions!$B$21*J21/1000000 -> 28.521283 | L21: =G21*Assumptions!F15*(1+Assumptions!$B$32) -> 13.043306 | M21: =K21*Assumptions!$B$34 -> 2.1390962 | N21: =G21*(Assumptions!G15*(1+Assumptions!$B$33)+Assumptions!$B$35*(1+Assumptions!$B$33)) -> 1.7887963 | O21: =K21*Assumptions!$B$36*(1+Assumptions!$B$33) -> 1.334796 | P21: =SUM(L21:O21) -> 18.305995 | Q21: =K21-P21 -> 10.215288
A22: 46478 | B22: Application Development | C22: =F17 -> 180.9015 | D22: =C22*(Assumptions!$B$29+Assumptions!$B$28)/12 -> 1.809015 | E22: =C22*Assumptions!$B$29/12 -> 1.5075125 | F22: =C22+D22-E22 -> 181.203 | G22: =(C22+F22)/2 -> 181.05225 | H22: =G22*Assumptions!C16 -> 144.8418 | I22: =MAX(0,MIN(0.95,Assumptions!D16+Assumptions!$B$30)) -> 0.75 | J22: =Assumptions!E16*(1+Assumptions!$B$31) -> 2163 | K22: =H22*I22*Assumptions!$B$21*J22/1000000 -> 37.595138 | L22: =G22*Assumptions!F16*(1+Assumptions!$B$32) -> 19.961011 | M22: =K22*Assumptions!$B$34 -> 2.8196354 | N22: =G22*(Assumptions!G16*(1+Assumptions!$B$33)+Assumptions!$B$35*(1+Assumptions!$B$33)) -> 2.8244151 | O22: =K22*Assumptions!$B$36*(1+Assumptions!$B$33) -> 1.7594525 | P22: =SUM(L22:O22) -> 27.364514 | Q22: =K22-P22 -> 10.230624
A23: 46478 | B23: Managed Services | C23: =F18 -> 155.77629 | D23: =C23*(Assumptions!$B$29+Assumptions!$B$28)/12 -> 1.5577629 | E23: =C23*Assumptions!$B$29/12 -> 1.2981358 | F23: =C23+D23-E23 -> 156.03592 | G23: =(C23+F23)/2 -> 155.90611 | H23: =G23*Assumptions!C17 -> 121.60676 | I23: =MAX(0,MIN(0.95,Assumptions!D17+Assumptions!$B$30)) -> 0.73 | J23: =Assumptions!E17*(1+Assumptions!$B$31) -> 2008.5 | K23: =H23*I23*Assumptions!$B$21*J23/1000000 -> 28.528071 | L23: =G23*Assumptions!F17*(1+Assumptions!$B$32) -> 16.370141 | M23: =K23*Assumptions!$B$34 -> 2.1396053 | N23: =G23*(Assumptions!G17*(1+Assumptions!$B$33)+Assumptions!$B$35*(1+Assumptions!$B$33)) -> 2.2699929 | O23: =K23*Assumptions!$B$36*(1+Assumptions!$B$33) -> 1.3351137 | P23: =SUM(L23:O23) -> 22.114853 | Q23: =K23-P23 -> 6.4132179
A24: 46508 | B24: Cloud Services | C24: =F19 -> 145.96909 | D24: =C24*(Assumptions!$B$29+Assumptions!$B$28)/12 -> 1.4596909 | E24: =C24*Assumptions!$B$29/12 -> 1.2164091 | F24: =C24+D24-E24 -> 146.21237 | G24: =(C24+F24)/2 -> 146.09073 | H24: =G24*Assumptions!C13 -> 119.7944 | I24: =MAX(0,MIN(0.95,Assumptions!D13+Assumptions!$B$30)) -> 0.77 | J24: =Assumptions!E13*(1+Assumptions!$B$31) -> 2317.5 | K24: =H24*I24*Assumptions!$B$21*J24/1000000 -> 34.203217 | L24: =G24*Assumptions!F13*(1+Assumptions!$B$32) -> 17.640455 | M24: =K24*Assumptions!$B$34 -> 2.5652413 | N24: =G24*(Assumptions!G13*(1+Assumptions!$B$33)+Assumptions!$B$35*(1+Assumptions!$B$33)) -> 2.4309497 | O24: =K24*Assumptions!$B$36*(1+Assumptions!$B$33) -> 1.6007105 | P24: =SUM(L24:O24) -> 24.237357 | Q24: =K24-P24 -> 9.96586
A25: 46508 | B25: Data & Analytics | C25: =F20 -> 125.83542 | D25: =C25*(Assumptions!$B$29+Assumptions!$B$28)/12 -> 1.2583542 | E25: =C25*Assumptions!$B$29/12 -> 1.0486285 | F25: =C25+D25-E25 -> 126.04514 | G25: =(C25+F25)/2 -> 125.94028 | H25: =G25*Assumptions!C14 -> 105.78984 | I25: =MAX(0,MIN(0.95,Assumptions!D14+Assumptions!$B$30)) -> 0.79 | J25: =Assumptions!E14*(1+Assumptions!$B$31) -> 2472 | K25: =H25*I25*Assumptions!$B$21*J25/1000000 -> 33.055177 | L25: =G25*Assumptions!F14*(1+Assumptions!$B$32) -> 15.868476 | M25: =K25*Assumptions!$B$34 -> 2.4791383 | N25: =G25*(Assumptions!G14*(1+Assumptions!$B$33)+Assumptions!$B$35*(1+Assumptions!$B$33)) -> 2.2266242 | O25: =K25*Assumptions!$B$36*(1+Assumptions!$B$33) -> 1.5469823 | P25: =SUM(L25:O25) -> 22.12122 | Q25: =K25-P25 -> 10.933957
A26: 46508 | B26: Cybersecurity | C26: =F21 -> 95.634918 | D26: =C26*(Assumptions!$B$29+Assumptions!$B$28)/12 -> 0.95634918 | E26: =C26*Assumptions!$B$29/12 -> 0.79695765 | F26: =C26+D26-E26 -> 95.79431 | G26: =(C26+F26)/2 -> 95.714614 | H26: =G26*Assumptions!C15 -> 82.314568 | I26: =MAX(0,MIN(0.95,Assumptions!D15+Assumptions!$B$30)) -> 0.81 | J26: =Assumptions!E15*(1+Assumptions!$B$31) -> 2678 | K26: =H26*I26*Assumptions!$B$21*J26/1000000 -> 28.568818 | L26: =G26*Assumptions!F15*(1+Assumptions!$B$32) -> 13.065045 | M26: =K26*Assumptions!$B$34 -> 2.1426614 | N26: =G26*(Assumptions!G15*(1+Assumptions!$B$33)+Assumptions!$B$35*(1+Assumptions!$B$33)) -> 1.7917776 | O26: =K26*Assumptions!$B$36*(1+Assumptions!$B$33) -> 1.3370207 | P26: =SUM(L26:O26) -> 18.336504 | Q26: =K26-P26 -> 10.232314
A27: 46508 | B27: Application Development | C27: =F22 -> 181.203 | D27: =C27*(Assumptions!$B$29+Assumptions!$B$28)/12 -> 1.81203 | E27: =C27*Assumptions!$B$29/12 -> 1.510025 | F27: =C27+D27-E27 -> 181.50501 | G27: =(C27+F27)/2 -> 181.35401 | H27: =G27*Assumptions!C16 -> 145.0832 | I27: =MAX(0,MIN(0.95,Assumptions!D16+Assumptions!$B$30)) -> 0.75 | J27: =Assumptions!E16*(1+Assumptions!$B$31) -> 2163 | K27: =H27*I27*Assumptions!$B$21*J27/1000000 -> 37.657797 | L27: =G27*Assumptions!F16*(1+Assumptions!$B$32) -> 19.994279 | M27: =K27*Assumptions!$B$34 -> 2.8243347 | N27: =G27*(Assumptions!G16*(1+Assumptions!$B$33)+Assumptions!$B$35*(1+Assumptions!$B$33)) -> 2.8291225 | O27: =K27*Assumptions!$B$36*(1+Assumptions!$B$33) -> 1.7623849 | P27: =SUM(L27:O27) -> 27.410121 | Q27: =K27-P27 -> 10.247675
A28: 46508 | B28: Managed Services | C28: =F23 -> 156.03592 | D28: =C28*(Assumptions!$B$29+Assumptions!$B$28)/12 -> 1.5603592 | E28: =C28*Assumptions!$B$29/12 -> 1.3002993 | F28: =C28+D28-E28 -> 156.29598 | G28: =(C28+F28)/2 -> 156.16595 | H28: =G28*Assumptions!C17 -> 121.80944 | I28: =MAX(0,MIN(0.95,Assumptions!D17+Assumptions!$B$30)) -> 0.73 | J28: =Assumptions!E17*(1+Assumptions!$B$31) -> 2008.5 | K28: =H28*I28*Assumptions!$B$21*J28/1000000 -> 28.575618 | L28: =G28*Assumptions!F17*(1+Assumptions!$B$32) -> 16.397425 | M28: =K28*Assumptions!$B$34 -> 2.1431713 | N28: =G28*(Assumptions!G17*(1+Assumptions!$B$33)+Assumptions!$B$35*(1+Assumptions!$B$33)) -> 2.2737762 | O28: =K28*Assumptions!$B$36*(1+Assumptions!$B$33) -> 1.3373389 | P28: =SUM(L28:O28) -> 22.151711 | Q28: =K28-P28 -> 6.4239066
A29: 46539 | B29: Cloud Services | C29: =F24 -> 146.21237 | D29: =C29*(Assumptions!$B$29+Assumptions!$B$28)/12 -> 1.4621237 | E29: =C29*Assumptions!$B$29/12 -> 1.2184364 | F29: =C29+D29-E29 -> 146.45606 | G29: =(C29+F29)/2 -> 146.33421 | H29: =G29*Assumptions!C13 -> 119.99405 | I29: =MAX(0,MIN(0.95,Assumptions!D13+Assumptions!$B$30)) -> 0.77 | J29: =Assumptions!E13*(1+Assumptions!$B$31) -> 2317.5 | K29: =H29*I29*Assumptions!$B$21*J29/1000000 -> 34.260222 | L29: =G29*Assumptions!F13*(1+Assumptions!$B$32) -> 17.669856 | M29: =K29*Assumptions!$B$34 -> 2.5695167 | N29: =G29*(Assumptions!G13*(1+Assumptions!$B$33)+Assumptions!$B$35*(1+Assumptions!$B$33)) -> 2.4350013 | O29: =K29*Assumptions!$B$36*(1+Assumptions!$B$33) -> 1.6033784 | P29: =SUM(L29:O29) -> 24.277752 | Q29: =K29-P29 -> 9.9824698
A30: 46539 | B30: Data & Analytics | C30: =F25 -> 126.04514 | D30: =C30*(Assumptions!$B$29+Assumptions!$B$28)/12 -> 1.2604514 | E30: =C30*Assumptions!$B$29/12 -> 1.0503762 | F30: =C30+D30-E30 -> 126.25522 | G30: =(C30+F30)/2 -> 126.15018 | H30: =G30*Assumptions!C14 -> 105.96615 | I30: =MAX(0,MIN(0.95,Assumptions!D14+Assumptions!$B$30)) -> 0.79 | J30: =Assumptions!E14*(1+Assumptions!$B$31) -> 2472 | K30: =H30*I30*Assumptions!$B$21*J30/1000000 -> 33.110269 | L30: =G30*Assumptions!F14*(1+Assumptions!$B$32) -> 15.894923 | M30: =K30*Assumptions!$B$34 -> 2.4832702 | N30: =G30*(Assumptions!G14*(1+Assumptions!$B$33)+Assumptions!$B$35*(1+Assumptions!$B$33)) -> 2.2303352 | O30: =K30*Assumptions!$B$36*(1+Assumptions!$B$33) -> 1.5495606 | P30: =SUM(L30:O30) -> 22.158089 | Q30: =K30-P30 -> 10.95218
A31: 46539 | B31: Cybersecurity | C31: =F26 -> 95.79431 | D31: =C31*(Assumptions!$B$29+Assumptions!$B$28)/12 -> 0.9579431 | E31: =C31*Assumptions!$B$29/12 -> 0.79828592 | F31: =C31+D31-E31 -> 95.953967 | G31: =(C31+F31)/2 -> 95.874139 | H31: =G31*Assumptions!C15 -> 82.451759 | I31: =MAX(0,MIN(0.95,Assumptions!D15+Assumptions!$B$30)) -> 0.81 | J31: =Assumptions!E15*(1+Assumptions!$B$31) -> 2678 | K31: =H31*I31*Assumptions!$B$21*J31/1000000 -> 28.616433 | L31: =G31*Assumptions!F15*(1+Assumptions!$B$32) -> 13.08682 | M31: =K31*Assumptions!$B$34 -> 2.1462325 | N31: =G31*(Assumptions!G15*(1+Assumptions!$B$33)+Assumptions!$B$35*(1+Assumptions!$B$33)) -> 1.7947639 | O31: =K31*Assumptions!$B$36*(1+Assumptions!$B$33) -> 1.3392491 | P31: =SUM(L31:O31) -> 18.367065 | Q31: =K31-P31 -> 10.249368
A32: 46539 | B32: Application Development | C32: =F27 -> 181.50501 | D32: =C32*(Assumptions!$B$29+Assumptions!$B$28)/12 -> 1.8150501 | E32: =C32*Assumptions!$B$29/12 -> 1.5125417 | F32: =C32+D32-E32 -> 181.80752 | G32: =(C32+F32)/2 -> 181.65626 | H32: =G32*Assumptions!C16 -> 145.32501 | I32: =MAX(0,MIN(0.95,Assumptions!D16+Assumptions!$B$30)) -> 0.75 | J32: =Assumptions!E16*(1+Assumptions!$B$31) -> 2163 | K32: =H32*I32*Assumptions!$B$21*J32/1000000 -> 37.72056 | L32: =G32*Assumptions!F16*(1+Assumptions!$B$32) -> 20.027603 | M32: =K32*Assumptions!$B$34 -> 2.829042 | N32: =G32*(Assumptions!G16*(1+Assumptions!$B$33)+Assumptions!$B$35*(1+Assumptions!$B$33)) -> 2.8338377 | O32: =K32*Assumptions!$B$36*(1+Assumptions!$B$33) -> 1.7653222 | P32: =SUM(L32:O32) -> 27.455805 | Q32: =K32-P32 -> 10.264755
A33: 46539 | B33: Managed Services | C33: =F28 -> 156.29598 | D33: =C33*(Assumptions!$B$29+Assumptions!$B$28)/12 -> 1.5629598 | E33: =C33*Assumptions!$B$29/12 -> 1.3024665 | F33: =C33+D33-E33 -> 156.55647 | G33: =(C33+F33)/2 -> 156.42623 | H33: =G33*Assumptions!C17 -> 122.01246 | I33: =MAX(0,MIN(0.95,Assumptions!D17+Assumptions!$B$30)) -> 0.73 | J33: =Assumptions!E17*(1+Assumptions!$B$31) -> 2008.5 | K33: =H33*I33*Assumptions!$B$21*J33/1000000 -> 28.623244 | L33: =G33*Assumptions!F17*(1+Assumptions!$B$32) -> 16.424754 | M33: =K33*Assumptions!$B$34 -> 2.1467433 | N33: =G33*(Assumptions!G17*(1+Assumptions!$B$33)+Assumptions!$B$35*(1+Assumptions!$B$33)) -> 2.2775659 | O33: =K33*Assumptions!$B$36*(1+Assumptions!$B$33) -> 1.3395678 | P33: =SUM(L33:O33) -> 22.188631 | Q33: =K33-P33 -> 6.4346131
A34: 46569 | B34: Cloud Services | C34: =F29 -> 146.45606 | D34: =C34*(Assumptions!$B$29+Assumptions!$B$28)/12 -> 1.4645606 | E34: =C34*Assumptions!$B$29/12 -> 1.2204671 | F34: =C34+D34-E34 -> 146.70015 | G34: =(C34+F34)/2 -> 146.5781 | H34: =G34*Assumptions!C13 -> 120.19404 | I34: =MAX(0,MIN(0.95,Assumptions!D13+Assumptions!$B$30)) -> 0.77 | J34: =Assumptions!E13*(1+Assumptions!$B$31) -> 2317.5 | K34: =H34*I34*Assumptions!$B$21*J34/1000000 -> 34.317323 | L34: =G34*Assumptions!F13*(1+Assumptions!$B$32) -> 17.699306 | M34: =K34*Assumptions!$B$34 -> 2.5737992 | N34: =G34*(Assumptions!G13*(1+Assumptions!$B$33)+Assumptions!$B$35*(1+Assumptions!$B$33)) -> 2.4390596 | O34: =K34*Assumptions!$B$36*(1+Assumptions!$B$33) -> 1.6060507 | P34: =SUM(L34:O34) -> 24.318215 | Q34: =K34-P34 -> 9.9991072
A35: 46569 | B35: Data & Analytics | C35: =F30 -> 126.25522 | D35: =C35*(Assumptions!$B$29+Assumptions!$B$28)/12 -> 1.2625522 | E35: =C35*Assumptions!$B$29/12 -> 1.0521268 | F35: =C35+D35-E35 -> 126.46565 | G35: =(C35+F35)/2 -> 126.36043 | H35: =G35*Assumptions!C14 -> 106.14276 | I35: =MAX(0,MIN(0.95,Assumptions!D14+Assumptions!$B$30)) -> 0.79 | J35: =Assumptions!E14*(1+Assumptions!$B$31) -> 2472 | K35: =H35*I35*Assumptions!$B$21*J35/1000000 -> 33.165453 | L35: =G35*Assumptions!F14*(1+Assumptions!$B$32) -> 15.921415 | M35: =K35*Assumptions!$B$34 -> 2.487409 | N35: =G35*(Assumptions!G14*(1+Assumptions!$B$33)+Assumptions!$B$35*(1+Assumptions!$B$33)) -> 2.2340524 | O35: =K35*Assumptions!$B$36*(1+Assumptions!$B$33) -> 1.5521432 | P35: =SUM(L35:O35) -> 22.195019 | Q35: =K35-P35 -> 10.970434
A36: 46569 | B36: Cybersecurity | C36: =F31 -> 95.953967 | D36: =C36*(Assumptions!$B$29+Assumptions!$B$28)/12 -> 0.95953967 | E36: =C36*Assumptions!$B$29/12 -> 0.79961639 | F36: =C36+D36-E36 -> 96.11389 | G36: =(C36+F36)/2 -> 96.033929 | H36: =G36*Assumptions!C15 -> 82.589179 | I36: =MAX(0,MIN(0.95,Assumptions!D15+Assumptions!$B$30)) -> 0.81 | J36: =Assumptions!E15*(1+Assumptions!$B$31) -> 2678 | K36: =H36*I36*Assumptions!$B$21*J36/1000000 -> 28.664127 | L36: =G36*Assumptions!F15*(1+Assumptions!$B$32) -> 13.108631 | M36: =K36*Assumptions!$B$34 -> 2.1498095 | N36: =G36*(Assumptions!G15*(1+Assumptions!$B$33)+Assumptions!$B$35*(1+Assumptions!$B$33)) -> 1.7977551 | O36: =K36*Assumptions!$B$36*(1+Assumptions!$B$33) -> 1.3414812 | P36: =SUM(L36:O36) -> 18.397677 | Q36: =K36-P36 -> 10.26645
A37: 46569 | B37: Application Development | C37: =F32 -> 181.80752 | D37: =C37*(Assumptions!$B$29+Assumptions!$B$28)/12 -> 1.8180752 | E37: =C37*Assumptions!$B$29/12 -> 1.5150626 | F37: =C37+D37-E37 -> 182.11053 | G37: =(C37+F37)/2 -> 181.95902 | H37: =G37*Assumptions!C16 -> 145.56722 | I37: =MAX(0,MIN(0.95,Assumptions!D16+Assumptions!$B$30)) -> 0.75 | J37: =Assumptions!E16*(1+Assumptions!$B$31) -> 2163 | K37: =H37*I37*Assumptions!$B$21*J37/1000000 -> 37.783427 | L37: =G37*Assumptions!F16*(1+Assumptions!$B$32) -> 20.060982 | M37: =K37*Assumptions!$B$34 -> 2.833757 | N37: =G37*(Assumptions!G16*(1+Assumptions!$B$33)+Assumptions!$B$35*(1+Assumptions!$B$33)) -> 2.8385608 | O37: =K37*Assumptions!$B$36*(1+Assumptions!$B$33) -> 1.7682644 | P37: =SUM(L37:O37) -> 27.501564 | Q37: =K37-P37 -> 10.281863
A38: 46569 | B38: Managed Services | C38: =F33 -> 156.55647 | D38: =C38*(Assumptions!$B$29+Assumptions!$B$28)/12 -> 1.5655647 | E38: =C38*Assumptions!$B$29/12 -> 1.3046373 | F38: =C38+D38-E38 -> 156.8174 | G38: =(C38+F38)/2 -> 156.68694 | H38: =G38*Assumptions!C17 -> 122.21581 | I38: =MAX(0,MIN(0.95,Assumptions!D17+Assumptions!$B$30)) -> 0.73 | J38: =Assumptions!E17*(1+Assumptions!$B$31) -> 2008.5 | K38: =H38*I38*Assumptions!$B$21*J38/1000000 -> 28.670949 | L38: =G38*Assumptions!F17*(1+Assumptions!$B$32) -> 16.452128 | M38: =K38*Assumptions!$B$34 -> 2.1503212 | N38: =G38*(Assumptions!G17*(1+Assumptions!$B$33)+Assumptions!$B$35*(1+Assumptions!$B$33)) -> 2.2813618 | O38: =K38*Assumptions!$B$36*(1+Assumptions!$B$33) -> 1.3418004 | P38: =SUM(L38:O38) -> 22.225612 | Q38: =K38-P38 -> 6.4453374
A39: 46600 | B39: Cloud Services | C39: =F34 -> 146.70015 | D39: =C39*(Assumptions!$B$29+Assumptions!$B$28)/12 -> 1.4670015 | E39: =C39*Assumptions!$B$29/12 -> 1.2225012 | F39: =C39+D39-E39 -> 146.94465 | G39: =(C39+F39)/2 -> 146.8224 | H39: =G39*Assumptions!C13 -> 120.39437 | I39: =MAX(0,MIN(0.95,Assumptions!D13+Assumptions!$B$30)) -> 0.77 | J39: =Assumptions!E13*(1+Assumptions!$B$31) -> 2317.5 | K39: =H39*I39*Assumptions!$B$21*J39/1000000 -> 34.374518 | L39: =G39*Assumptions!F13*(1+Assumptions!$B$32) -> 17.728805 | M39: =K39*Assumptions!$B$34 -> 2.5780889 | N39: =G39*(Assumptions!G13*(1+Assumptions!$B$33)+Assumptions!$B$35*(1+Assumptions!$B$33)) -> 2.4431247 | O39: =K39*Assumptions!$B$36*(1+Assumptions!$B$33) -> 1.6087274 | P39: =SUM(L39:O39) -> 24.358746 | Q39: =K39-P39 -> 10.015772
A40: 46600 | B40: Data & Analytics | C40: =F35 -> 126.46565 | D40: =C40*(Assumptions!$B$29+Assumptions!$B$28)/12 -> 1.2646565 | E40: =C40*Assumptions!$B$29/12 -> 1.0538804 | F40: =C40+D40-E40 -> 126.67642 | G40: =(C40+F40)/2 -> 126.57103 | H40: =G40*Assumptions!C14 -> 106.31967 | I40: =MAX(0,MIN(0.95,Assumptions!D14+Assumptions!$B$30)) -> 0.79 | J40: =Assumptions!E14*(1+Assumptions!$B$31) -> 2472 | K40: =H40*I40*Assumptions!$B$21*J40/1000000 -> 33.220729 | L40: =G40*Assumptions!F14*(1+Assumptions!$B$32) -> 15.94795 | M40: =K40*Assumptions!$B$34 -> 2.4915546 | N40: =G40*(Assumptions!G14*(1+Assumptions!$B$33)+Assumptions!$B$35*(1+Assumptions!$B$33)) -> 2.2377759 | O40: =K40*Assumptions!$B$36*(1+Assumptions!$B$33) -> 1.5547301 | P40: =SUM(L40:O40) -> 22.232011 | Q40: =K40-P40 -> 10.988718
A41: 46600 | B41: Cybersecurity | C41: =F36 -> 96.11389 | D41: =C41*(Assumptions!$B$29+Assumptions!$B$28)/12 -> 0.9611389 | E41: =C41*Assumptions!$B$29/12 -> 0.80094909 | F41: =C41+D41-E41 -> 96.27408 | G41: =(C41+F41)/2 -> 96.193985 | H41: =G41*Assumptions!C15 -> 82.726827 | I41: =MAX(0,MIN(0.95,Assumptions!D15+Assumptions!$B$30)) -> 0.81 | J41: =Assumptions!E15*(1+Assumptions!$B$31) -> 2678 | K41: =H41*I41*Assumptions!$B$21*J41/1000000 -> 28.711901 | L41: =G41*Assumptions!F15*(1+Assumptions!$B$32) -> 13.130479 | M41: =K41*Assumptions!$B$34 -> 2.1533926 | N41: =G41*(Assumptions!G15*(1+Assumptions!$B$33)+Assumptions!$B$35*(1+Assumptions!$B$33)) -> 1.8007514 | O41: =K41*Assumptions!$B$36*(1+Assumptions!$B$33) -> 1.343717 | P41: =SUM(L41:O41) -> 18.42834 | Q41: =K41-P41 -> 10.283561
A42: 46600 | B42: Application Development | C42: =F37 -> 182.11053 | D42: =C42*(Assumptions!$B$29+Assumptions!$B$28)/12 -> 1.8211053 | E42: =C42*Assumptions!$B$29/12 -> 1.5175877 | F42: =C42+D42-E42 -> 182.41405 | G42: =(C42+F42)/2 -> 182.26229 | H42: =G42*Assumptions!C16 -> 145.80983 | I42: =MAX(0,MIN(0.95,Assumptions!D16+Assumptions!$B$30)) -> 0.75 | J42: =Assumptions!E16*(1+Assumptions!$B$31) -> 2163 | K42: =H42*I42*Assumptions!$B$21*J42/1000000 -> 37.8464 | L42: =G42*Assumptions!F16*(1+Assumptions!$B$32) -> 20.094417 | M42: =K42*Assumptions!$B$34 -> 2.83848 | N42: =G42*(Assumptions!G16*(1+Assumptions!$B$33)+Assumptions!$B$35*(1+Assumptions!$B$33)) -> 2.8432917 | O42: =K42*Assumptions!$B$36*(1+Assumptions!$B$33) -> 1.7712115 | P42: =SUM(L42:O42) -> 27.5474 | Q42: =K42-P42 -> 10.298999
A43: 46600 | B43: Managed Services | C43: =F38 -> 156.8174 | D43: =C43*(Assumptions!$B$29+Assumptions!$B$28)/12 -> 1.568174 | E43: =C43*Assumptions!$B$29/12 -> 1.3068117 | F43: =C43+D43-E43 -> 157.07876 | G43: =(C43+F43)/2 -> 156.94808 | H43: =G43*Assumptions!C17 -> 122.4195 | I43: =MAX(0,MIN(0.95,Assumptions!D17+Assumptions!$B$30)) -> 0.73 | J43: =Assumptions!E17*(1+Assumptions!$B$31) -> 2008.5 | K43: =H43*I43*Assumptions!$B$21*J43/1000000 -> 28.718734 | L43: =G43*Assumptions!F17*(1+Assumptions!$B$32) -> 16.479549 | M43: =K43*Assumptions!$B$34 -> 2.1539051 | N43: =G43*(Assumptions!G17*(1+Assumptions!$B$33)+Assumptions!$B$35*(1+Assumptions!$B$33)) -> 2.2851641 | O43: =K43*Assumptions!$B$36*(1+Assumptions!$B$33) -> 1.3440368 | P43: =SUM(L43:O43) -> 22.262654 | Q43: =K43-P43 -> 6.4560797
A44: 46631 | B44: Cloud Services | C44: =F39 -> 146.94465 | D44: =C44*(Assumptions!$B$29+Assumptions!$B$28)/12 -> 1.4694465 | E44: =C44*Assumptions!$B$29/12 -> 1.2245387 | F44: =C44+D44-E44 -> 147.18956 | G44: =(C44+F44)/2 -> 147.0671 | H44: =G44*Assumptions!C13 -> 120.59502 | I44: =MAX(0,MIN(0.95,Assumptions!D13+Assumptions!$B$30)) -> 0.77 | J44: =Assumptions!E13*(1+Assumptions!$B$31) -> 2317.5 | K44: =H44*I44*Assumptions!$B$21*J44/1000000 -> 34.431809 | L44: =G44*Assumptions!F13*(1+Assumptions!$B$32) -> 17.758353 | M44: =K44*Assumptions!$B$34 -> 2.5823857 | N44: =G44*(Assumptions!G13*(1+Assumptions!$B$33)+Assumptions!$B$35*(1+Assumptions!$B$33)) -> 2.4471966 | O44: =K44*Assumptions!$B$36*(1+Assumptions!$B$33) -> 1.6114087 | P44: =SUM(L44:O44) -> 24.399344 | Q44: =K44-P44 -> 10.032465
A45: 46631 | B45: Data & Analytics | C45: =F40 -> 126.67642 | D45: =C45*(Assumptions!$B$29+Assumptions!$B$28)/12 -> 1.2667642 | E45: =C45*Assumptions!$B$29/12 -> 1.0556368 | F45: =C45+D45-E45 -> 126.88755 | G45: =(C45+F45)/2 -> 126.78199 | H45: =G45*Assumptions!C14 -> 106.49687 | I45: =MAX(0,MIN(0.95,Assumptions!D14+Assumptions!$B$30)) -> 0.79 | J45: =Assumptions!E14*(1+Assumptions!$B$31) -> 2472 | K45: =H45*I45*Assumptions!$B$21*J45/1000000 -> 33.276096 | L45: =G45*Assumptions!F14*(1+Assumptions!$B$32) -> 15.97453 | M45: =K45*Assumptions!$B$34 -> 2.4957072 | N45: =G45*(Assumptions!G14*(1+Assumptions!$B$33)+Assumptions!$B$35*(1+Assumptions!$B$33)) -> 2.2415055 | O45: =K45*Assumptions!$B$36*(1+Assumptions!$B$33) -> 1.5573213 | P45: =SUM(L45:O45) -> 22.269064 | Q45: =K45-P45 -> 11.007032
A46: 46631 | B46: Cybersecurity | C46: =F41 -> 96.27408 | D46: =C46*(Assumptions!$B$29+Assumptions!$B$28)/12 -> 0.9627408 | E46: =C46*Assumptions!$B$29/12 -> 0.802284 | F46: =C46+D46-E46 -> 96.434537 | G46: =(C46+F46)/2 -> 96.354309 | H46: =G46*Assumptions!C15 -> 82.864705 | I46: =MAX(0,MIN(0.95,Assumptions!D15+Assumptions!$B$30)) -> 0.81 | J46: =Assumptions!E15*(1+Assumptions!$B$31) -> 2678 | K46: =H46*I46*Assumptions!$B$21*J46/1000000 -> 28.759754 | L46: =G46*Assumptions!F15*(1+Assumptions!$B$32) -> 13.152363 | M46: =K46*Assumptions!$B$34 -> 2.1569815 | N46: =G46*(Assumptions!G15*(1+Assumptions!$B$33)+Assumptions!$B$35*(1+Assumptions!$B$33)) -> 1.8037527 | O46: =K46*Assumptions!$B$36*(1+Assumptions!$B$33) -> 1.3459565 | P46: =SUM(L46:O46) -> 18.459054 | Q46: =K46-P46 -> 10.3007
A47: 46631 | B47: Application Development | C47: =F42 -> 182.41405 | D47: =C47*(Assumptions!$B$29+Assumptions!$B$28)/12 -> 1.8241405 | E47: =C47*Assumptions!$B$29/12 -> 1.5201171 | F47: =C47+D47-E47 -> 182.71807 | G47: =(C47+F47)/2 -> 182.56606 | H47: =G47*Assumptions!C16 -> 146.05285 | I47: =MAX(0,MIN(0.95,Assumptions!D16+Assumptions!$B$30)) -> 0.75 | J47: =Assumptions!E16*(1+Assumptions!$B$31) -> 2163 | K47: =H47*I47*Assumptions!$B$21*J47/1000000 -> 37.909477 | L47: =G47*Assumptions!F16*(1+Assumptions!$B$32) -> 20.127908 | M47: =K47*Assumptions!$B$34 -> 2.8432108 | N47: =G47*(Assumptions!G16*(1+Assumptions!$B$33)+Assumptions!$B$35*(1+Assumptions!$B$33)) -> 2.8480305 | O47: =K47*Assumptions!$B$36*(1+Assumptions!$B$33) -> 1.7741635 | P47: =SUM(L47:O47) -> 27.593313 | Q47: =K47-P47 -> 10.316164
A48: 46631 | B48: Managed Services | C48: =F43 -> 157.07876 | D48: =C48*(Assumptions!$B$29+Assumptions!$B$28)/12 -> 1.5707876 | E48: =C48*Assumptions!$B$29/12 -> 1.3089897 | F48: =C48+D48-E48 -> 157.34056 | G48: =(C48+F48)/2 -> 157.20966 | H48: =G48*Assumptions!C17 -> 122.62354 | I48: =MAX(0,MIN(0.95,Assumptions!D17+Assumptions!$B$30)) -> 0.73 | J48: =Assumptions!E17*(1+Assumptions!$B$31) -> 2008.5 | K48: =H48*I48*Assumptions!$B$21*J48/1000000 -> 28.766599 | L48: =G48*Assumptions!F17*(1+Assumptions!$B$32) -> 16.507014 | M48: =K48*Assumptions!$B$34 -> 2.1574949 | N48: =G48*(Assumptions!G17*(1+Assumptions!$B$33)+Assumptions!$B$35*(1+Assumptions!$B$33)) -> 2.2889727 | O48: =K48*Assumptions!$B$36*(1+Assumptions!$B$33) -> 1.3462768 | P48: =SUM(L48:O48) -> 22.299759 | Q48: =K48-P48 -> 6.4668398
A49: 46661 | B49: Cloud Services | C49: =F44 -> 147.18956 | D49: =C49*(Assumptions!$B$29+Assumptions!$B$28)/12 -> 1.4718956 | E49: =C49*Assumptions!$B$29/12 -> 1.2265796 | F49: =C49+D49-E49 -> 147.43487 | G49: =(C49+F49)/2 -> 147.31221 | H49: =G49*Assumptions!C13 -> 120.79602 | I49: =MAX(0,MIN(0.95,Assumptions!D13+Assumptions!$B$30)) -> 0.77 | J49: =Assumptions!E13*(1+Assumptions!$B$31) -> 2317.5 | K49: =H49*I49*Assumptions!$B$21*J49/1000000 -> 34.489195 | L49: =G49*Assumptions!F13*(1+Assumptions!$B$32) -> 17.78795 | M49: =K49*Assumptions!$B$34 -> 2.5866896 | N49: =G49*(Assumptions!G13*(1+Assumptions!$B$33)+Assumptions!$B$35*(1+Assumptions!$B$33)) -> 2.4512752 | O49: =K49*Assumptions!$B$36*(1+Assumptions!$B$33) -> 1.6140943 | P49: =SUM(L49:O49) -> 24.440009 | Q49: =K49-P49 -> 10.049186
A50: 46661 | B50: Data & Analytics | C50: =F45 -> 126.88755 | D50: =C50*(Assumptions!$B$29+Assumptions!$B$28)/12 -> 1.2688755 | E50: =C50*Assumptions!$B$29/12 -> 1.0573962 | F50: =C50+D50-E50 -> 127.09903 | G50: =(C50+F50)/2 -> 126.99329 | H50: =G50*Assumptions!C14 -> 106.67436 | I50: =MAX(0,MIN(0.95,Assumptions!D14+Assumptions!$B$30)) -> 0.79 | J50: =Assumptions!E14*(1+Assumptions!$B$31) -> 2472 | K50: =H50*I50*Assumptions!$B$21*J50/1000000 -> 33.331557 | L50: =G50*Assumptions!F14*(1+Assumptions!$B$32) -> 16.001154 | M50: =K50*Assumptions!$B$34 -> 2.4998667 | N50: =G50*(Assumptions!G14*(1+Assumptions!$B$33)+Assumptions!$B$35*(1+Assumptions!$B$33)) -> 2.2452413 | O50: =K50*Assumptions!$B$36*(1+Assumptions!$B$33) -> 1.5599168 | P50: =SUM(L50:O50) -> 22.306179 | Q50: =K50-P50 -> 11.025377
A51: 46661 | B51: Cybersecurity | C51: =F46 -> 96.434537 | D51: =C51*(Assumptions!$B$29+Assumptions!$B$28)/12 -> 0.96434537 | E51: =C51*Assumptions!$B$29/12 -> 0.80362114 | F51: =C51+D51-E51 -> 96.595261 | G51: =(C51+F51)/2 -> 96.514899 | H51: =G51*Assumptions!C15 -> 83.002813 | I51: =MAX(0,MIN(0.95,Assumptions!D15+Assumptions!$B$30)) -> 0.81 | J51: =Assumptions!E15*(1+Assumptions!$B$31) -> 2678 | K51: =H51*I51*Assumptions!$B$21*J51/1000000 -> 28.807687 | L51: =G51*Assumptions!F15*(1+Assumptions!$B$32) -> 13.174284 | M51: =K51*Assumptions!$B$34 -> 2.1605765 | N51: =G51*(Assumptions!G15*(1+Assumptions!$B$33)+Assumptions!$B$35*(1+Assumptions!$B$33)) -> 1.8067589 | O51: =K51*Assumptions!$B$36*(1+Assumptions!$B$33) -> 1.3481997 | P51: =SUM(L51:O51) -> 18.489819 | Q51: =K51-P51 -> 10.317868
A52: 46661 | B52: Application Development | C52: =F47 -> 182.71807 | D52: =C52*(Assumptions!$B$29+Assumptions!$B$28)/12 -> 1.8271807 | E52: =C52*Assumptions!$B$29/12 -> 1.5226506 | F52: =C52+D52-E52 -> 183.0226 | G52: =(C52+F52)/2 -> 182.87034 | H52: =G52*Assumptions!C16 -> 146.29627 | I52: =MAX(0,MIN(0.95,Assumptions!D16+Assumptions!$B$30)) -> 0.75 | J52: =Assumptions!E16*(1+Assumptions!$B$31) -> 2163 | K52: =H52*I52*Assumptions!$B$21*J52/1000000 -> 37.972659 | L52: =G52*Assumptions!F16*(1+Assumptions!$B$32) -> 20.161454 | M52: =K52*Assumptions!$B$34 -> 2.8479495 | N52: =G52*(Assumptions!G16*(1+Assumptions!$B$33)+Assumptions!$B$35*(1+Assumptions!$B$33)) -> 2.8527772 | O52: =K52*Assumptions!$B$36*(1+Assumptions!$B$33) -> 1.7771205 | P52: =SUM(L52:O52) -> 27.639302 | Q52: =K52-P52 -> 10.333358
A53: 46661 | B53: Managed Services | C53: =F48 -> 157.34056 | D53: =C53*(Assumptions!$B$29+Assumptions!$B$28)/12 -> 1.5734056 | E53: =C53*Assumptions!$B$29/12 -> 1.3111713 | F53: =C53+D53-E53 -> 157.60279 | G53: =(C53+F53)/2 -> 157.47168 | H53: =G53*Assumptions!C17 -> 122.82791 | I53: =MAX(0,MIN(0.95,Assumptions!D17+Assumptions!$B$30)) -> 0.73 | J53: =Assumptions!E17*(1+Assumptions!$B$31) -> 2008.5 | K53: =H53*I53*Assumptions!$B$21*J53/1000000 -> 28.814543 | L53: =G53*Assumptions!F17*(1+Assumptions!$B$32) -> 16.534526 | M53: =K53*Assumptions!$B$34 -> 2.1610907 | N53: =G53*(Assumptions!G17*(1+Assumptions!$B$33)+Assumptions!$B$35*(1+Assumptions!$B$33)) -> 2.2927876 | O53: =K53*Assumptions!$B$36*(1+Assumptions!$B$33) -> 1.3485206 | P53: =SUM(L53:O53) -> 22.336925 | Q53: =K53-P53 -> 6.4776179
A54: 46692 | B54: Cloud Services | C54: =F49 -> 147.43487 | D54: =C54*(Assumptions!$B$29+Assumptions!$B$28)/12 -> 1.4743487 | E54: =C54*Assumptions!$B$29/12 -> 1.2286239 | F54: =C54+D54-E54 -> 147.6806 | G54: =(C54+F54)/2 -> 147.55773 | H54: =G54*Assumptions!C13 -> 120.99734 | I54: =MAX(0,MIN(0.95,Assumptions!D13+Assumptions!$B$30)) -> 0.77 | J54: =Assumptions!E13*(1+Assumptions!$B$31) -> 2317.5 | K54: =H54*I54*Assumptions!$B$21*J54/1000000 -> 34.546677 | L54: =G54*Assumptions!F13*(1+Assumptions!$B$32) -> 17.817596 | M54: =K54*Assumptions!$B$34 -> 2.5910008 | N54: =G54*(Assumptions!G13*(1+Assumptions!$B$33)+Assumptions!$B$35*(1+Assumptions!$B$33)) -> 2.4553607 | O54: =K54*Assumptions!$B$36*(1+Assumptions!$B$33) -> 1.6167845 | P54: =SUM(L54:O54) -> 24.480742 | Q54: =K54-P54 -> 10.065935
A55: 46692 | B55: Data & Analytics | C55: =F50 -> 127.09903 | D55: =C55*(Assumptions!$B$29+Assumptions!$B$28)/12 -> 1.2709903 | E55: =C55*Assumptions!$B$29/12 -> 1.0591586 | F55: =C55+D55-E55 -> 127.31086 | G55: =(C55+F55)/2 -> 127.20494 | H55: =G55*Assumptions!C14 -> 106.85215 | I55: =MAX(0,MIN(0.95,Assumptions!D14+Assumptions!$B$30)) -> 0.79 | J55: =Assumptions!E14*(1+Assumptions!$B$31) -> 2472 | K55: =H55*I55*Assumptions!$B$21*J55/1000000 -> 33.387109 | L55: =G55*Assumptions!F14*(1+Assumptions!$B$32) -> 16.027823 | M55: =K55*Assumptions!$B$34 -> 2.5040332 | N55: =G55*(Assumptions!G14*(1+Assumptions!$B$33)+Assumptions!$B$35*(1+Assumptions!$B$33)) -> 2.2489834 | O55: =K55*Assumptions!$B$36*(1+Assumptions!$B$33) -> 1.5625167 | P55: =SUM(L55:O55) -> 22.343356 | Q55: =K55-P55 -> 11.043753
A56: 46692 | B56: Cybersecurity | C56: =F51 -> 96.595261 | D56: =C56*(Assumptions!$B$29+Assumptions!$B$28)/12 -> 0.96595261 | E56: =C56*Assumptions!$B$29/12 -> 0.80496051 | F56: =C56+D56-E56 -> 96.756253 | G56: =(C56+F56)/2 -> 96.675757 | H56: =G56*Assumptions!C15 -> 83.141151 | I56: =MAX(0,MIN(0.95,Assumptions!D15+Assumptions!$B$30)) -> 0.81 | J56: =Assumptions!E15*(1+Assumptions!$B$31) -> 2678 | K56: =H56*I56*Assumptions!$B$21*J56/1000000 -> 28.8557 | L56: =G56*Assumptions!F15*(1+Assumptions!$B$32) -> 13.196241 | M56: =K56*Assumptions!$B$34 -> 2.1641775 | N56: =G56*(Assumptions!G15*(1+Assumptions!$B$33)+Assumptions!$B$35*(1+Assumptions!$B$33)) -> 1.8097702 | O56: =K56*Assumptions!$B$36*(1+Assumptions!$B$33) -> 1.3504467 | P56: =SUM(L56:O56) -> 18.520635 | Q56: =K56-P56 -> 10.335064
A57: 46692 | B57: Application Development | C57: =F52 -> 183.0226 | D57: =C57*(Assumptions!$B$29+Assumptions!$B$28)/12 -> 1.830226 | E57: =C57*Assumptions!$B$29/12 -> 1.5251883 | F57: =C57+D57-E57 -> 183.32764 | G57: =(C57+F57)/2 -> 183.17512 | H57: =G57*Assumptions!C16 -> 146.5401 | I57: =MAX(0,MIN(0.95,Assumptions!D16+Assumptions!$B$30)) -> 0.75 | J57: =Assumptions!E16*(1+Assumptions!$B$31) -> 2163 | K57: =H57*I57*Assumptions!$B$21*J57/1000000 -> 38.035947 | L57: =G57*Assumptions!F16*(1+Assumptions!$B$32) -> 20.195057 | M57: =K57*Assumptions!$B$34 -> 2.852696 | N57: =G57*(Assumptions!G16*(1+Assumptions!$B$33)+Assumptions!$B$35*(1+Assumptions!$B$33)) -> 2.8575319 | O57: =K57*Assumptions!$B$36*(1+Assumptions!$B$33) -> 1.7800823 | P57: =SUM(L57:O57) -> 27.685367 | Q57: =K57-P57 -> 10.35058
A58: 46692 | B58: Managed Services | C58: =F53 -> 157.60279 | D58: =C58*(Assumptions!$B$29+Assumptions!$B$28)/12 -> 1.5760279 | E58: =C58*Assumptions!$B$29/12 -> 1.3133566 | F58: =C58+D58-E58 -> 157.86547 | G58: =(C58+F58)/2 -> 157.73413 | H58: =G58*Assumptions!C17 -> 123.03262 | I58: =MAX(0,MIN(0.95,Assumptions!D17+Assumptions!$B$30)) -> 0.73 | J58: =Assumptions!E17*(1+Assumptions!$B$31) -> 2008.5 | K58: =H58*I58*Assumptions!$B$21*J58/1000000 -> 28.862567 | L58: =G58*Assumptions!F17*(1+Assumptions!$B$32) -> 16.562084 | M58: =K58*Assumptions!$B$34 -> 2.1646925 | N58: =G58*(Assumptions!G17*(1+Assumptions!$B$33)+Assumptions!$B$35*(1+Assumptions!$B$33)) -> 2.2966089 | O58: =K58*Assumptions!$B$36*(1+Assumptions!$B$33) -> 1.3507681 | P58: =SUM(L58:O58) -> 22.374153 | Q58: =K58-P58 -> 6.4884139
A59: 46722 | B59: Cloud Services | C59: =F54 -> 147.6806 | D59: =C59*(Assumptions!$B$29+Assumptions!$B$28)/12 -> 1.476806 | E59: =C59*Assumptions!$B$29/12 -> 1.2306716 | F59: =C59+D59-E59 -> 147.92673 | G59: =(C59+F59)/2 -> 147.80366 | H59: =G59*Assumptions!C13 -> 121.199 | I59: =MAX(0,MIN(0.95,Assumptions!D13+Assumptions!$B$30)) -> 0.77 | J59: =Assumptions!E13*(1+Assumptions!$B$31) -> 2317.5 | K59: =H59*I59*Assumptions!$B$21*J59/1000000 -> 34.604255 | L59: =G59*Assumptions!F13*(1+Assumptions!$B$32) -> 17.847292 | M59: =K59*Assumptions!$B$34 -> 2.5953191 | N59: =G59*(Assumptions!G13*(1+Assumptions!$B$33)+Assumptions!$B$35*(1+Assumptions!$B$33)) -> 2.459453 | O59: =K59*Assumptions!$B$36*(1+Assumptions!$B$33) -> 1.6194791 | P59: =SUM(L59:O59) -> 24.521544 | Q59: =K59-P59 -> 10.082711
A60: 46722 | B60: Data & Analytics | C60: =F55 -> 127.31086 | D60: =C60*(Assumptions!$B$29+Assumptions!$B$28)/12 -> 1.2731086 | E60: =C60*Assumptions!$B$29/12 -> 1.0609238 | F60: =C60+D60-E60 -> 127.52304 | G60: =(C60+F60)/2 -> 127.41695 | H60: =G60*Assumptions!C14 -> 107.03024 | I60: =MAX(0,MIN(0.95,Assumptions!D14+Assumptions!$B$30)) -> 0.79 | J60: =Assumptions!E14*(1+Assumptions!$B$31) -> 2472 | K60: =H60*I60*Assumptions!$B$21*J60/1000000 -> 33.442754 | L60: =G60*Assumptions!F14*(1+Assumptions!$B$32) -> 16.054536 | M60: =K60*Assumptions!$B$34 -> 2.5082066 | N60: =G60*(Assumptions!G14*(1+Assumptions!$B$33)+Assumptions!$B$35*(1+Assumptions!$B$33)) -> 2.2527317 | O60: =K60*Assumptions!$B$36*(1+Assumptions!$B$33) -> 1.5651209 | P60: =SUM(L60:O60) -> 22.380595 | Q60: =K60-P60 -> 11.062159
A61: 46722 | B61: Cybersecurity | C61: =F56 -> 96.756253 | D61: =C61*(Assumptions!$B$29+Assumptions!$B$28)/12 -> 0.96756253 | E61: =C61*Assumptions!$B$29/12 -> 0.80630211 | F61: =C61+D61-E61 -> 96.917514 | G61: =(C61+F61)/2 -> 96.836884 | H61: =G61*Assumptions!C15 -> 83.27972 | I61: =MAX(0,MIN(0.95,Assumptions!D15+Assumptions!$B$30)) -> 0.81 | J61: =Assumptions!E15*(1+Assumptions!$B$31) -> 2678 | K61: =H61*I61*Assumptions!$B$21*J61/1000000 -> 28.903792 | L61: =G61*Assumptions!F15*(1+Assumptions!$B$32) -> 13.218235 | M61: =K61*Assumptions!$B$34 -> 2.1677844 | N61: =G61*(Assumptions!G15*(1+Assumptions!$B$33)+Assumptions!$B$35*(1+Assumptions!$B$33)) -> 1.8127865 | O61: =K61*Assumptions!$B$36*(1+Assumptions!$B$33) -> 1.3526975 | P61: =SUM(L61:O61) -> 18.551503 | Q61: =K61-P61 -> 10.352289
A62: 46722 | B62: Application Development | C62: =F57 -> 183.32764 | D62: =C62*(Assumptions!$B$29+Assumptions!$B$28)/12 -> 1.8332764 | E62: =C62*Assumptions!$B$29/12 -> 1.5277303 | F62: =C62+D62-E62 -> 183.63318 | G62: =(C62+F62)/2 -> 183.48041 | H62: =G62*Assumptions!C16 -> 146.78433 | I62: =MAX(0,MIN(0.95,Assumptions!D16+Assumptions!$B$30)) -> 0.75 | J62: =Assumptions!E16*(1+Assumptions!$B$31) -> 2163 | K62: =H62*I62*Assumptions!$B$21*J62/1000000 -> 38.09934 | L62: =G62*Assumptions!F16*(1+Assumptions!$B$32) -> 20.228715 | M62: =K62*Assumptions!$B$34 -> 2.8574505 | N62: =G62*(Assumptions!G16*(1+Assumptions!$B$33)+Assumptions!$B$35*(1+Assumptions!$B$33)) -> 2.8622944 | O62: =K62*Assumptions!$B$36*(1+Assumptions!$B$33) -> 1.7830491 | P62: =SUM(L62:O62) -> 27.731509 | Q62: =K62-P62 -> 10.367831
A63: 46722 | B63: Managed Services | C63: =F58 -> 157.86547 | D63: =C63*(Assumptions!$B$29+Assumptions!$B$28)/12 -> 1.5786547 | E63: =C63*Assumptions!$B$29/12 -> 1.3155456 | F63: =C63+D63-E63 -> 158.12858 | G63: =(C63+F63)/2 -> 157.99702 | H63: =G63*Assumptions!C17 -> 123.23768 | I63: =MAX(0,MIN(0.95,Assumptions!D17+Assumptions!$B$30)) -> 0.73 | J63: =Assumptions!E17*(1+Assumptions!$B$31) -> 2008.5 | K63: =H63*I63*Assumptions!$B$21*J63/1000000 -> 28.910671 | L63: =G63*Assumptions!F17*(1+Assumptions!$B$32) -> 16.589687 | M63: =K63*Assumptions!$B$34 -> 2.1683004 | N63: =G63*(Assumptions!G17*(1+Assumptions!$B$33)+Assumptions!$B$35*(1+Assumptions!$B$33)) -> 2.3004366 | O63: =K63*Assumptions!$B$36*(1+Assumptions!$B$33) -> 1.3530194 | P63: =SUM(L63:O63) -> 22.411444 | Q63: =K63-P63 -> 6.4992279

Sheet Checks
A1: Model Checks
A3: Check | B3: Difference | C3: Tolerance | D3: Status
A4: Forecast revenue: P&L vs Revenue Forecast | B4: =SUM('P&L'!Z4:AK4)-SUM('Revenue Forecast'!I4:I63) -> 0 | C4: 0.01 | D4: =IF(ABS(B4)<=C4,"OK","REVIEW") -> OK
A5: Personnel cost: P&L vs Headcount Plan | B5: =SUM('P&L'!Z5:AK5)-SUM('Headcount Plan'!K4:K63) -> 0 | C5: 0.01 | D5: =IF(ABS(B5)<=C5,"OK","REVIEW") -> OK
A6: Total cost: P&L vs Opex Forecast | B6: =SUM('P&L'!Z5:AK6)+SUM('P&L'!Z9:AK11)-SUM('Opex Forecast'!I4:I15) -> 0 | C6: 0.01 | D6: =IF(ABS(B6)<=C6,"OK","REVIEW") -> OK
A7: Forecast EBITDA: P&L vs Revenue less cost | B7: =SUM('P&L'!Z12:AK12)-(SUM('P&L'!Z4:AK4)-SUM('Opex Forecast'!I4:I15)) -> 0 | C7: 0.01 | D7: =IF(ABS(B7)<=C7,"OK","REVIEW") -> OK
A8: January opening HC vs assumptions | B8: =SUM('Headcount Plan'!C4:C8)-SUM(Assumptions!B13:B17) -> 0 | C8: 0.01 | D8: =IF(ABS(B8)<=C8,"OK","REVIEW") -> OK
A9: Detailed P&L revenue vs consolidated P&L | B9: =SUM('P&L'!Z4:AK4)-SUM('P&L- Detailed View'!Z4:AK4)-SUM('P&L- Detailed View'!Z16:AK16)-SUM('P&L- Detailed View'!Z28:AK28)-SUM('P&L- Detailed View'!Z40:AK40)-SUM('P&L- Detailed View'!Z52:AK52) -> 0 | C9: 0.01 | D9: =IF(ABS(B9)<=C9,"OK","REVIEW") -> OK
