Workbook

Sheet Cover
B3: Integrated 3-Statement Financial Model & DCF Valuation
B4: Portfolio Project | Historical 2023–2025 | Forecast 2026–2030
B6: Rukmini KS — Illustrative IT Services Company (For demonstration)
B7: Model Highlights
B8: • Fully integrated Income Statement, Balance Sheet and Cash Flow
B9: • Driver-based 5-year operating forecast
B10: • Working capital, PP&E and debt schedules
B11: • FCFF DCF with WACC, terminal value and sensitivity analysis
B13: All data is fictional and created for demonstration / learning purposes.

Sheet Assumptions
A1: Forecast & Valuation Assumptions
A3: Operating Assumptions | B3: 2026E | C3: 2027E | D3: 2028E | E3: 2029E | F3: 2030E
A4: Revenue Growth | B4: 0.14 | C4: 0.12 | D4: 0.1 | E4: 0.09 | F4: 0.08
A5: COGS % Revenue | B5: 0.37 | C5: 0.36 | D5: 0.35 | E5: 0.35 | F5: 0.34
A6: OpEx % Revenue | B6: 0.34 | C6: 0.33 | D6: 0.32 | E6: 0.31 | F6: 0.3
A7: D&A % Revenue | B7: 0.04 | C7: 0.04 | D7: 0.04 | E7: 0.04 | F7: 0.04
A8: Tax Rate | B8: 0.25 | C8: 0.25 | D8: 0.25 | E8: 0.25 | F8: 0.25
A9: DSO | B9: 60 | C9: 58 | D9: 56 | E9: 55 | F9: 54 | G9: days
A10: Inventory % Revenue | B10: 0.04 | C10: 0.04 | D10: 0.04 | E10: 0.04 | F10: 0.04
A11: DPO | B11: 75 | C11: 75 | D11: 75 | E11: 75 | F11: 75 | G11: days
A12: Accrued Liab. % Revenue | B12: 0.065 | C12: 0.065 | D12: 0.065 | E12: 0.065 | F12: 0.065
A13: Other Current Assets % Revenue | B13: 0.028 | C13: 0.028 | D13: 0.028 | E13: 0.028 | F13: 0.028
A14: Other Assets % Revenue | B14: 0.045 | C14: 0.045 | D14: 0.045 | E14: 0.045 | F14: 0.045
A15: Other Liabilities % Revenue | B15: 0.035 | C15: 0.035 | D15: 0.035 | E15: 0.035 | F15: 0.035
A16: CapEx % Revenue | B16: 0.065 | C16: 0.06 | D16: 0.055 | E16: 0.05 | F16: 0.05
A17: Debt | B17: 42 | C17: 40 | D17: 37 | E17: 33 | F17: 28 | G17: $mm
A18: Interest Rate | B18: 0.09 | C18: 0.09 | D18: 0.09 | E18: 0.09 | F18: 0.09
A19: Valuation Assumptions
A20: Risk-free Rate | B20: 0.042
A21: Equity Risk Premium | B21: 0.055
A22: Beta | B22: 1.15
A23: Pre-tax Cost of Debt | B23: 0.09
A24: Debt Weight | B24: 0.15
A25: Equity Weight | B25: 0.85
A26: Terminal Growth Rate | B26: 0.03
A27: Shares Outstanding | B27: 25 | C27: million shares

Sheet Historical Data
A1: Historical Financial Data ($mm, except per-share data)
A3: Metric | B3: 2023 | C3: 2024 | D3: 2025
A4: Revenue | B4: 180 | C4: 210 | D4: 250
A5: COGS | B5: -72 | C5: -82 | D5: -95
A6: Operating Expenses | B6: -70 | C6: -78 | D6: -88
A7: D&A | B7: -8 | C7: -9 | D7: -10
A8: Interest Expense | B8: -3 | C8: -3 | D8: -4
A9: Tax Rate | B9: 0.25 | C9: 0.25 | D9: 0.25
A10: Cash | B10: 18 | C10: 22 | D10: 28
A11: Accounts Receivable | B11: 30 | C11: 35 | D11: 42
A12: Inventory | B12: 8 | C12: 9 | D12: 10
A13: Other Current Assets | B13: 5 | C13: 6 | D13: 7
A14: PP&E, Net | B14: 45 | C14: 50 | D14: 57
... A22: CapEx | B22: -12 | C22: -14 | D22: -17

Sheet Revenue Build
A1: Revenue Build ($mm)
A3: Metric | B3: 2023 | C3: 2024 | D3: 2025 | E3: 2026 | F3: 2027 | G3: 2028 | H3: 2029 | I3: 2030
A4: Revenue | B4: ='Historical Data'!B4 -> 180 | C4: ='Historical Data'!C4 -> 210 | D4: ='Historical Data'!D4 -> 250 | E4: =D4*(1+E5) -> 285 | F4: =E4*(1+F5) -> 319.2 | G4: =F4*(1+G5) -> 351.12 | H4: =G4*(1+H5) -> 382.7208 | I4: =H4*(1+I5) -> 413.33846
A5: Growth | B5: - | C5: =C4/B4-1 -> 0.16666667 | D5: =D4/C4-1 -> 0.19047619 | E5: =Assumptions!B4 -> 0.14 | F5: =Assumptions!C4 -> 0.12 | G5: =Assumptions!D4 -> 0.1 | H5: =Assumptions!E4 -> 0.09 | I5: =Assumptions!F4 -> 0.08

Sheet Income Statement
A1: Income Statement ($mm)
A3: Metric | B3: 2023 | C3: 2024 | D3: 2025 | E3: 2026 | F3: 2027 | G3: 2028 | H3: 2029 | I3: 2030
A4: Revenue | B4: ='Historical Data'!B4 -> 180 | C4: ='Historical Data'!C4 -> 210 | D4: ='Historical Data'!D4 -> 250 | E4: ='Revenue Build'!E4 -> 285 | F4: ='Revenue Build'!F4 -> 319.2 | G4: ='Revenue Build'!G4 -> 351.12 | H4: ='Revenue Build'!H4 -> 382.7208 | I4: ='Revenue Build'!I4 -> 413.33846
A5: COGS | B5: ='Historical Data'!B5 -> -72 | C5: ='Historical Data'!C5 -> -82 | D5: ='Historical Data'!D5 -> -95 | E5: =-E4*Assumptions!B5 -> -105.45 | F5: =-F4*Assumptions!C5 -> -114.912 | G5: =-G4*Assumptions!D5 -> -122.892 | H5: =-H4*Assumptions!E5 -> -133.95228 | I5: =-I4*Assumptions!F5 -> -140.53508
A6: Gross Profit | B6: =SUM(B4:B5) -> 108 | C6: =SUM(C4:C5) -> 128 | D6: =SUM(D4:D5) -> 155 | E6: =SUM(E4:E5) -> 179.55 | F6: =SUM(F4:F5) -> 204.288 | G6: =SUM(G4:G5) -> 228.228 | H6: =SUM(H4:H5) -> 248.76852 | I6: =SUM(I4:I5) -> 272.80339
A7: Operating Expenses | B7: ='Historical Data'!B6 -> -70 | C7: ='Historical Data'!C6 -> -78 | D7: ='Historical Data'!D6 -> -88 | E7: =-E4*Assumptions!B6 -> -96.9 | F7: =-F4*Assumptions!C6 -> -105.336 | G7: =-G4*Assumptions!D6 -> -112.3584 | H7: =-H4*Assumptions!E6 -> -118.64345 | I7: =-I4*Assumptions!F6 -> -124.00154
A8: EBITDA | B8: =SUM(B6:B7) -> 38 | C8: =SUM(C6:C7) -> 50 | D8: =SUM(D6:D7) -> 67 | E8: =SUM(E6:E7) -> 82.65 | F8: =SUM(F6:F7) -> 98.952 | G8: =SUM(G6:G7) -> 115.8696 | H8: =SUM(H6:H7) -> 130.12507 | I8: =SUM(I6:I7) -> 148.80185
A9: D&A | B9: ='Historical Data'!B7 -> -8 | C9: ='Historical Data'!C7 -> -9 | D9: ='Historical Data'!D7 -> -10 | E9: =-E4*Assumptions!B7 -> -11.4 | F9: =-F4*Assumptions!C7 -> -12.768 | G9: =-G4*Assumptions!D7 -> -14.0448 | H9: =-H4*Assumptions!E7 -> -15.308832 | I9: =-I4*Assumptions!F7 -> -16.533539
A10: EBIT | B10: =SUM(B8:B9) -> 30 | C10: =SUM(C8:C9) -> 41 | D10: =SUM(D8:D9) -> 57 | E10: =SUM(E8:E9) -> 71.25 | F10: =SUM(F8:F9) -> 86.184 | G10: =SUM(G8:G9) -> 101.8248 | H10: =SUM(H8:H9) -> 114.81624 | I10: =SUM(I8:I9) -> 132.26831
A11: Interest Expense | B11: ='Historical Data'!B8 -> -3 | C11: ='Historical Data'!C8 -> -3 | D11: ='Historical Data'!D8 -> -4 | E11: =-Assumptions!B17*Assumptions!B18 -> -3.78 | F11: =-Assumptions!C17*Assumptions!C18 -> -3.6 | G11: =-Assumptions!D17*Assumptions!D18 -> -3.33 | H11: =-Assumptions!E17*Assumptions!E18 -> -2.97 | I11: =-Assumptions!F17*Assumptions!F18 -> -2.52
A12: EBT | B12: =SUM(B10:B11) -> 27 | C12: =SUM(C10:C11) -> 38 | D12: =SUM(D10:D11) -> 53 | E12: =SUM(E10:E11) -> 67.47 | F12: =SUM(F10:F11) -> 82.584 | G12: =SUM(G10:G11) -> 98.4948 | H12: =SUM(H10:H11) -> 111.84624 | I12: =SUM(I10:I11) -> 129.74831
A13: Taxes | B13: =-MAX(0,B12*'Historical Data'!B9) -> -6.75 | C13: =-MAX(0,C12*'Historical Data'!C9) -> -9.5 | D13: =-MAX(0,D12*'Historical Data'!D9) -> -13.25 | E13: =-MAX(0,E12*Assumptions!B8) -> -16.8675 | F13: =-MAX(0,F12*Assumptions!C8) -> -20.646 | G13: =-MAX(0,G12*Assumptions!D8) -> -24.6237 | H13: =-MAX(0,H12*Assumptions!E8) -> -27.96156 | I13: =-MAX(0,I12*Assumptions!F8) -> -32.437077
A14: Net Income | B14: =SUM(B12:B13) -> 20.25 | C14: =SUM(C12:C13) -> 28.5 | D14: =SUM(D12:D13) -> 39.75 | E14: =SUM(E12:E13) -> 50.6025 | F14: =SUM(F12:F13) -> 61.938 | G14: =SUM(G12:G13) -> 73.8711 | H14: =SUM(H12:H13) -> 83.88468 | I14: =SUM(I12:I13) -> 97.311231

Sheet Balance Sheet
A1: Balance Sheet ($mm)
A3: Metric | B3: 2023 | C3: 2024 | D3: 2025 | E3: 2026 | F3: 2027 | G3: 2028 | H3: 2029 | I3: 2030
A4: Cash | B4: ='Historical Data'!B10 -> 18 | C4: ='Historical Data'!C10 -> 22 | D4: ='Historical Data'!D10 -> 28 | E4: ='Cash Flow'!E20 -> 62.590993 | F4: ='Cash Flow'!F20 -> 113.77176 | G4: ='Cash Flow'!G20 -> 177.45256 | H4: ='Cash Flow'!H20 -> 251.57209 | I4: ='Cash Flow'!I20 -> 337.22335
A5: Accounts Receivable | B5: ='Historical Data'!B11 -> 30 | C5: ='Historical Data'!C11 -> 35 | D5: ='Historical Data'!D11 -> 42 | E5: =Schedules!E4 -> 46.849315 | F5: =Schedules!F4 -> 50.722192 | G5: =Schedules!G4 -> 53.870466 | H5: =Schedules!H4 -> 57.670258 | I5: =Schedules!I4 -> 61.151444
A6: Inventory | B6: ='Historical Data'!B12 -> 8 | C6: ='Historical Data'!C12 -> 9 | D6: ='Historical Data'!D12 -> 10 | E6: =Schedules!E5 -> 11.4 | F6: =Schedules!F5 -> 12.768 | G6: =Schedules!G5 -> 14.0448 | H6: =Schedules!H5 -> 15.308832 | I6: =Schedules!I5 -> 16.533539
A7: Other Current Assets | B7: ='Historical Data'!B13 -> 5 | C7: ='Historical Data'!C13 -> 6 | D7: ='Historical Data'!D13 -> 7 | E7: =Schedules!E6 -> 7.98 | F7: =Schedules!F6 -> 8.9376 | G7: =Schedules!G6 -> 9.83136 | H7: =Schedules!H6 -> 10.716182 | I7: =Schedules!I6 -> 11.573477
A8: Total Current Assets | B8: =SUM(B4:B7) -> 61 | C8: =SUM(C4:C7) -> 72 | D8: =SUM(D4:D7) -> 87 | E8: =SUM(E4:E7) -> 128.82031 | F8: =SUM(F4:F7) -> 186.19955 | G8: =SUM(G4:G7) -> 255.19918 | H8: =SUM(H4:H7) -> 335.26736 | I8: =SUM(I4:I7) -> 426.48181
A9: PP&E, Net | B9: ='Historical Data'!B14 -> 45 | C9: ='Historical Data'!C14 -> 50 | D9: ='Historical Data'!D14 -> 57 | E9: =Schedules!E13 -> 64.125 | F9: =Schedules!F13 -> 70.509 | G9: =Schedules!G13 -> 75.7758 | H9: =Schedules!H13 -> 79.603008 | I9: =Schedules!I13 -> 83.736393
A10: Other Assets | B10: ='Historical Data'!B15 -> 9 | C10: ='Historical Data'!C15 -> 10 | D10: ='Historical Data'!D15 -> 11 | E10: =Schedules!E9 -> 12.825 | F10: =Schedules!F9 -> 14.364 | G10: =Schedules!G9 -> 15.8004 | H10: =Schedules!H9 -> 17.222436 | I10: =Schedules!I9 -> 18.600231
A11: Total Assets | B11: =SUM(B8:B10) -> 115 | C11: =SUM(C8:C10) -> 132 | D11: =SUM(D8:D10) -> 155 | E11: =SUM(E8:E10) -> 205.77031 | F11: =SUM(F8:F10) -> 271.07255 | G11: =SUM(G8:G10) -> 346.77538 | H11: =SUM(H8:H10) -> 432.0928 | I11: =SUM(I8:I10) -> 528.81843
A12: Accounts Payable | B12: ='Historical Data'!B16 -> 18 | C12: ='Historical Data'!C16 -> 21 | D12: ='Historical Data'!D16 -> 25 | E12: =Schedules!E7 -> 21.667808 | F12: =Schedules!F7 -> 23.612055 | G12: =Schedules!G7 -> 25.251781 | H12: =Schedules!H7 -> 27.524441 | I12: =Schedules!I7 -> 28.877071
A13: Accrued Liabilities | B13: ='Historical Data'!B17 -> 12 | C13: ='Historical Data'!C17 -> 14 | D13: ='Historical Data'!D17 -> 16 | E13: =Schedules!E8 -> 18.525 | F13: =Schedules!F8 -> 20.748 | G13: =Schedules!G8 -> 22.8228 | H13: =Schedules!H8 -> 24.876852 | I13: =Schedules!I8 -> 26.867
A14: Debt | B14: ='Historical Data'!B18 -> 35 | C14: ='Historical Data'!C18 -> 38 | D14: ='Historical Data'!D18 -> 42 | E14: =Schedules!E14 -> 42 | F14: =Schedules!F14 -> 40 | G14: =Schedules!G14 -> 37 | H14: =Schedules!H14 -> 33 | I14: =Schedules!I14 -> 28
A15: Other Liabilities | B15: ='Historical Data'!B19 -> 7 | C15: ='Historical Data'!C19 -> 8 | D15: ='Historical Data'!D19 -> 9 | E15: =Schedules!E10 -> 9.975 | F15: =Schedules!F10 -> 11.172 | G15: =Schedules!G10 -> 12.2892 | H15: =Schedules!H10 -> 13.395228 | I15: =Schedules!I10 -> 14.466846
A16: Total Liabilities | B16: =SUM(B12:B15) -> 72 | C16: =SUM(C12:C15) -> 81 | D16: =SUM(D12:D15) -> 92 | E16: =SUM(E12:E15) -> 92.167808 | F16: =SUM(F12:F15) -> 95.532055 | G16: =SUM(G12:G15) -> 97.363781 | H16: =SUM(H12:H15) -> 98.796521 | I16: =SUM(I12:I15) -> 98.210917
A17: Share Capital | B17: ='Historical Data'!B20 -> 40 | C17: ='Historical Data'!C20 -> 40 | D17: ='Historical Data'!D20 -> 40 | E17: =D17 -> 40 | F17: =E17 -> 40 | G17: =F17 -> 40 | H17: =G17 -> 40 | I17: =H17 -> 40
A18: Retained Earnings | B18: ='Historical Data'!B21 -> 3 | C18: ='Historical Data'!C21 -> 11 | D18: ='Historical Data'!D21 -> 23 | E18: =D18+'Income Statement'!E14+'Cash Flow'!E23 -> 73.6025 | F18: =E18+'Income Statement'!F14+'Cash Flow'!F23 -> 135.5405 | G18: =F18+'Income Statement'!G14+'Cash Flow'!G23 -> 209.4116 | H18: =G18+'Income Statement'!H14+'Cash Flow'!H23 -> 293.29628 | I18: =H18+'Income Statement'!I14+'Cash Flow'!I23 -> 390.60751
A19: Total Equity | B19: =SUM(B17:B18) -> 43 | C19: =SUM(C17:C18) -> 51 | D19: =SUM(D17:D18) -> 63 | E19: =SUM(E17:E18) -> 113.6025 | F19: =SUM(F17:F18) -> 175.5405 | G19: =SUM(G17:G18) -> 249.4116 | H19: =SUM(H17:H18) -> 333.29628 | I19: =SUM(I17:I18) -> 430.60751
A20: Total Liabilities & Equity | B20: =SUM(B16,B19) -> 115 | C20: =SUM(C16,C19) -> 132 | D20: =SUM(D16,D19) -> 155 | E20: =SUM(E16,E19) -> 205.77031 | F20: =SUM(F16,F19) -> 271.07255 | G20: =SUM(G16,G19) -> 346.77538 | H20: =SUM(H16,H19) -> 432.0928 | I20: =SUM(I16,I19) -> 528.81843
A21: Balance Check | B21: =B11-B20 -> 0 | C21: =C11-C20 -> 0 | D21: =D11-D20 -> 0 | E21: =E11-E20 -> 0 | F21: =F11-F20 -> 0 | G21: =G11-G20 -> 0 | H21: =H11-H20 -> 0 | I21: =I11-I20 -> 0

Sheet Cash Flow
A1: Cash Flow Statement ($mm)
A3: Metric | B3: 2023 | C3: 2024 | D3: 2025 | E3: 2026 | F3: 2027 | G3: 2028 | H3: 2029 | I3: 2030
A4: Net Income | B4: ='Income Statement'!B14 -> 20.25 | C4: ='Income Statement'!C14 -> 28.5 | D4: ='Income Statement'!D14 -> 39.75 | E4: ='Income Statement'!E14 -> 50.6025 | F4: ='Income Statement'!F14 -> 61.938 | G4: ='Income Statement'!G14 -> 73.8711 | H4: ='Income Statement'!H14 -> 83.88468 | I4: ='Income Statement'!I14 -> 97.311231
A5: D&A | B5: =-Schedules!B12 -> 8 | C5: =-Schedules!C12 -> 9 | D5: =-Schedules!D12 -> 10 | E5: =-Schedules!E12 -> 11.4 | F5: =-Schedules!F12 -> 12.768 | G5: =-Schedules!G12 -> 14.0448 | H5: =-Schedules!H12 -> 15.308832 | I5: =-Schedules!I12 -> 16.533539
A6: Change in A/R | B6: - | C6: =-(Schedules!C4-Schedules!B4) -> -5 | D6: =-(Schedules!D4-Schedules!C4) -> -7 | E6: =-(Schedules!E4-Schedules!D4) -> -4.8493151 | F6: =-(Schedules!F4-Schedules!E4) -> -3.8728767 | G6: =-(Schedules!G4-Schedules!F4) -> -3.148274 | H6: =-(Schedules!H4-Schedules!G4) -> -3.7997918 | I6: =-(Schedules!I4-Schedules!H4) -> -3.4811865
A7: Change in Inventory | B7: - | C7: =-(Schedules!C5-Schedules!B5) -> -1 | D7: =-(Schedules!D5-Schedules!C5) -> -1 | E7: =-(Schedules!E5-Schedules!D5) -> -1.4 | F7: =-(Schedules!F5-Schedules!E5) -> -1.368 | G7: =-(Schedules!G5-Schedules!F5) -> -1.2768 | H7: =-(Schedules!H5-Schedules!G5) -> -1.264032 | I7: =-(Schedules!I5-Schedules!H5) -> -1.2247066
A8: Change in Other Current Assets | B8: - | C8: =-(Schedules!C6-Schedules!B6) -> -1 | D8: =-(Schedules!D6-Schedules!C6) -> -1 | E8: =-(Schedules!E6-Schedules!D6) -> -0.98 | F8: =-(Schedules!F6-Schedules!E6) -> -0.9576 | G8: =-(Schedules!G6-Schedules!F6) -> -0.89376 | H8: =-(Schedules!H6-Schedules!G6) -> -0.8848224 | I8: =-(Schedules!I6-Schedules!H6) -> -0.85729459
A9: Change in A/P | B9: - | C9: =(Schedules!C7-Schedules!B7) -> 3 | D9: =(Schedules!D7-Schedules!C7) -> 4 | E9: =Schedules!E7-Schedules!D7 -> -3.3321918 | F9: =Schedules!F7-Schedules!E7 -> 1.9442466 | G9: =Schedules!G7-Schedules!F7 -> 1.639726 | H9: =Schedules!H7-Schedules!G7 -> 2.2726603 | I9: =Schedules!I7-Schedules!H7 -> 1.3526297
A10: Change in Accrued Liabilities | B10: - | C10: =(Schedules!C8-Schedules!B8) -> 2 | D10: =(Schedules!D8-Schedules!C8) -> 2 | E10: =Schedules!E8-Schedules!D8 -> 2.525 | F10: =Schedules!F8-Schedules!E8 -> 2.223 | G10: =Schedules!G8-Schedules!F8 -> 2.0748 | H10: =Schedules!H8-Schedules!G8 -> 2.054052 | I10: =Schedules!I8-Schedules!H8 -> 1.9901482
A11: Change in Other Assets | B11: - | C11: =-(Schedules!C9-Schedules!B9) -> -1 | D11: =-(Schedules!D9-Schedules!C9) -> -1 | E11: =-(Schedules!E9-Schedules!D9) -> -1.825 | F11: =-(Schedules!F9-Schedules!E9) -> -1.539 | G11: =-(Schedules!G9-Schedules!F9) -> -1.4364 | H11: =-(Schedules!H9-Schedules!G9) -> -1.422036 | I11: =-(Schedules!I9-Schedules!H9) -> -1.3777949
A12: Change in Other Liabilities | B12: - | C12: =(Schedules!C10-Schedules!B10) -> 1 | D12: =(Schedules!D10-Schedules!C10) -> 1 | E12: =Schedules!E10-Schedules!D10 -> 0.975 | F12: =Schedules!F10-Schedules!E10 -> 1.197 | G12: =Schedules!G10-Schedules!F10 -> 1.1172 | H12: =Schedules!H10-Schedules!G10 -> 1.106028 | I12: =Schedules!I10-Schedules!H10 -> 1.0716182
A13: Cash Flow from Operations | B13: - | C13: =SUM(C4:C12) -> 35.5 | D13: =SUM(D4:D12) -> 46.75 | E13: =SUM(E4:E12) -> 53.115993 | F13: =SUM(F4:F12) -> 72.33277 | G13: =SUM(G4:G12) -> 85.992392 | H13: =SUM(H4:H12) -> 97.25557 | I13: =SUM(I4:I12) -> 111.31818
A14: CapEx | B14: =Schedules!B11 -> -12 | C14: =Schedules!C11 -> -14 | D14: =Schedules!D11 -> -17 | E14: =Schedules!E11 -> -18.525 | F14: =Schedules!F11 -> -19.152 | G14: =Schedules!G11 -> -19.3116 | H14: =Schedules!H11 -> -19.13604 | I14: =Schedules!I11 -> -20.666923
A15: Cash Flow from Investing | B15: =B14 -> -12 | C15: =C14 -> -14 | D15: =D14 -> -17 | E15: =E14 -> -18.525 | F15: =F14 -> -19.152 | G15: =G14 -> -19.3116 | H15: =H14 -> -19.13604 | I15: =I14 -> -20.666923
A16: Change in Debt | B16: - | C16: =Schedules!C14-Schedules!B14 -> 3 | D16: =Schedules!D14-Schedules!C14 -> 4 | E16: =Schedules!E14-Schedules!D14 -> 0 | F16: =Schedules!F14-Schedules!E14 -> -2 | G16: =Schedules!G14-Schedules!F14 -> -3 | H16: =Schedules!H14-Schedules!G14 -> -4 | I16: =Schedules!I14-Schedules!H14 -> -5
A17: Cash Flow from Financing | B17: - | C17: =SUM(C16,C23) -> -17.5 | D17: =SUM(D16,D23) -> -23.75 | E17: =SUM(E16,E23) -> 0 | F17: =SUM(F16,F23) -> -2 | G17: =SUM(G16,G23) -> -3 | H17: =SUM(H16,H23) -> -4 | I17: =SUM(I16,I23) -> -5
A18: Net Change in Cash | B18: - | C18: =SUM(C13,C15,C17) -> 4 | D18: =SUM(D13,D15,D17) -> 6 | E18: =SUM(E13,E15,E17) -> 34.590993 | F18: =SUM(F13,F15,F17) -> 51.18077 | G18: =SUM(G13,G15,G17) -> 63.680792 | H18: =SUM(H13,H15,H17) -> 74.11953 | I18: =SUM(I13,I15,I17) -> 85.65126
A19: Beginning Cash | B19: - | C19: ='Balance Sheet'!B4 -> 18 | D19: ='Balance Sheet'!C4 -> 22 | E19: =D20 -> 28 | F19: =E20 -> 62.590993 | G19: =F20 -> 113.77176 | H19: =G20 -> 177.45256 | I19: =H20 -> 251.57209
A20: Ending Cash | B20: 18 | C20: =SUM(C18:C19) -> 22 | D20: =SUM(D18:D19) -> 28 | E20: =SUM(E18:E19) -> 62.590993 | F20: =SUM(F18:F19) -> 113.77176 | G20: =SUM(G18:G19) -> 177.45256 | H20: =SUM(H18:H19) -> 251.57209 | I20: =SUM(I18:I19) -> 337.22335
A23: Dividends / distributions | B23: n.a. | C23: ='Balance Sheet'!C18-'Balance Sheet'!B18-'Income Statement'!C14 -> -20.5 | D23: ='Balance Sheet'!D18-'Balance Sheet'!C18-'Income Statement'!D14 -> -27.75 | E23: 0 | F23: 0 | G23: 0 | H23: 0 | I23: 0
A24: Cash reconciliation | B24: n.a. | C24: =C20-'Balance Sheet'!C4 -> 0 | D24: =D20-'Balance Sheet'!D4 -> 0 | E24: =E20-'Balance Sheet'!E4 -> 0 | F24: =F20-'Balance Sheet'!F4 -> 0 | G24: =G20-'Balance Sheet'!G4 -> 0 | H24: =H20-'Balance Sheet'!H4 -> 0 | I24: =I20-'Balance Sheet'!I4 -> 0
A26: 2024–2025 distributions inferred from retained earnings; no other equity adjustments assumed.
A27: 2023 cash movements unavailable: opening balances were not provided. Forecast distributions assumed zero.

Sheet Schedules
A1: Supporting Schedules ($mm)
A3: Metric | B3: 2023 | C3: 2024 | D3: 2025 | E3: 2026 | F3: 2027 | G3: 2028 | H3: 2029 | I3: 2030
A4: Accounts Receivable | B4: ='Historical Data'!B11 -> 30 | C4: ='Historical Data'!C11 -> 35 | D4: ='Historical Data'!D11 -> 42 | E4: ='Income Statement'!E4/365*Assumptions!B9 -> 46.849315 | F4: ='Income Statement'!F4/365*Assumptions!C9 -> 50.722192 | G4: ='Income Statement'!G4/365*Assumptions!D9 -> 53.870466 | H4: ='Income Statement'!H4/365*Assumptions!E9 -> 57.670258 | I4: ='Income Statement'!I4/365*Assumptions!F9 -> 61.151444
A5: Inventory | B5: ='Historical Data'!B12 -> 8 | C5: ='Historical Data'!C12 -> 9 | D5: ='Historical Data'!D12 -> 10 | E5: ='Income Statement'!E4*Assumptions!B10 -> 11.4 | F5: ='Income Statement'!F4*Assumptions!C10 -> 12.768 | G5: ='Income Statement'!G4*Assumptions!D10 -> 14.0448 | H5: ='Income Statement'!H4*Assumptions!E10 -> 15.308832 | I5: ='Income Statement'!I4*Assumptions!F10 -> 16.533539
A6: Other Current Assets | B6: ='Historical Data'!B13 -> 5 | C6: ='Historical Data'!C13 -> 6 | D6: ='Historical Data'!D13 -> 7 | E6: ='Income Statement'!E4*Assumptions!B13 -> 7.98 | F6: ='Income Statement'!F4*Assumptions!C13 -> 8.9376 | G6: ='Income Statement'!G4*Assumptions!D13 -> 9.83136 | H6: ='Income Statement'!H4*Assumptions!E13 -> 10.716182 | I6: ='Income Statement'!I4*Assumptions!F13 -> 11.573477
A7: Accounts Payable | B7: ='Historical Data'!B16 -> 18 | C7: ='Historical Data'!C16 -> 21 | D7: ='Historical Data'!D16 -> 25 | E7: =-'Income Statement'!E5/365*Assumptions!B11 -> 21.667808 | F7: =-'Income Statement'!F5/365*Assumptions!C11 -> 23.612055 | G7: =-'Income Statement'!G5/365*Assumptions!D11 -> 25.251781 | H7: =-'Income Statement'!H5/365*Assumptions!E11 -> 27.524441 | I7: =-'Income Statement'!I5/365*Assumptions!F11 -> 28.877071
A8: Accrued Liabilities | B8: ='Historical Data'!B17 -> 12 | C8: ='Historical Data'!C17 -> 14 | D8: ='Historical Data'!D17 -> 16 | E8: ='Income Statement'!E4*Assumptions!B12 -> 18.525 | F8: ='Income Statement'!F4*Assumptions!C12 -> 20.748 | G8: ='Income Statement'!G4*Assumptions!D12 -> 22.8228 | H8: ='Income Statement'!H4*Assumptions!E12 -> 24.876852 | I8: ='Income Statement'!I4*Assumptions!F12 -> 26.867
A9: Other Assets | B9: ='Historical Data'!B15 -> 9 | C9: ='Historical Data'!C15 -> 10 | D9: ='Historical Data'!D15 -> 11 | E9: ='Income Statement'!E4*Assumptions!B14 -> 12.825 | F9: ='Income Statement'!F4*Assumptions!C14 -> 14.364 | G9: ='Income Statement'!G4*Assumptions!D14 -> 15.8004 | H9: ='Income Statement'!H4*Assumptions!E14 -> 17.222436 | I9: ='Income Statement'!I4*Assumptions!F14 -> 18.600231
A10: Other Liabilities | B10: ='Historical Data'!B19 -> 7 | C10: ='Historical Data'!C19 -> 8 | D10: ='Historical Data'!D19 -> 9 | E10: ='Income Statement'!E4*Assumptions!B15 -> 9.975 | F10: ='Income Statement'!F4*Assumptions!C15 -> 11.172 | G10: ='Income Statement'!G4*Assumptions!D15 -> 12.2892 | H10: ='Income Statement'!H4*Assumptions!E15 -> 13.395228 | I10: ='Income Statement'!I4*Assumptions!F15 -> 14.466846
A11: CapEx | B11: ='Historical Data'!B22 -> -12 | C11: ='Historical Data'!C22 -> -14 | D11: ='Historical Data'!D22 -> -17 | E11: =-'Income Statement'!E4*Assumptions!B16 -> -18.525 | F11: =-'Income Statement'!F4*Assumptions!C16 -> -19.152 | G11: =-'Income Statement'!G4*Assumptions!D16 -> -19.3116 | H11: =-'Income Statement'!H4*Assumptions!E16 -> -19.13604 | I11: =-'Income Statement'!I4*Assumptions!F16 -> -20.666923
A12: D&A | B12: ='Historical Data'!B7 -> -8 | C12: ='Historical Data'!C7 -> -9 | D12: ='Historical Data'!D7 -> -10 | E12: ='Income Statement'!E9 -> -11.4 | F12: ='Income Statement'!F9 -> -12.768 | G12: ='Income Statement'!G9 -> -14.0448 | H12: ='Income Statement'!H9 -> -15.308832 | I12: ='Income Statement'!I9 -> -16.533539
A13: PP&E, Net | B13: ='Historical Data'!B14 -> 45 | C13: ='Historical Data'!C14 -> 50 | D13: ='Historical Data'!D14 -> 57 | E13: =D13-E11+E12 -> 64.125 | F13: =E13-F11+F12 -> 70.509 | G13: =F13-G11+G12 -> 75.7758 | H13: =G13-H11+H12 -> 79.603008 | I13: =H13-I11+I12 -> 83.736393
A14: Debt | B14: ='Historical Data'!B18 -> 35 | C14: ='Historical Data'!C18 -> 38 | D14: ='Historical Data'!D18 -> 42 | E14: =Assumptions!B17 -> 42 | F14: =Assumptions!C17 -> 40 | G14: =Assumptions!D17 -> 37 | H14: =Assumptions!E17 -> 33 | I14: =Assumptions!F17 -> 28
A15: Interest Expense | B15: ='Historical Data'!B8 -> -3 | C15: ='Historical Data'!C8 -> -3 | D15: ='Historical Data'!D8 -> -4 | E15: ='Income Statement'!E11 -> -3.78 | F15: ='Income Statement'!F11 -> -3.6 | G15: ='Income Statement'!G11 -> -3.33 | H15: ='Income Statement'!H11 -> -2.97 | I15: ='Income Statement'!I11 -> -2.52

Sheet DCF Valuation
A1: DCF Valuation ($mm, except per-share data)
A3: Metric | B3: 2026 | C3: 2027 | D3: 2028 | E3: 2029 | F3: 2030
A4: EBIT | B4: ='Income Statement'!E10 -> 71.25 | C4: ='Income Statement'!F10 -> 86.184 | D4: ='Income Statement'!G10 -> 101.8248 | E4: ='Income Statement'!H10 -> 114.81624 | F4: ='Income Statement'!I10 -> 132.26831
A5: Tax Rate | B5: =Assumptions!B8 -> 0.25 | C5: =Assumptions!C8 -> 0.25 | D5: =Assumptions!D8 -> 0.25 | E5: =Assumptions!E8 -> 0.25 | F5: =Assumptions!F8 -> 0.25
A6: NOPAT | B6: =B4*(1-B5) -> 53.4375 | C6: =C4*(1-C5) -> 64.638 | D6: =D4*(1-D5) -> 76.3686 | E6: =E4*(1-E5) -> 86.11218 | F6: =F4*(1-F5) -> 99.201231
A7: D&A | B7: =-Schedules!E12 -> 11.4 | C7: =-Schedules!F12 -> 12.768 | D7: =-Schedules!G12 -> 14.0448 | E7: =-Schedules!H12 -> 15.308832 | F7: =-Schedules!I12 -> 16.533539
A8: CapEx | B8: =Schedules!E11 -> -18.525 | C8: =Schedules!F11 -> -19.152 | D8: =Schedules!G11 -> -19.3116 | E8: =Schedules!H11 -> -19.13604 | F8: =Schedules!I11 -> -20.666923
A9: Change in operating assets / liabilities | B9: =SUM('Cash Flow'!E6:E12) -> -8.8865068 | C9: =SUM('Cash Flow'!F6:F12) -> -2.3732301 | D9: =SUM('Cash Flow'!G6:G12) -> -1.9235079 | E9: =SUM('Cash Flow'!H6:H12) -> -1.9379419 | F9: =SUM('Cash Flow'!I6:I12) -> -2.5265864
A10: FCFF | B10: =SUM(B6:B9) -> 37.425993 | C10: =SUM(C6:C9) -> 55.88077 | D10: =SUM(D6:D9) -> 69.178292 | E10: =SUM(E6:E9) -> 80.34703 | F10: =SUM(F6:F9) -> 92.54126
A11: Discount Period | B11: 1 | C11: 2 | D11: 3 | E11: 4 | F11: 5
A12: Discount Factor | B12: =1/(1+$B$16)^B11 -> 0.90943195 | C12: =1/(1+$B$16)^C11 -> 0.82706646 | D12: =1/(1+$B$16)^D11 -> 0.75216066 | E12: =1/(1+$B$16)^E11 -> 0.68403894 | F12: =1/(1+$B$16)^F11 -> 0.62208686
A13: PV of FCFF | B13: =B10*B12 -> 34.036394 | C13: =C10*C12 -> 46.217111 | D13: =D10*D12 -> 52.03319 | E13: =E10*E12 -> 54.960497 | F13: =F10*F12 -> 57.568702
A15: Valuation Summary | B15: Value
A16: WACC | B16: =Assumptions!B25*(Assumptions!B20+Assumptions!B22*Assumptions!B21)+Assumptions!B24*Assumptions!B23*(1-Assumptions!B8) -> 0.0995875
A17: Terminal Growth Rate | B17: =Assumptions!B26 -> 0.03
A18: Terminal Value | B18: =F10*(1+B17)/(B16-B17) -> 1369.7503
A19: PV of Terminal Value | B19: =B18*F12 -> 852.10366
A20: PV of Forecast FCFF | B20: =SUM(B13:F13) -> 244.81589
A21: Enterprise Value | B21: =SUM(B19:B20) -> 1096.9196
A22: Less: Debt | B22: ='Balance Sheet'!D14 -> 42
A23: Add: Cash | B23: ='Balance Sheet'!D4 -> 28
A24: Equity Value | B24: =SUM(B21,-B22,B23) -> 1082.9196
A25: Shares Outstanding (millions) | B25: =Assumptions!B27 -> 25
A26: Implied Value / Share | B26: =B24/B25 -> 43.316782
A29: DCF Sensitivity — Implied Value / Share ($)
A32: Terminal Growth / WACC | B32: 0.08 | C32: 0.09 | D32: 0.1 | E32: 0.11 | F32: 0.12 | G32: 0.13
A33: 0.02 | B33: =('DCF Valuation'!$B$10/(1+B$32)^1+'DCF Valuation'!$C$10/(1+B$32)^2+'DCF Valuation'!$D$10/(1+B$32)^3+'DCF Valuation'!$E$10/(1+B$32)^4+'DCF Valuation'!$F$10/(1+B$32)^5+('DCF Valuation'!$F$10*(1+$A33)/(B$32-$A33))/(1+B$32)^5-'DCF Valuation'!$B$22+'DCF Valuation'!$B$23)/'DCF Valuation'!$B$25 -> 52.648494 | C33: =('DCF Valuation'!$B$10/(1+C$32)^1+'DCF Valuation'!$C$10/(1+C$32)^2+'DCF Valuation'!$D$10/(1+C$32)^3+'DCF Valuation'!$E$10/(1+C$32)^4+'DCF Valuation'!$F$10/(1+C$32)^5+('DCF Valuation'!$F$10*(1+$A33)/(C$32-$A33))/(1+C$32)^5-'DCF Valuation'!$B$22+'DCF Valuation'!$B$23)/'DCF Valuation'!$B$25 -> 44.570343 | D33: =('DCF Valuation'!$B$10/(1+D$32)^1+'DCF Valuation'!$C$10/(1+D$32)^2+'DCF Valuation'!$D$10/(1+D$32)^3+'DCF Valuation'!$E$10/(1+D$32)^4+'DCF Valuation'!$F$10/(1+D$32)^5+('DCF Valuation'!$F$10*(1+$A33)/(D$32-$A33))/(1+D$32)^5-'DCF Valuation'!$B$22+'DCF Valuation'!$B$23)/'DCF Valuation'!$B$25 -> 38.525817 | E33: =('DCF Valuation'!$B$10/(1+E$32)^1+'DCF Valuation'!$C$10/(1+E$32)^2+'DCF Valuation'!$D$10/(1+E$32)^3+'DCF Valuation'!$E$10/(1+E$32)^4+'DCF Valuation'!$F$10/(1+E$32)^5+('DCF Valuation'!$F$10*(1+$A33)/(E$32-$A33))/(1+E$32)^5-'DCF Valuation'!$B$22+'DCF Valuation'!$B$23)/'DCF Valuation'!$B$25 -> 33.836476 | F33: =('DCF Valuation'!$B$10/(1+F$32)^1+'DCF Valuation'!$C$10/(1+F$32)^2+'DCF Valuation'!$D$10/(1+F$32)^3+'DCF Valuation'!$E$10/(1+F$32)^4+'DCF Valuation'!$F$10/(1+F$32)^5+('DCF Valuation'!$F$10*(1+$A33)/(F$32-$A33))/(1+F$32)^5-'DCF Valuation'!$B$22+'DCF Valuation'!$B$23)/'DCF Valuation'!$B$25 -> 30.095282 | G33: =('DCF Valuation'!$B$10/(1+G$32)^1+'DCF Valuation'!$C$10/(1+G$32)^2+'DCF Valuation'!$D$10/(1+G$32)^3+'DCF Valuation'!$E$10/(1+G$32)^4+'DCF Valuation'!$F$10/(1+G$32)^5+('DCF Valuation'!$F$10*(1+$A33)/(G$32-$A33))/(1+G$32)^5-'DCF Valuation'!$B$22+'DCF Valuation'!$B$23)/'DCF Valuation'!$B$25 -> 27.043236
A34: 0.025 | B34: =('DCF Valuation'!$B$10/(1+B$32)^1+'DCF Valuation'!$C$10/(1+B$32)^2+'DCF Valuation'!$D$10/(1+B$32)^3+'DCF Valuation'!$E$10/(1+B$32)^4+'DCF Valuation'!$F$10/(1+B$32)^5+('DCF Valuation'!$F$10*(1+$A34)/(B$32-$A34))/(1+B$32)^5-'DCF Valuation'!$B$22+'DCF Valuation'!$B$23)/'DCF Valuation'!$B$25 -> 56.770954 | C34: =('DCF Valuation'!$B$10/(1+C$32)^1+'DCF Valuation'!$C$10/(1+C$32)^2+'DCF Valuation'!$D$10/(1+C$32)^3+'DCF Valuation'!$E$10/(1+C$32)^4+'DCF Valuation'!$F$10/(1+C$32)^5+('DCF Valuation'!$F$10*(1+$A34)/(C$32-$A34))/(1+C$32)^5-'DCF Valuation'!$B$22+'DCF Valuation'!$B$23)/'DCF Valuation'!$B$25 -> 47.452038 | D34: =('DCF Valuation'!$B$10/(1+D$32)^1+'DCF Valuation'!$C$10/(1+D$32)^2+'DCF Valuation'!$D$10/(1+D$32)^3+'DCF Valuation'!$E$10/(1+D$32)^4+'DCF Valuation'!$F$10/(1+D$32)^5+('DCF Valuation'!$F$10*(1+$A34)/(D$32-$A34))/(1+D$32)^5-'DCF Valuation'!$B$22+'DCF Valuation'!$B$23)/'DCF Valuation'!$B$25 -> 40.632715 | E34: =('DCF Valuation'!$B$10/(1+E$32)^1+'DCF Valuation'!$C$10/(1+E$32)^2+'DCF Valuation'!$D$10/(1+E$32)^3+'DCF Valuation'!$E$10/(1+E$32)^4+'DCF Valuation'!$F$10/(1+E$32)^5+('DCF Valuation'!$F$10*(1+$A34)/(E$32-$A34))/(1+E$32)^5-'DCF Valuation'!$B$22+'DCF Valuation'!$B$23)/'DCF Valuation'!$B$25 -> 35.430196 | F34: =('DCF Valuation'!$B$10/(1+F$32)^1+'DCF Valuation'!$C$10/(1+F$32)^2+'DCF Valuation'!$D$10/(1+F$32)^3+'DCF Valuation'!$E$10/(1+F$32)^4+'DCF Valuation'!$F$10/(1+F$32)^5+('DCF Valuation'!$F$10*(1+$A34)/(F$32-$A34))/(1+F$32)^5-'DCF Valuation'!$B$22+'DCF Valuation'!$B$23)/'DCF Valuation'!$B$25 -> 31.333422 | G34: =('DCF Valuation'!$B$10/(1+G$32)^1+'DCF Valuation'!$C$10/(1+G$32)^2+'DCF Valuation'!$D$10/(1+G$32)^3+'DCF Valuation'!$E$10/(1+G$32)^4+'DCF Valuation'!$F$10/(1+G$32)^5+('DCF Valuation'!$F$10*(1+$A34)/(G$32-$A34))/(1+G$32)^5-'DCF Valuation'!$B$22+'DCF Valuation'!$B$23)/'DCF Valuation'!$B$25 -> 28.026046
A35: 0.03 | B35: =('DCF Valuation'!$B$10/(1+B$32)^1+'DCF Valuation'!$C$10/(1+B$32)^2+'DCF Valuation'!$D$10/(1+B$32)^3+'DCF Valuation'!$E$10/(1+B$32)^4+'DCF Valuation'!$F$10/(1+B$32)^5+('DCF Valuation'!$F$10*(1+$A35)/(B$32-$A35))/(1+B$32)^5-'DCF Valuation'!$B$22+'DCF Valuation'!$B$23)/'DCF Valuation'!$B$25 -> 61.717906 | C35: =('DCF Valuation'!$B$10/(1+C$32)^1+'DCF Valuation'!$C$10/(1+C$32)^2+'DCF Valuation'!$D$10/(1+C$32)^3+'DCF Valuation'!$E$10/(1+C$32)^4+'DCF Valuation'!$F$10/(1+C$32)^5+('DCF Valuation'!$F$10*(1+$A35)/(C$32-$A35))/(1+C$32)^5-'DCF Valuation'!$B$22+'DCF Valuation'!$B$23)/'DCF Valuation'!$B$25 -> 50.814016 | D35: =('DCF Valuation'!$B$10/(1+D$32)^1+'DCF Valuation'!$C$10/(1+D$32)^2+'DCF Valuation'!$D$10/(1+D$32)^3+'DCF Valuation'!$E$10/(1+D$32)^4+'DCF Valuation'!$F$10/(1+D$32)^5+('DCF Valuation'!$F$10*(1+$A35)/(D$32-$A35))/(1+D$32)^5-'DCF Valuation'!$B$22+'DCF Valuation'!$B$23)/'DCF Valuation'!$B$25 -> 43.040598 | E35: =('DCF Valuation'!$B$10/(1+E$32)^1+'DCF Valuation'!$C$10/(1+E$32)^2+'DCF Valuation'!$D$10/(1+E$32)^3+'DCF Valuation'!$E$10/(1+E$32)^4+'DCF Valuation'!$F$10/(1+E$32)^5+('DCF Valuation'!$F$10*(1+$A35)/(E$32-$A35))/(1+E$32)^5-'DCF Valuation'!$B$22+'DCF Valuation'!$B$23)/'DCF Valuation'!$B$25 -> 37.223131 | F35: =('DCF Valuation'!$B$10/(1+F$32)^1+'DCF Valuation'!$C$10/(1+F$32)^2+'DCF Valuation'!$D$10/(1+F$32)^3+'DCF Valuation'!$E$10/(1+F$32)^4+'DCF Valuation'!$F$10/(1+F$32)^5+('DCF Valuation'!$F$10*(1+$A35)/(F$32-$A35))/(1+F$32)^5-'DCF Valuation'!$B$22+'DCF Valuation'!$B$23)/'DCF Valuation'!$B$25 -> 32.709133 | G35: =('DCF Valuation'!$B$10/(1+G$32)^1+'DCF Valuation'!$C$10/(1+G$32)^2+'DCF Valuation'!$D$10/(1+G$32)^3+'DCF Valuation'!$E$10/(1+G$32)^4+'DCF Valuation'!$F$10/(1+G$32)^5+('DCF Valuation'!$F$10*(1+$A35)/(G$32-$A35))/(1+G$32)^5-'DCF Valuation'!$B$22+'DCF Valuation'!$B$23)/'DCF Valuation'!$B$25 -> 29.107137
A36: 0.035 | B36: =('DCF Valuation'!$B$10/(1+B$32)^1+'DCF Valuation'!$C$10/(1+B$32)^2+'DCF Valuation'!$D$10/(1+B$32)^3+'DCF Valuation'!$E$10/(1+B$32)^4+'DCF Valuation'!$F$10/(1+B$32)^5+('DCF Valuation'!$F$10*(1+$A36)/(B$32-$A36))/(1+B$32)^5-'DCF Valuation'!$B$22+'DCF Valuation'!$B$23)/'DCF Valuation'!$B$25 -> 67.764181 | C36: =('DCF Valuation'!$B$10/(1+C$32)^1+'DCF Valuation'!$C$10/(1+C$32)^2+'DCF Valuation'!$D$10/(1+C$32)^3+'DCF Valuation'!$E$10/(1+C$32)^4+'DCF Valuation'!$F$10/(1+C$32)^5+('DCF Valuation'!$F$10*(1+$A36)/(C$32-$A36))/(1+C$32)^5-'DCF Valuation'!$B$22+'DCF Valuation'!$B$23)/'DCF Valuation'!$B$25 -> 54.787262 | D36: =('DCF Valuation'!$B$10/(1+D$32)^1+'DCF Valuation'!$C$10/(1+D$32)^2+'DCF Valuation'!$D$10/(1+D$32)^3+'DCF Valuation'!$E$10/(1+D$32)^4+'DCF Valuation'!$F$10/(1+D$32)^5+('DCF Valuation'!$F$10*(1+$A36)/(D$32-$A36))/(1+D$32)^5-'DCF Valuation'!$B$22+'DCF Valuation'!$B$23)/'DCF Valuation'!$B$25 -> 45.818924 | E36: =('DCF Valuation'!$B$10/(1+E$32)^1+'DCF Valuation'!$C$10/(1+E$32)^2+'DCF Valuation'!$D$10/(1+E$32)^3+'DCF Valuation'!$E$10/(1+E$32)^4+'DCF Valuation'!$F$10/(1+E$32)^5+('DCF Valuation'!$F$10*(1+$A36)/(E$32-$A36))/(1+E$32)^5-'DCF Valuation'!$B$22+'DCF Valuation'!$B$23)/'DCF Valuation'!$B$25 -> 39.255124 | F36: =('DCF Valuation'!$B$10/(1+F$32)^1+'DCF Valuation'!$C$10/(1+F$32)^2+'DCF Valuation'!$D$10/(1+F$32)^3+'DCF Valuation'!$E$10/(1+F$32)^4+'DCF Valuation'!$F$10/(1+F$32)^5+('DCF Valuation'!$F$10*(1+$A36)/(F$32-$A36))/(1+F$32)^5-'DCF Valuation'!$B$22+'DCF Valuation'!$B$23)/'DCF Valuation'!$B$25 -> 34.246692 | G36: =('DCF Valuation'!$B$10/(1+G$32)^1+'DCF Valuation'!$C$10/(1+G$32)^2+'DCF Valuation'!$D$10/(1+G$32)^3+'DCF Valuation'!$E$10/(1+G$32)^4+'DCF Valuation'!$F$10/(1+G$32)^5+('DCF Valuation'!$F$10*(1+$A36)/(G$32-$A36))/(1+G$32)^5-'DCF Valuation'!$B$22+'DCF Valuation'!$B$23)/'DCF Valuation'!$B$25 -> 30.302028
A37: 0.04 | B37: =('DCF Valuation'!$B$10/(1+B$32)^1+'DCF Valuation'!$C$10/(1+B$32)^2+'DCF Valuation'!$D$10/(1+B$32)^3+'DCF Valuation'!$E$10/(1+B$32)^4+'DCF Valuation'!$F$10/(1+B$32)^5+('DCF Valuation'!$F$10*(1+$A37)/(B$32-$A37))/(1+B$32)^5-'DCF Valuation'!$B$22+'DCF Valuation'!$B$23)/'DCF Valuation'!$B$25 -> 75.322024 | C37: =('DCF Valuation'!$B$10/(1+C$32)^1+'DCF Valuation'!$C$10/(1+C$32)^2+'DCF Valuation'!$D$10/(1+C$32)^3+'DCF Valuation'!$E$10/(1+C$32)^4+'DCF Valuation'!$F$10/(1+C$32)^5+('DCF Valuation'!$F$10*(1+$A37)/(C$32-$A37))/(1+C$32)^5-'DCF Valuation'!$B$22+'DCF Valuation'!$B$23)/'DCF Valuation'!$B$25 -> 59.555157 | D37: =('DCF Valuation'!$B$10/(1+D$32)^1+'DCF Valuation'!$C$10/(1+D$32)^2+'DCF Valuation'!$D$10/(1+D$32)^3+'DCF Valuation'!$E$10/(1+D$32)^4+'DCF Valuation'!$F$10/(1+D$32)^5+('DCF Valuation'!$F$10*(1+$A37)/(D$32-$A37))/(1+D$32)^5-'DCF Valuation'!$B$22+'DCF Valuation'!$B$23)/'DCF Valuation'!$B$25 -> 49.060305 | E37: =('DCF Valuation'!$B$10/(1+E$32)^1+'DCF Valuation'!$C$10/(1+E$32)^2+'DCF Valuation'!$D$10/(1+E$32)^3+'DCF Valuation'!$E$10/(1+E$32)^4+'DCF Valuation'!$F$10/(1+E$32)^5+('DCF Valuation'!$F$10*(1+$A37)/(E$32-$A37))/(1+E$32)^5-'DCF Valuation'!$B$22+'DCF Valuation'!$B$23)/'DCF Valuation'!$B$25 -> 41.577402 | F37: =('DCF Valuation'!$B$10/(1+F$32)^1+'DCF Valuation'!$C$10/(1+F$32)^2+'DCF Valuation'!$D$10/(1+F$32)^3+'DCF Valuation'!$E$10/(1+F$32)^4+'DCF Valuation'!$F$10/(1+F$32)^5+('DCF Valuation'!$F$10*(1+$A37)/(F$32-$A37))/(1+F$32)^5-'DCF Valuation'!$B$22+'DCF Valuation'!$B$23)/'DCF Valuation'!$B$25 -> 35.976446 | G37: =('DCF Valuation'!$B$10/(1+G$32)^1+'DCF Valuation'!$C$10/(1+G$32)^2+'DCF Valuation'!$D$10/(1+G$32)^3+'DCF Valuation'!$E$10/(1+G$32)^4+'DCF Valuation'!$F$10/(1+G$32)^5+('DCF Valuation'!$F$10*(1+$A37)/(G$32-$A37))/(1+G$32)^5-'DCF Valuation'!$B$22+'DCF Valuation'!$B$23)/'DCF Valuation'!$B$25 -> 31.629683
A39: Valuation date: 31 Dec 2025. Year-end discounting; perpetual-growth terminal value.
A40: Other assets and liabilities treated as operating. Interest uses year-end debt; no forecast dividends.

Sheet Dashboard
A1: Valuation & Financial Dashboard
A3: Key KPI | B3: Value
A4: 2025 Revenue ($mm) | B4: ='Income Statement'!D4 -> 250
A5: 2030 Revenue ($mm) | B5: ='Income Statement'!I4 -> 413.33846
A6: 2030 EBITDA Margin | B6: ='Income Statement'!I8/'Income Statement'!I4 -> 0.36
A7: Enterprise Value ($mm) | B7: ='DCF Valuation'!B21 -> 1096.9196
A8: Implied Value / Share ($) | B8: ='DCF Valuation'!B26 -> 43.316782
A11: Metric | B11: 2026 | C11: 2027 | D11: 2028 | E11: 2029 | F11: 2030
A12: Revenue | B12: ='Income Statement'!E4 -> 285 | C12: ='Income Statement'!F4 -> 319.2 | D12: ='Income Statement'!G4 -> 351.12 | E12: ='Income Statement'!H4 -> 382.7208 | F12: ='Income Statement'!I4 -> 413.33846
A13: EBITDA | B13: ='Income Statement'!E8 -> 82.65 | C13: ='Income Statement'!F8 -> 98.952 | D13: ='Income Statement'!G8 -> 115.8696 | E13: ='Income Statement'!H8 -> 130.12507 | F13: ='Income Statement'!I8 -> 148.80185
A14: FCFF | B14: ='DCF Valuation'!B10 -> 37.425993 | C14: ='DCF Valuation'!C10 -> 55.88077 | D14: ='DCF Valuation'!D10 -> 69.178292 | E14: ='DCF Valuation'!E10 -> 80.34703 | F14: ='DCF Valuation'!F10 -> 92.54126
